assignment3/mux/m4x1.v
module m4x1(
    input en ,
    input [1:0] s ,
    input [3:0] i ,
    output y
);

    assign y = en?(s[1]?(s[0]?i[3]:i[2]):(s[0]?i[1]:i[0])):0;

endmodule

assignment3/mux/m4x1tb.v
`timescale 1ns/1ps
module m4x1tb;

    reg en;
    reg [1:0] s;
    reg [3:0] i;
    wire y;

    m4x1 mux(
        .en(en) , .s(s) , .i(i) , .y(y)
    );
    integer z;
    initial begin
        $dumpfile("m4x1v.vcd");
        $dumpvars(0 , m4x1tb);
        for (z = 0; z<128; z=z+1) begin
            {s , i , en} =z;
            #1;
        end
        $finish;
    end
endmodule

assignment3/mux/m4x1v.vcd
$date
	Thu Jun 05 21:15:36 2025
$end
$version
	Icarus Verilog
$end
$timescale
	1ps
$end
$scope module m4x1tb $end
$var wire 1 ! y $end
$var reg 1 " en $end
$var reg 4 # i [3:0] $end
$var reg 2 $ s [1:0] $end
$var integer 32 % z [31:0] $end
$scope module mux $end
$var wire 1 " en $end
$var wire 4 & i [3:0] $end
$var wire 2 ' s [1:0] $end
$var wire 1 ! y $end
$upscope $end
$upscope $end
$enddefinitions $end
$comment Show the parameter values. $end
$dumpall
$end
#0
$dumpvars
b0 '
b0 &
b0 %
b0 $
b0 #
0"
0!
$end
#1000
1"
b1 %
#2000
b1 #
b1 &
0"
b10 %
#3000
1!
1"
b11 %
#4000
0!
b10 #
b10 &
0"
b100 %
#5000
1"
b101 %
#6000
b11 #
b11 &
0"
b110 %
#7000
1!
1"
b111 %
#8000
0!
b100 #
b100 &
0"
b1000 %
#9000
1"
b1001 %
#10000
b101 #
b101 &
0"
b1010 %
#11000
1!
1"
b1011 %
#12000
0!
b110 #
b110 &
0"
b1100 %
#13000
1"
b1101 %
#14000
b111 #
b111 &
0"
b1110 %
#15000
1!
1"
b1111 %
#16000
0!
b1000 #
b1000 &
0"
b10000 %
#17000
1"
b10001 %
#18000
b1001 #
b1001 &
0"
b10010 %
#19000
1!
1"
b10011 %
#20000
0!
b1010 #
b1010 &
0"
b10100 %
#21000
1"
b10101 %
#22000
b1011 #
b1011 &
0"
b10110 %
#23000
1!
1"
b10111 %
#24000
0!
b1100 #
b1100 &
0"
b11000 %
#25000
1"
b11001 %
#26000
b1101 #
b1101 &
0"
b11010 %
#27000
1!
1"
b11011 %
#28000
0!
b1110 #
b1110 &
0"
b11100 %
#29000
1"
b11101 %
#30000
b1111 #
b1111 &
0"
b11110 %
#31000
1!
1"
b11111 %
#32000
0!
b1 $
b1 '
b0 #
b0 &
0"
b100000 %
#33000
1"
b100001 %
#34000
b1 #
b1 &
0"
b100010 %
#35000
1"
b100011 %
#36000
b10 #
b10 &
0"
b100100 %
#37000
1!
1"
b100101 %
#38000
0!
b11 #
b11 &
0"
b100110 %
#39000
1!
1"
b100111 %
#40000
0!
b100 #
b100 &
0"
b101000 %
#41000
1"
b101001 %
#42000
b101 #
b101 &
0"
b101010 %
#43000
1"
b101011 %
#44000
b110 #
b110 &
0"
b101100 %
#45000
1!
1"
b101101 %
#46000
0!
b111 #
b111 &
0"
b101110 %
#47000
1!
1"
b101111 %
#48000
0!
b1000 #
b1000 &
0"
b110000 %
#49000
1"
b110001 %
#50000
b1001 #
b1001 &
0"
b110010 %
#51000
1"
b110011 %
#52000
b1010 #
b1010 &
0"
b110100 %
#53000
1!
1"
b110101 %
#54000
0!
b1011 #
b1011 &
0"
b110110 %
#55000
1!
1"
b110111 %
#56000
0!
b1100 #
b1100 &
0"
b111000 %
#57000
1"
b111001 %
#58000
b1101 #
b1101 &
0"
b111010 %
#59000
1"
b111011 %
#60000
b1110 #
b1110 &
0"
b111100 %
#61000
1!
1"
b111101 %
#62000
0!
b1111 #
b1111 &
0"
b111110 %
#63000
1!
1"
b111111 %
#64000
0!
b10 $
b10 '
b0 #
b0 &
0"
b1000000 %
#65000
1"
b1000001 %
#66000
b1 #
b1 &
0"
b1000010 %
#67000
1"
b1000011 %
#68000
b10 #
b10 &
0"
b1000100 %
#69000
1"
b1000101 %
#70000
b11 #
b11 &
0"
b1000110 %
#71000
1"
b1000111 %
#72000
b100 #
b100 &
0"
b1001000 %
#73000
1!
1"
b1001001 %
#74000
0!
b101 #
b101 &
0"
b1001010 %
#75000
1!
1"
b1001011 %
#76000
0!
b110 #
b110 &
0"
b1001100 %
#77000
1!
1"
b1001101 %
#78000
0!
b111 #
b111 &
0"
b1001110 %
#79000
1!
1"
b1001111 %
#80000
0!
b1000 #
b1000 &
0"
b1010000 %
#81000
1"
b1010001 %
#82000
b1001 #
b1001 &
0"
b1010010 %
#83000
1"
b1010011 %
#84000
b1010 #
b1010 &
0"
b1010100 %
#85000
1"
b1010101 %
#86000
b1011 #
b1011 &
0"
b1010110 %
#87000
1"
b1010111 %
#88000
b1100 #
b1100 &
0"
b1011000 %
#89000
1!
1"
b1011001 %
#90000
0!
b1101 #
b1101 &
0"
b1011010 %
#91000
1!
1"
b1011011 %
#92000
0!
b1110 #
b1110 &
0"
b1011100 %
#93000
1!
1"
b1011101 %
#94000
0!
b1111 #
b1111 &
0"
b1011110 %
#95000
1!
1"
b1011111 %
#96000
0!
b11 $
b11 '
b0 #
b0 &
0"
b1100000 %
#97000
1"
b1100001 %
#98000
b1 #
b1 &
0"
b1100010 %
#99000
1"
b1100011 %
#100000
b10 #
b10 &
0"
b1100100 %
#101000
1"
b1100101 %
#102000
b11 #
b11 &
0"
b1100110 %
#103000
1"
b1100111 %
#104000
b100 #
b100 &
0"
b1101000 %
#105000
1"
b1101001 %
#106000
b101 #
b101 &
0"
b1101010 %
#107000
1"
b1101011 %
#108000
b110 #
b110 &
0"
b1101100 %
#109000
1"
b1101101 %
#110000
b111 #
b111 &
0"
b1101110 %
#111000
1"
b1101111 %
#112000
b1000 #
b1000 &
0"
b1110000 %
#113000
1!
1"
b1110001 %
#114000
0!
b1001 #
b1001 &
0"
b1110010 %
#115000
1!
1"
b1110011 %
#116000
0!
b1010 #
b1010 &
0"
b1110100 %
#117000
1!
1"
b1110101 %
#118000
0!
b1011 #
b1011 &
0"
b1110110 %
#119000
1!
1"
b1110111 %
#120000
0!
b1100 #
b1100 &
0"
b1111000 %
#121000
1!
1"
b1111001 %
#122000
0!
b1101 #
b1101 &
0"
b1111010 %
#123000
1!
1"
b1111011 %
#124000
0!
b1110 #
b1110 &
0"
b1111100 %
#125000
1!
1"
b1111101 %
#126000
0!
b1111 #
b1111 &
0"
b1111110 %
#127000
1!
1"
b1111111 %
#128000
b10000000 %
