assignment3/mux/mnx1.v
module mnx1 #(parameter N=4 )(
    input en,
    input [$clog2(N)-1:0] s,
    input [N-1:0] i,
    output y
);
    reg x;
    always @(*) begin
        if (en)
            x = i[s];
        else
            x = 0;
    end
    assign y = x;
endmodule

assignment3/mux/mnx1tb.v
`timescale 1ns/1ps
module mnx1tb;
    localparam N=50;
    reg en;
    reg [$clog2(N)-1:0] s;
    reg [N-1:0] i;
    wire y;

    mnx1 #(.N(N)) mux(
        .en(en) , .s(s) , .i(i) , .y(y)
    );

    integer x ;
    initial begin
        $dumpfile("mnx1v.vcd");
        $dumpvars(0 , mnx1tb);
        en = 1;
    for (x = 0; x<N ; x=x+1) begin
        s = x;
        i = 1<< x;
        #1;
    end
    $finish;
end 
endmodule

assignment3/mux/mnx1v.vcd
$date
	Fri Jun 06 10:21:53 2025
$end
$version
	Icarus Verilog
$end
$timescale
	1ps
$end
$scope module mnx1tb $end
$var wire 1 ! y $end
$var parameter 32 " N $end
$var reg 1 # en $end
$var reg 50 $ i [49:0] $end
$var reg 6 % s [5:0] $end
$var integer 32 & x [31:0] $end
$scope module mux $end
$var wire 1 # en $end
$var wire 50 ' i [49:0] $end
$var wire 6 ( s [5:0] $end
$var wire 1 ! y $end
$var parameter 32 ) N $end
$var reg 1 * x $end
$upscope $end
$upscope $end
$enddefinitions $end
$comment Show the parameter values. $end
$dumpall
b110010 )
b110010 "
$end
#0
$dumpvars
1*
b0 (
b1 '
b0 &
b0 %
b1 $
1#
1!
$end
#1000
b10 $
b10 '
b1 %
b1 (
b1 &
#2000
b100 $
b100 '
b10 %
b10 (
b10 &
#3000
b1000 $
b1000 '
b11 %
b11 (
b11 &
#4000
b10000 $
b10000 '
b100 %
b100 (
b100 &
#5000
b100000 $
b100000 '
b101 %
b101 (
b101 &
#6000
b1000000 $
b1000000 '
b110 %
b110 (
b110 &
#7000
b10000000 $
b10000000 '
b111 %
b111 (
b111 &
#8000
b100000000 $
b100000000 '
b1000 %
b1000 (
b1000 &
#9000
b1000000000 $
b1000000000 '
b1001 %
b1001 (
b1001 &
#10000
b10000000000 $
b10000000000 '
b1010 %
b1010 (
b1010 &
#11000
b100000000000 $
b100000000000 '
b1011 %
b1011 (
b1011 &
#12000
b1000000000000 $
b1000000000000 '
b1100 %
b1100 (
b1100 &
#13000
b10000000000000 $
b10000000000000 '
b1101 %
b1101 (
b1101 &
#14000
b100000000000000 $
b100000000000000 '
b1110 %
b1110 (
b1110 &
#15000
b1000000000000000 $
b1000000000000000 '
b1111 %
b1111 (
b1111 &
#16000
b10000000000000000 $
b10000000000000000 '
b10000 %
b10000 (
b10000 &
#17000
b100000000000000000 $
b100000000000000000 '
b10001 %
b10001 (
b10001 &
#18000
b1000000000000000000 $
b1000000000000000000 '
b10010 %
b10010 (
b10010 &
#19000
b10000000000000000000 $
b10000000000000000000 '
b10011 %
b10011 (
b10011 &
#20000
b100000000000000000000 $
b100000000000000000000 '
b10100 %
b10100 (
b10100 &
#21000
b1000000000000000000000 $
b1000000000000000000000 '
b10101 %
b10101 (
b10101 &
#22000
b10000000000000000000000 $
b10000000000000000000000 '
b10110 %
b10110 (
b10110 &
#23000
b100000000000000000000000 $
b100000000000000000000000 '
b10111 %
b10111 (
b10111 &
#24000
b1000000000000000000000000 $
b1000000000000000000000000 '
b11000 %
b11000 (
b11000 &
#25000
b10000000000000000000000000 $
b10000000000000000000000000 '
b11001 %
b11001 (
b11001 &
#26000
b100000000000000000000000000 $
b100000000000000000000000000 '
b11010 %
b11010 (
b11010 &
#27000
b1000000000000000000000000000 $
b1000000000000000000000000000 '
b11011 %
b11011 (
b11011 &
#28000
b10000000000000000000000000000 $
b10000000000000000000000000000 '
b11100 %
b11100 (
b11100 &
#29000
b100000000000000000000000000000 $
b100000000000000000000000000000 '
b11101 %
b11101 (
b11101 &
#30000
b1000000000000000000000000000000 $
b1000000000000000000000000000000 '
b11110 %
b11110 (
b11110 &
#31000
b10000000000000000000000000000000 $
b10000000000000000000000000000000 '
b11111 %
b11111 (
b11111 &
#32000
b100000000000000000000000000000000 $
b100000000000000000000000000000000 '
b100000 %
b100000 (
b100000 &
#33000
b1000000000000000000000000000000000 $
b1000000000000000000000000000000000 '
b100001 %
b100001 (
b100001 &
#34000
b10000000000000000000000000000000000 $
b10000000000000000000000000000000000 '
b100010 %
b100010 (
b100010 &
#35000
b100000000000000000000000000000000000 $
b100000000000000000000000000000000000 '
b100011 %
b100011 (
b100011 &
#36000
b1000000000000000000000000000000000000 $
b1000000000000000000000000000000000000 '
b100100 %
b100100 (
b100100 &
#37000
b10000000000000000000000000000000000000 $
b10000000000000000000000000000000000000 '
b100101 %
b100101 (
b100101 &
#38000
b100000000000000000000000000000000000000 $
b100000000000000000000000000000000000000 '
b100110 %
b100110 (
b100110 &
#39000
b1000000000000000000000000000000000000000 $
b1000000000000000000000000000000000000000 '
b100111 %
b100111 (
b100111 &
#40000
b10000000000000000000000000000000000000000 $
b10000000000000000000000000000000000000000 '
b101000 %
b101000 (
b101000 &
#41000
b100000000000000000000000000000000000000000 $
b100000000000000000000000000000000000000000 '
b101001 %
b101001 (
b101001 &
#42000
b1000000000000000000000000000000000000000000 $
b1000000000000000000000000000000000000000000 '
b101010 %
b101010 (
b101010 &
#43000
b10000000000000000000000000000000000000000000 $
b10000000000000000000000000000000000000000000 '
b101011 %
b101011 (
b101011 &
#44000
b100000000000000000000000000000000000000000000 $
b100000000000000000000000000000000000000000000 '
b101100 %
b101100 (
b101100 &
#45000
b1000000000000000000000000000000000000000000000 $
b1000000000000000000000000000000000000000000000 '
b101101 %
b101101 (
b101101 &
#46000
b10000000000000000000000000000000000000000000000 $
b10000000000000000000000000000000000000000000000 '
b101110 %
b101110 (
b101110 &
#47000
b100000000000000000000000000000000000000000000000 $
b100000000000000000000000000000000000000000000000 '
b101111 %
b101111 (
b101111 &
#48000
b1000000000000000000000000000000000000000000000000 $
b1000000000000000000000000000000000000000000000000 '
b110000 %
b110000 (
b110000 &
#49000
b10000000000000000000000000000000000000000000000000 $
b10000000000000000000000000000000000000000000000000 '
b110001 %
b110001 (
b110001 &
#50000
b110010 &
