assignment2/cla.v
module cla(
    input [7:0] a, b,
    input cin,
    output [7:0] sum,
    output cout
    );
    wire [7:0] c;
    wire [7:0] p, g;

    assign p = a ^ b;
    assign g = a & b;
    assign c[0] = cin;
    assign c[1] = g[0] | (p[0] & cin);
    assign c[2] = g[1] | (p[1] & c[1]);
    assign c[3] = g[2] | (p[2] & c[2]);
    assign c[4] = g[3] | (p[3] & c[3]);
    assign c[5] = g[4] | (p[4] & c[4]);
    assign c[6] = g[5] | (p[5] & c[5]);
    assign c[7] = g[6] | (p[6] & c[6]);
    assign cout = g[7] | (p[7] & c[7]);
    assign sum = p ^ c;

endmodule

assignment 2/clatb.v
`timescale 1ns/1ps
module clatb;
    reg [7:0] a, b;
    reg cin ;
    wire [7:0] sum;
    wire cout;

    cla clao(
        .a(a), .b(b), .cin(cin), .sum(sum), .cout(cout)
    );
    integer i;
    initial begin
        $dumpfile("clatb.vcd");
        $dumpvars(0, clatb);
        $display(" a  b  cin | sum cout");
        $display("----------------------");
        for (i = 0; i < 256; i = i + 1) begin
            {a, b, cin} = i;
            #1;
            $display("%b %b  %b  | %b  %b", a, b, cin, sum, cout);
        end
        $finish;
    end
endmodule

assignment2/clatb.vcd
$date
	Wed Jun 04 17:28:08 2025
$end
$version
	Icarus Verilog
$end
$timescale
	1ps
$end
$scope module clatb $end
$var wire 8 ! sum [7:0] $end
$var wire 1 " cout $end
$var reg 8 # a [7:0] $end
$var reg 8 $ b [7:0] $end
$var reg 1 % cin $end
$var integer 32 & i [31:0] $end
$scope module clao $end
$var wire 8 ' a [7:0] $end
$var wire 8 ( b [7:0] $end
$var wire 1 % cin $end
$var wire 1 " cout $end
$var wire 8 ) g [7:0] $end
$var wire 8 * p [7:0] $end
$var wire 8 + sum [7:0] $end
$var wire 8 , c [7:0] $end
$upscope $end
$upscope $end
$enddefinitions $end
$comment Show the parameter values. $end
$dumpall
$end
#0
$dumpvars
b0 ,
b0 +
b0 *
b0 )
b0 (
b0 '
b0 &
0%
b0 $
b0 #
0"
b0 !
$end
#1000
b1 !
b1 +
b1 ,
1%
b1 &
#2000
b1 *
b1 !
b1 +
b1 $
b1 (
b0 ,
0%
b10 &
#3000
b10 !
b10 +
b11 ,
1%
b11 &
#4000
b10 *
b10 !
b10 +
b10 $
b10 (
b0 ,
0%
b100 &
#5000
b11 !
b11 +
b1 ,
1%
b101 &
#6000
b11 *
b11 !
b11 +
b11 $
b11 (
b0 ,
0%
b110 &
#7000
b100 !
b100 +
b111 ,
1%
b111 &
#8000
b100 *
b100 !
b100 +
b100 $
b100 (
b0 ,
0%
b1000 &
#9000
b101 !
b101 +
b1 ,
1%
b1001 &
#10000
b101 *
b101 !
b101 +
b101 $
b101 (
b0 ,
0%
b1010 &
#11000
b110 !
b110 +
b11 ,
1%
b1011 &
#12000
b110 *
b110 !
b110 +
b110 $
b110 (
b0 ,
0%
b1100 &
#13000
b111 !
b111 +
b1 ,
1%
b1101 &
#14000
b111 *
b111 !
b111 +
b111 $
b111 (
b0 ,
0%
b1110 &
#15000
b1000 !
b1000 +
b1111 ,
1%
b1111 &
#16000
b1000 *
b1000 !
b1000 +
b1000 $
b1000 (
b0 ,
0%
b10000 &
#17000
b1001 !
b1001 +
b1 ,
1%
b10001 &
#18000
b1001 *
b1001 !
b1001 +
b1001 $
b1001 (
b0 ,
0%
b10010 &
#19000
b1010 !
b1010 +
b11 ,
1%
b10011 &
#20000
b1010 *
b1010 !
b1010 +
b1010 $
b1010 (
b0 ,
0%
b10100 &
#21000
b1011 !
b1011 +
b1 ,
1%
b10101 &
#22000
b1011 *
b1011 !
b1011 +
b1011 $
b1011 (
b0 ,
0%
b10110 &
#23000
b1100 !
b1100 +
b111 ,
1%
b10111 &
#24000
b1100 *
b1100 !
b1100 +
b1100 $
b1100 (
b0 ,
0%
b11000 &
#25000
b1101 !
b1101 +
b1 ,
1%
b11001 &
#26000
b1101 *
b1101 !
b1101 +
b1101 $
b1101 (
b0 ,
0%
b11010 &
#27000
b1110 !
b1110 +
b11 ,
1%
b11011 &
#28000
b1110 *
b1110 !
b1110 +
b1110 $
b1110 (
b0 ,
0%
b11100 &
#29000
b1111 !
b1111 +
b1 ,
1%
b11101 &
#30000
b1111 *
b1111 !
b1111 +
b1111 $
b1111 (
b0 ,
0%
b11110 &
#31000
b10000 !
b10000 +
b11111 ,
1%
b11111 &
#32000
b10000 *
b10000 !
b10000 +
b10000 $
b10000 (
b0 ,
0%
b100000 &
#33000
b10001 !
b10001 +
b1 ,
1%
b100001 &
#34000
b10001 *
b10001 !
b10001 +
b10001 $
b10001 (
b0 ,
0%
b100010 &
#35000
b10010 !
b10010 +
b11 ,
1%
b100011 &
#36000
b10010 *
b10010 !
b10010 +
b10010 $
b10010 (
b0 ,
0%
b100100 &
#37000
b10011 !
b10011 +
b1 ,
1%
b100101 &
#38000
b10011 *
b10011 !
b10011 +
b10011 $
b10011 (
b0 ,
0%
b100110 &
#39000
b10100 !
b10100 +
b111 ,
1%
b100111 &
#40000
b10100 *
b10100 !
b10100 +
b10100 $
b10100 (
b0 ,
0%
b101000 &
#41000
b10101 !
b10101 +
b1 ,
1%
b101001 &
#42000
b10101 *
b10101 !
b10101 +
b10101 $
b10101 (
b0 ,
0%
b101010 &
#43000
b10110 !
b10110 +
b11 ,
1%
b101011 &
#44000
b10110 *
b10110 !
b10110 +
b10110 $
b10110 (
b0 ,
0%
b101100 &
#45000
b10111 !
b10111 +
b1 ,
1%
b101101 &
#46000
b10111 *
b10111 !
b10111 +
b10111 $
b10111 (
b0 ,
0%
b101110 &
#47000
b11000 !
b11000 +
b1111 ,
1%
b101111 &
#48000
b11000 *
b11000 !
b11000 +
b11000 $
b11000 (
b0 ,
0%
b110000 &
#49000
b11001 !
b11001 +
b1 ,
1%
b110001 &
#50000
b11001 *
b11001 !
b11001 +
b11001 $
b11001 (
b0 ,
0%
b110010 &
#51000
b11010 !
b11010 +
b11 ,
1%
b110011 &
#52000
b11010 *
b11010 !
b11010 +
b11010 $
b11010 (
b0 ,
0%
b110100 &
#53000
b11011 !
b11011 +
b1 ,
1%
b110101 &
#54000
b11011 *
b11011 !
b11011 +
b11011 $
b11011 (
b0 ,
0%
b110110 &
#55000
b11100 !
b11100 +
b111 ,
1%
b110111 &
#56000
b11100 *
b11100 !
b11100 +
b11100 $
b11100 (
b0 ,
0%
b111000 &
#57000
b11101 !
b11101 +
b1 ,
1%
b111001 &
#58000
b11101 *
b11101 !
b11101 +
b11101 $
b11101 (
b0 ,
0%
b111010 &
#59000
b11110 !
b11110 +
b11 ,
1%
b111011 &
#60000
b11110 *
b11110 !
b11110 +
b11110 $
b11110 (
b0 ,
0%
b111100 &
#61000
b11111 !
b11111 +
b1 ,
1%
b111101 &
#62000
b11111 *
b11111 !
b11111 +
b11111 $
b11111 (
b0 ,
0%
b111110 &
#63000
b100000 !
b100000 +
b111111 ,
1%
b111111 &
#64000
b100000 *
b100000 !
b100000 +
b100000 $
b100000 (
b0 ,
0%
b1000000 &
#65000
b100001 !
b100001 +
b1 ,
1%
b1000001 &
#66000
b100001 *
b100001 !
b100001 +
b100001 $
b100001 (
b0 ,
0%
b1000010 &
#67000
b100010 !
b100010 +
b11 ,
1%
b1000011 &
#68000
b100010 *
b100010 !
b100010 +
b100010 $
b100010 (
b0 ,
0%
b1000100 &
#69000
b100011 !
b100011 +
b1 ,
1%
b1000101 &
#70000
b100011 *
b100011 !
b100011 +
b100011 $
b100011 (
b0 ,
0%
b1000110 &
#71000
b100100 !
b100100 +
b111 ,
1%
b1000111 &
#72000
b100100 *
b100100 !
b100100 +
b100100 $
b100100 (
b0 ,
0%
b1001000 &
#73000
b100101 !
b100101 +
b1 ,
1%
b1001001 &
#74000
b100101 *
b100101 !
b100101 +
b100101 $
b100101 (
b0 ,
0%
b1001010 &
#75000
b100110 !
b100110 +
b11 ,
1%
b1001011 &
#76000
b100110 *
b100110 !
b100110 +
b100110 $
b100110 (
b0 ,
0%
b1001100 &
#77000
b100111 !
b100111 +
b1 ,
1%
b1001101 &
#78000
b100111 *
b100111 !
b100111 +
b100111 $
b100111 (
b0 ,
0%
b1001110 &
#79000
b101000 !
b101000 +
b1111 ,
1%
b1001111 &
#80000
b101000 *
b101000 !
b101000 +
b101000 $
b101000 (
b0 ,
0%
b1010000 &
#81000
b101001 !
b101001 +
b1 ,
1%
b1010001 &
#82000
b101001 *
b101001 !
b101001 +
b101001 $
b101001 (
b0 ,
0%
b1010010 &
#83000
b101010 !
b101010 +
b11 ,
1%
b1010011 &
#84000
b101010 *
b101010 !
b101010 +
b101010 $
b101010 (
b0 ,
0%
b1010100 &
#85000
b101011 !
b101011 +
b1 ,
1%
b1010101 &
#86000
b101011 *
b101011 !
b101011 +
b101011 $
b101011 (
b0 ,
0%
b1010110 &
#87000
b101100 !
b101100 +
b111 ,
1%
b1010111 &
#88000
b101100 *
b101100 !
b101100 +
b101100 $
b101100 (
b0 ,
0%
b1011000 &
#89000
b101101 !
b101101 +
b1 ,
1%
b1011001 &
#90000
b101101 *
b101101 !
b101101 +
b101101 $
b101101 (
b0 ,
0%
b1011010 &
#91000
b101110 !
b101110 +
b11 ,
1%
b1011011 &
#92000
b101110 *
b101110 !
b101110 +
b101110 $
b101110 (
b0 ,
0%
b1011100 &
#93000
b101111 !
b101111 +
b1 ,
1%
b1011101 &
#94000
b101111 *
b101111 !
b101111 +
b101111 $
b101111 (
b0 ,
0%
b1011110 &
#95000
b110000 !
b110000 +
b11111 ,
1%
b1011111 &
#96000
b110000 *
b110000 !
b110000 +
b110000 $
b110000 (
b0 ,
0%
b1100000 &
#97000
b110001 !
b110001 +
b1 ,
1%
b1100001 &
#98000
b110001 *
b110001 !
b110001 +
b110001 $
b110001 (
b0 ,
0%
b1100010 &
#99000
b110010 !
b110010 +
b11 ,
1%
b1100011 &
#100000
b110010 *
b110010 !
b110010 +
b110010 $
b110010 (
b0 ,
0%
b1100100 &
#101000
b110011 !
b110011 +
b1 ,
1%
b1100101 &
#102000
b110011 *
b110011 !
b110011 +
b110011 $
b110011 (
b0 ,
0%
b1100110 &
#103000
b110100 !
b110100 +
b111 ,
1%
b1100111 &
#104000
b110100 *
b110100 !
b110100 +
b110100 $
b110100 (
b0 ,
0%
b1101000 &
#105000
b110101 !
b110101 +
b1 ,
1%
b1101001 &
#106000
b110101 *
b110101 !
b110101 +
b110101 $
b110101 (
b0 ,
0%
b1101010 &
#107000
b110110 !
b110110 +
b11 ,
1%
b1101011 &
#108000
b110110 *
b110110 !
b110110 +
b110110 $
b110110 (
b0 ,
0%
b1101100 &
#109000
b110111 !
b110111 +
b1 ,
1%
b1101101 &
#110000
b110111 *
b110111 !
b110111 +
b110111 $
b110111 (
b0 ,
0%
b1101110 &
#111000
b111000 !
b111000 +
b1111 ,
1%
b1101111 &
#112000
b111000 *
b111000 !
b111000 +
b111000 $
b111000 (
b0 ,
0%
b1110000 &
#113000
b111001 !
b111001 +
b1 ,
1%
b1110001 &
#114000
b111001 *
b111001 !
b111001 +
b111001 $
b111001 (
b0 ,
0%
b1110010 &
#115000
b111010 !
b111010 +
b11 ,
1%
b1110011 &
#116000
b111010 *
b111010 !
b111010 +
b111010 $
b111010 (
b0 ,
0%
b1110100 &
#117000
b111011 !
b111011 +
b1 ,
1%
b1110101 &
#118000
b111011 *
b111011 !
b111011 +
b111011 $
b111011 (
b0 ,
0%
b1110110 &
#119000
b111100 !
b111100 +
b111 ,
1%
b1110111 &
#120000
b111100 *
b111100 !
b111100 +
b111100 $
b111100 (
b0 ,
0%
b1111000 &
#121000
b111101 !
b111101 +
b1 ,
1%
b1111001 &
#122000
b111101 *
b111101 !
b111101 +
b111101 $
b111101 (
b0 ,
0%
b1111010 &
#123000
b111110 !
b111110 +
b11 ,
1%
b1111011 &
#124000
b111110 *
b111110 !
b111110 +
b111110 $
b111110 (
b0 ,
0%
b1111100 &
#125000
b111111 !
b111111 +
b1 ,
1%
b1111101 &
#126000
b111111 *
b111111 !
b111111 +
b111111 $
b111111 (
b0 ,
0%
b1111110 &
#127000
b1000000 !
b1000000 +
b1111111 ,
1%
b1111111 &
#128000
b1000000 *
b1000000 !
b1000000 +
b1000000 $
b1000000 (
b0 ,
0%
b10000000 &
#129000
b1000001 !
b1000001 +
b1 ,
1%
b10000001 &
#130000
b1000001 *
b1000001 !
b1000001 +
b1000001 $
b1000001 (
b0 ,
0%
b10000010 &
#131000
b1000010 !
b1000010 +
b11 ,
1%
b10000011 &
#132000
b1000010 *
b1000010 !
b1000010 +
b1000010 $
b1000010 (
b0 ,
0%
b10000100 &
#133000
b1000011 !
b1000011 +
b1 ,
1%
b10000101 &
#134000
b1000011 *
b1000011 !
b1000011 +
b1000011 $
b1000011 (
b0 ,
0%
b10000110 &
#135000
b1000100 !
b1000100 +
b111 ,
1%
b10000111 &
#136000
b1000100 *
b1000100 !
b1000100 +
b1000100 $
b1000100 (
b0 ,
0%
b10001000 &
#137000
b1000101 !
b1000101 +
b1 ,
1%
b10001001 &
#138000
b1000101 *
b1000101 !
b1000101 +
b1000101 $
b1000101 (
b0 ,
0%
b10001010 &
#139000
b1000110 !
b1000110 +
b11 ,
1%
b10001011 &
#140000
b1000110 *
b1000110 !
b1000110 +
b1000110 $
b1000110 (
b0 ,
0%
b10001100 &
#141000
b1000111 !
b1000111 +
b1 ,
1%
b10001101 &
#142000
b1000111 *
b1000111 !
b1000111 +
b1000111 $
b1000111 (
b0 ,
0%
b10001110 &
#143000
b1001000 !
b1001000 +
b1111 ,
1%
b10001111 &
#144000
b1001000 *
b1001000 !
b1001000 +
b1001000 $
b1001000 (
b0 ,
0%
b10010000 &
#145000
b1001001 !
b1001001 +
b1 ,
1%
b10010001 &
#146000
b1001001 *
b1001001 !
b1001001 +
b1001001 $
b1001001 (
b0 ,
0%
b10010010 &
#147000
b1001010 !
b1001010 +
b11 ,
1%
b10010011 &
#148000
b1001010 *
b1001010 !
b1001010 +
b1001010 $
b1001010 (
b0 ,
0%
b10010100 &
#149000
b1001011 !
b1001011 +
b1 ,
1%
b10010101 &
#150000
b1001011 *
b1001011 !
b1001011 +
b1001011 $
b1001011 (
b0 ,
0%
b10010110 &
#151000
b1001100 !
b1001100 +
b111 ,
1%
b10010111 &
#152000
b1001100 *
b1001100 !
b1001100 +
b1001100 $
b1001100 (
b0 ,
0%
b10011000 &
#153000
b1001101 !
b1001101 +
b1 ,
1%
b10011001 &
#154000
b1001101 *
b1001101 !
b1001101 +
b1001101 $
b1001101 (
b0 ,
0%
b10011010 &
#155000
b1001110 !
b1001110 +
b11 ,
1%
b10011011 &
#156000
b1001110 *
b1001110 !
b1001110 +
b1001110 $
b1001110 (
b0 ,
0%
b10011100 &
#157000
b1001111 !
b1001111 +
b1 ,
1%
b10011101 &
#158000
b1001111 *
b1001111 !
b1001111 +
b1001111 $
b1001111 (
b0 ,
0%
b10011110 &
#159000
b1010000 !
b1010000 +
b11111 ,
1%
b10011111 &
#160000
b1010000 *
b1010000 !
b1010000 +
b1010000 $
b1010000 (
b0 ,
0%
b10100000 &
#161000
b1010001 !
b1010001 +
b1 ,
1%
b10100001 &
#162000
b1010001 *
b1010001 !
b1010001 +
b1010001 $
b1010001 (
b0 ,
0%
b10100010 &
#163000
b1010010 !
b1010010 +
b11 ,
1%
b10100011 &
#164000
b1010010 *
b1010010 !
b1010010 +
b1010010 $
b1010010 (
b0 ,
0%
b10100100 &
#165000
b1010011 !
b1010011 +
b1 ,
1%
b10100101 &
#166000
b1010011 *
b1010011 !
b1010011 +
b1010011 $
b1010011 (
b0 ,
0%
b10100110 &
#167000
b1010100 !
b1010100 +
b111 ,
1%
b10100111 &
#168000
b1010100 *
b1010100 !
b1010100 +
b1010100 $
b1010100 (
b0 ,
0%
b10101000 &
#169000
b1010101 !
b1010101 +
b1 ,
1%
b10101001 &
#170000
b1010101 *
b1010101 !
b1010101 +
b1010101 $
b1010101 (
b0 ,
0%
b10101010 &
#171000
b1010110 !
b1010110 +
b11 ,
1%
b10101011 &
#172000
b1010110 *
b1010110 !
b1010110 +
b1010110 $
b1010110 (
b0 ,
0%
b10101100 &
#173000
b1010111 !
b1010111 +
b1 ,
1%
b10101101 &
#174000
b1010111 *
b1010111 !
b1010111 +
b1010111 $
b1010111 (
b0 ,
0%
b10101110 &
#175000
b1011000 !
b1011000 +
b1111 ,
1%
b10101111 &
#176000
b1011000 *
b1011000 !
b1011000 +
b1011000 $
b1011000 (
b0 ,
0%
b10110000 &
#177000
b1011001 !
b1011001 +
b1 ,
1%
b10110001 &
#178000
b1011001 *
b1011001 !
b1011001 +
b1011001 $
b1011001 (
b0 ,
0%
b10110010 &
#179000
b1011010 !
b1011010 +
b11 ,
1%
b10110011 &
#180000
b1011010 *
b1011010 !
b1011010 +
b1011010 $
b1011010 (
b0 ,
0%
b10110100 &
#181000
b1011011 !
b1011011 +
b1 ,
1%
b10110101 &
#182000
b1011011 *
b1011011 !
b1011011 +
b1011011 $
b1011011 (
b0 ,
0%
b10110110 &
#183000
b1011100 !
b1011100 +
b111 ,
1%
b10110111 &
#184000
b1011100 *
b1011100 !
b1011100 +
b1011100 $
b1011100 (
b0 ,
0%
b10111000 &
#185000
b1011101 !
b1011101 +
b1 ,
1%
b10111001 &
#186000
b1011101 *
b1011101 !
b1011101 +
b1011101 $
b1011101 (
b0 ,
0%
b10111010 &
#187000
b1011110 !
b1011110 +
b11 ,
1%
b10111011 &
#188000
b1011110 *
b1011110 !
b1011110 +
b1011110 $
b1011110 (
b0 ,
0%
b10111100 &
#189000
b1011111 !
b1011111 +
b1 ,
1%
b10111101 &
#190000
b1011111 *
b1011111 !
b1011111 +
b1011111 $
b1011111 (
b0 ,
0%
b10111110 &
#191000
b1100000 !
b1100000 +
b111111 ,
1%
b10111111 &
#192000
b1100000 *
b1100000 !
b1100000 +
b1100000 $
b1100000 (
b0 ,
0%
b11000000 &
#193000
b1100001 !
b1100001 +
b1 ,
1%
b11000001 &
#194000
b1100001 *
b1100001 !
b1100001 +
b1100001 $
b1100001 (
b0 ,
0%
b11000010 &
#195000
b1100010 !
b1100010 +
b11 ,
1%
b11000011 &
#196000
b1100010 *
b1100010 !
b1100010 +
b1100010 $
b1100010 (
b0 ,
0%
b11000100 &
#197000
b1100011 !
b1100011 +
b1 ,
1%
b11000101 &
#198000
b1100011 *
b1100011 !
b1100011 +
b1100011 $
b1100011 (
b0 ,
0%
b11000110 &
#199000
b1100100 !
b1100100 +
b111 ,
1%
b11000111 &
#200000
b1100100 *
b1100100 !
b1100100 +
b1100100 $
b1100100 (
b0 ,
0%
b11001000 &
#201000
b1100101 !
b1100101 +
b1 ,
1%
b11001001 &
#202000
b1100101 *
b1100101 !
b1100101 +
b1100101 $
b1100101 (
b0 ,
0%
b11001010 &
#203000
b1100110 !
b1100110 +
b11 ,
1%
b11001011 &
#204000
b1100110 *
b1100110 !
b1100110 +
b1100110 $
b1100110 (
b0 ,
0%
b11001100 &
#205000
b1100111 !
b1100111 +
b1 ,
1%
b11001101 &
#206000
b1100111 *
b1100111 !
b1100111 +
b1100111 $
b1100111 (
b0 ,
0%
b11001110 &
#207000
b1101000 !
b1101000 +
b1111 ,
1%
b11001111 &
#208000
b1101000 *
b1101000 !
b1101000 +
b1101000 $
b1101000 (
b0 ,
0%
b11010000 &
#209000
b1101001 !
b1101001 +
b1 ,
1%
b11010001 &
#210000
b1101001 *
b1101001 !
b1101001 +
b1101001 $
b1101001 (
b0 ,
0%
b11010010 &
#211000
b1101010 !
b1101010 +
b11 ,
1%
b11010011 &
#212000
b1101010 *
b1101010 !
b1101010 +
b1101010 $
b1101010 (
b0 ,
0%
b11010100 &
#213000
b1101011 !
b1101011 +
b1 ,
1%
b11010101 &
#214000
b1101011 *
b1101011 !
b1101011 +
b1101011 $
b1101011 (
b0 ,
0%
b11010110 &
#215000
b1101100 !
b1101100 +
b111 ,
1%
b11010111 &
#216000
b1101100 *
b1101100 !
b1101100 +
b1101100 $
b1101100 (
b0 ,
0%
b11011000 &
#217000
b1101101 !
b1101101 +
b1 ,
1%
b11011001 &
#218000
b1101101 *
b1101101 !
b1101101 +
b1101101 $
b1101101 (
b0 ,
0%
b11011010 &
#219000
b1101110 !
b1101110 +
b11 ,
1%
b11011011 &
#220000
b1101110 *
b1101110 !
b1101110 +
b1101110 $
b1101110 (
b0 ,
0%
b11011100 &
#221000
b1101111 !
b1101111 +
b1 ,
1%
b11011101 &
#222000
b1101111 *
b1101111 !
b1101111 +
b1101111 $
b1101111 (
b0 ,
0%
b11011110 &
#223000
b1110000 !
b1110000 +
b11111 ,
1%
b11011111 &
#224000
b1110000 *
b1110000 !
b1110000 +
b1110000 $
b1110000 (
b0 ,
0%
b11100000 &
#225000
b1110001 !
b1110001 +
b1 ,
1%
b11100001 &
#226000
b1110001 *
b1110001 !
b1110001 +
b1110001 $
b1110001 (
b0 ,
0%
b11100010 &
#227000
b1110010 !
b1110010 +
b11 ,
1%
b11100011 &
#228000
b1110010 *
b1110010 !
b1110010 +
b1110010 $
b1110010 (
b0 ,
0%
b11100100 &
#229000
b1110011 !
b1110011 +
b1 ,
1%
b11100101 &
#230000
b1110011 *
b1110011 !
b1110011 +
b1110011 $
b1110011 (
b0 ,
0%
b11100110 &
#231000
b1110100 !
b1110100 +
b111 ,
1%
b11100111 &
#232000
b1110100 *
b1110100 !
b1110100 +
b1110100 $
b1110100 (
b0 ,
0%
b11101000 &
#233000
b1110101 !
b1110101 +
b1 ,
1%
b11101001 &
#234000
b1110101 *
b1110101 !
b1110101 +
b1110101 $
b1110101 (
b0 ,
0%
b11101010 &
#235000
b1110110 !
b1110110 +
b11 ,
1%
b11101011 &
#236000
b1110110 *
b1110110 !
b1110110 +
b1110110 $
b1110110 (
b0 ,
0%
b11101100 &
#237000
b1110111 !
b1110111 +
b1 ,
1%
b11101101 &
#238000
b1110111 *
b1110111 !
b1110111 +
b1110111 $
b1110111 (
b0 ,
0%
b11101110 &
#239000
b1111000 !
b1111000 +
b1111 ,
1%
b11101111 &
#240000
b1111000 *
b1111000 !
b1111000 +
b1111000 $
b1111000 (
b0 ,
0%
b11110000 &
#241000
b1111001 !
b1111001 +
b1 ,
1%
b11110001 &
#242000
b1111001 *
b1111001 !
b1111001 +
b1111001 $
b1111001 (
b0 ,
0%
b11110010 &
#243000
b1111010 !
b1111010 +
b11 ,
1%
b11110011 &
#244000
b1111010 *
b1111010 !
b1111010 +
b1111010 $
b1111010 (
b0 ,
0%
b11110100 &
#245000
b1111011 !
b1111011 +
b1 ,
1%
b11110101 &
#246000
b1111011 *
b1111011 !
b1111011 +
b1111011 $
b1111011 (
b0 ,
0%
b11110110 &
#247000
b1111100 !
b1111100 +
b111 ,
1%
b11110111 &
#248000
b1111100 *
b1111100 !
b1111100 +
b1111100 $
b1111100 (
b0 ,
0%
b11111000 &
#249000
b1111101 !
b1111101 +
b1 ,
1%
b11111001 &
#250000
b1111101 *
b1111101 !
b1111101 +
b1111101 $
b1111101 (
b0 ,
0%
b11111010 &
#251000
b1111110 !
b1111110 +
b11 ,
1%
b11111011 &
#252000
b1111110 *
b1111110 !
b1111110 +
b1111110 $
b1111110 (
b0 ,
0%
b11111100 &
#253000
b1111111 !
b1111111 +
b1 ,
1%
b11111101 &
#254000
b1111111 *
b1111111 !
b1111111 +
b1111111 $
b1111111 (
b0 ,
0%
b11111110 &
#255000
b10000000 !
b10000000 +
b11111111 ,
1%
b11111111 &
#256000
b100000000 &
