assignment 2/csa.v
module csa(
    input [7:0] a, b,
    input cin,
    output [7:0] sum,
    output cout
);
    wire [7:0] c1 ,c2;
    wire [7:0] p,g;
    wire [7:0] sum1,sum2;
    wire cout1 ,cout2;

    assign p = a ^ b;
    assign g = a & b;

    assign c1[0] = 0;
    assign c1[1] = g[0] | (p[0] & 0);
    assign c1[2] = g[1] | (p[1] & c1[1]);
    assign c1[3] = g[2] | (p[2] & c1[2]);
    assign c1[4] = g[3] | (p[3] & c1[3]);
    assign c1[5] = g[4] | (p[4] & c1[4]);
    assign c1[6] = g[5] | (p[5] & c1[5]);
    assign c1[7] = g[6] | (p[6] & c1[6]);
    assign cout1 = g[7] | (p[7] & c1[7]);

    assign c2[0] = 1;
    assign c2[1] = g[0] | (p[0] & 1);
    assign c2[2] = g[1] | (p[1] & c2[1]);
    assign c2[3] = g[2] | (p[2] & c2[2]);
    assign c2[4] = g[3] | (p[3] & c2[3]);
    assign c2[5] = g[4] | (p[4] & c2[4]);
    assign c2[6] = g[5] | (p[5] & c2[5]);
    assign c2[7] = g[6] | (p[6] & c2[6]);
    assign cout2 = g[7] | (p[7] & c2[7]);

    assign sum1 = p ^ c1;
    assign sum2 = p ^ c2;

    assign sum = cin ? sum2 : sum1;
    assign cout = cin ? cout2 : cout1;
endmodule

assignment2/csatb.v
`timescale 1ns/1fs
module csatb;
    reg [31:0] a, b;
    reg cin;
    wire [31:0] sum;
    wire cout;
    wire [2:0] c;
    csa csa0(   
        .a(a[7:0]) , .b(b[7:0]) , .cin(cin) , .sum(sum[7:0]) , .cout(c[0])
    );
    csa csa1(
        .a(a[15:8]) , .b(b[15:8]) , .cin(c[0]) , .sum(sum[15:8]) , .cout(c[1])
    );
    csa csa2(
        .a(a[23:16]) , .b(b[23:16]) , .cin(c[1]) , .sum(sum[23:16]) , .cout(c[2])
    );
    csa csa3(
        .a(a[31:24]) , .b(b[31:24]) , .cin(c[2]) , .sum(sum[31:24]) , .cout(cout)
    );

    integer i;
    initial begin
        $dumpfile("csatb.vcd");
        $dumpvars(0 , csatb);
        $display(" a          b          cin | sum        cout");
        $display("---------------------------------------------");
        for(i = 0; i< 5536 ; i = i+1)begin
            {a , b , cin} = i;
            #1;
            $display("%b %b %b | %b %b", a, b, cin, sum, cout);
        end
        a = 32'hffffffff;
        b = 32'h00000001;
        cin = 1'b0;
            #1;
            $display("%b %b %b | %b %b", a, b, cin, sum, cout);
        a = 32'h00ffffff;
        b = 32'hfdbace01;
        cin = 1'b0;
            #1;
            $display("%b %b %b | %b %b", a, b, cin, sum, cout);
        a = 32'h00ffffff;
        b = 32'h60d0f0a1;
        cin = 1'b0;
            #1;
            $display("%b %b %b | %b %b", a, b, cin, sum, cout);
        $finish;

    end
endmodule

assignment2/csatb.vcd
$date
	Wed Jun 04 21:34:08 2025
$end
$version
	Icarus Verilog
$end
$timescale
	1fs
$end
$scope module csatb $end
$var wire 32 ! sum [31:0] $end
$var wire 1 " cout $end
$var wire 3 # c [2:0] $end
$var reg 32 $ a [31:0] $end
$var reg 32 % b [31:0] $end
$var reg 1 & cin $end
$var integer 32 ' i [31:0] $end
$scope module csa0 $end
$var wire 8 ( a [7:0] $end
$var wire 8 ) b [7:0] $end
$var wire 1 & cin $end
$var wire 1 * cout1 $end
$var wire 1 + cout2 $end
$var wire 8 , g [7:0] $end
$var wire 8 - p [7:0] $end
$var wire 8 . sum1 [7:0] $end
$var wire 8 / sum2 [7:0] $end
$var wire 8 0 sum [7:0] $end
$var wire 1 1 cout $end
$var wire 8 2 c2 [7:0] $end
$var wire 8 3 c1 [7:0] $end
$upscope $end
$scope module csa1 $end
$var wire 8 4 a [7:0] $end
$var wire 8 5 b [7:0] $end
$var wire 1 6 cin $end
$var wire 1 7 cout1 $end
$var wire 1 8 cout2 $end
$var wire 8 9 g [7:0] $end
$var wire 8 : p [7:0] $end
$var wire 8 ; sum1 [7:0] $end
$var wire 8 < sum2 [7:0] $end
$var wire 8 = sum [7:0] $end
$var wire 1 > cout $end
$var wire 8 ? c2 [7:0] $end
$var wire 8 @ c1 [7:0] $end
$upscope $end
$scope module csa2 $end
$var wire 8 A a [7:0] $end
$var wire 8 B b [7:0] $end
$var wire 1 C cin $end
$var wire 1 D cout1 $end
$var wire 1 E cout2 $end
$var wire 8 F g [7:0] $end
$var wire 8 G p [7:0] $end
$var wire 8 H sum1 [7:0] $end
$var wire 8 I sum2 [7:0] $end
$var wire 8 J sum [7:0] $end
$var wire 1 K cout $end
$var wire 8 L c2 [7:0] $end
$var wire 8 M c1 [7:0] $end
$upscope $end
$scope module csa3 $end
$var wire 8 N a [7:0] $end
$var wire 8 O b [7:0] $end
$var wire 1 P cin $end
$var wire 1 Q cout1 $end
$var wire 1 R cout2 $end
$var wire 8 S g [7:0] $end
$var wire 8 T p [7:0] $end
$var wire 8 U sum1 [7:0] $end
$var wire 8 V sum2 [7:0] $end
$var wire 8 W sum [7:0] $end
$var wire 1 " cout $end
$var wire 8 X c2 [7:0] $end
$var wire 8 Y c1 [7:0] $end
$upscope $end
$upscope $end
$enddefinitions $end
$comment Show the parameter values. $end
$dumpall
$end
#0
$dumpvars
b0 Y
b1 X
b0 W
b1 V
b0 U
b0 T
b0 S
0R
0Q
0P
b0 O
b0 N
b0 M
b1 L
0K
b0 J
b1 I
b0 H
b0 G
b0 F
0E
0D
0C
b0 B
b0 A
b0 @
b1 ?
0>
b0 =
b1 <
b0 ;
b0 :
b0 9
08
07
06
b0 5
b0 4
b0 3
b1 2
01
b0 0
b1 /
b0 .
b0 -
b0 ,
0+
0*
b0 )
b0 (
b0 '
0&
b0 %
b0 $
b0 #
0"
b0 !
$end
#1000000
b1 !
b1 0
1&
b1 '
#2000000
b11 2
b1 .
b10 /
b1 -
b1 )
b1 !
b1 0
b1 %
0&
b10 '
#3000000
b10 !
b10 0
1&
b11 '
#4000000
b1 2
b10 .
b11 /
b10 -
b10 )
b10 !
b10 0
b10 %
0&
b100 '
#5000000
b11 !
b11 0
1&
b101 '
#6000000
b111 2
b11 .
b100 /
b11 -
b11 )
b11 !
b11 0
b11 %
0&
b110 '
#7000000
b100 !
b100 0
1&
b111 '
#8000000
b1 2
b100 .
b101 /
b100 -
b100 )
b100 !
b100 0
b100 %
0&
b1000 '
#9000000
b101 !
b101 0
1&
b1001 '
#10000000
b11 2
b101 .
b110 /
b101 -
b101 )
b101 !
b101 0
b101 %
0&
b1010 '
#11000000
b110 !
b110 0
1&
b1011 '
#12000000
b1 2
b110 .
b111 /
b110 -
b110 )
b110 !
b110 0
b110 %
0&
b1100 '
#13000000
b111 !
b111 0
1&
b1101 '
#14000000
b1111 2
b111 .
b1000 /
b111 -
b111 )
b111 !
b111 0
b111 %
0&
b1110 '
#15000000
b1000 !
b1000 0
1&
b1111 '
#16000000
b1 2
b1000 .
b1001 /
b1000 -
b1000 )
b1000 !
b1000 0
b1000 %
0&
b10000 '
#17000000
b1001 !
b1001 0
1&
b10001 '
#18000000
b11 2
b1001 .
b1010 /
b1001 -
b1001 )
b1001 !
b1001 0
b1001 %
0&
b10010 '
#19000000
b1010 !
b1010 0
1&
b10011 '
#20000000
b1 2
b1010 .
b1011 /
b1010 -
b1010 )
b1010 !
b1010 0
b1010 %
0&
b10100 '
#21000000
b1011 !
b1011 0
1&
b10101 '
#22000000
b111 2
b1011 .
b1100 /
b1011 -
b1011 )
b1011 !
b1011 0
b1011 %
0&
b10110 '
#23000000
b1100 !
b1100 0
1&
b10111 '
#24000000
b1 2
b1100 .
b1101 /
b1100 -
b1100 )
b1100 !
b1100 0
b1100 %
0&
b11000 '
#25000000
b1101 !
b1101 0
1&
b11001 '
#26000000
b11 2
b1101 .
b1110 /
b1101 -
b1101 )
b1101 !
b1101 0
b1101 %
0&
b11010 '
#27000000
b1110 !
b1110 0
1&
b11011 '
#28000000
b1 2
b1110 .
b1111 /
b1110 -
b1110 )
b1110 !
b1110 0
b1110 %
0&
b11100 '
#29000000
b1111 !
b1111 0
1&
b11101 '
#30000000
b11111 2
b1111 .
b10000 /
b1111 -
b1111 )
b1111 !
b1111 0
b1111 %
0&
b11110 '
#31000000
b10000 !
b10000 0
1&
b11111 '
#32000000
b1 2
b10000 .
b10001 /
b10000 -
b10000 )
b10000 !
b10000 0
b10000 %
0&
b100000 '
#33000000
b10001 !
b10001 0
1&
b100001 '
#34000000
b11 2
b10001 .
b10010 /
b10001 -
b10001 )
b10001 !
b10001 0
b10001 %
0&
b100010 '
#35000000
b10010 !
b10010 0
1&
b100011 '
#36000000
b1 2
b10010 .
b10011 /
b10010 -
b10010 )
b10010 !
b10010 0
b10010 %
0&
b100100 '
#37000000
b10011 !
b10011 0
1&
b100101 '
#38000000
b111 2
b10011 .
b10100 /
b10011 -
b10011 )
b10011 !
b10011 0
b10011 %
0&
b100110 '
#39000000
b10100 !
b10100 0
1&
b100111 '
#40000000
b1 2
b10100 .
b10101 /
b10100 -
b10100 )
b10100 !
b10100 0
b10100 %
0&
b101000 '
#41000000
b10101 !
b10101 0
1&
b101001 '
#42000000
b11 2
b10101 .
b10110 /
b10101 -
b10101 )
b10101 !
b10101 0
b10101 %
0&
b101010 '
#43000000
b10110 !
b10110 0
1&
b101011 '
#44000000
b1 2
b10110 .
b10111 /
b10110 -
b10110 )
b10110 !
b10110 0
b10110 %
0&
b101100 '
#45000000
b10111 !
b10111 0
1&
b101101 '
#46000000
b1111 2
b10111 .
b11000 /
b10111 -
b10111 )
b10111 !
b10111 0
b10111 %
0&
b101110 '
#47000000
b11000 !
b11000 0
1&
b101111 '
#48000000
b1 2
b11000 .
b11001 /
b11000 -
b11000 )
b11000 !
b11000 0
b11000 %
0&
b110000 '
#49000000
b11001 !
b11001 0
1&
b110001 '
#50000000
b11 2
b11001 .
b11010 /
b11001 -
b11001 )
b11001 !
b11001 0
b11001 %
0&
b110010 '
#51000000
b11010 !
b11010 0
1&
b110011 '
#52000000
b1 2
b11010 .
b11011 /
b11010 -
b11010 )
b11010 !
b11010 0
b11010 %
0&
b110100 '
#53000000
b11011 !
b11011 0
1&
b110101 '
#54000000
b111 2
b11011 .
b11100 /
b11011 -
b11011 )
b11011 !
b11011 0
b11011 %
0&
b110110 '
#55000000
b11100 !
b11100 0
1&
b110111 '
#56000000
b1 2
b11100 .
b11101 /
b11100 -
b11100 )
b11100 !
b11100 0
b11100 %
0&
b111000 '
#57000000
b11101 !
b11101 0
1&
b111001 '
#58000000
b11 2
b11101 .
b11110 /
b11101 -
b11101 )
b11101 !
b11101 0
b11101 %
0&
b111010 '
#59000000
b11110 !
b11110 0
1&
b111011 '
#60000000
b1 2
b11110 .
b11111 /
b11110 -
b11110 )
b11110 !
b11110 0
b11110 %
0&
b111100 '
#61000000
b11111 !
b11111 0
1&
b111101 '
#62000000
b111111 2
b11111 .
b100000 /
b11111 -
b11111 )
b11111 !
b11111 0
b11111 %
0&
b111110 '
#63000000
b100000 !
b100000 0
1&
b111111 '
#64000000
b1 2
b100000 .
b100001 /
b100000 -
b100000 )
b100000 !
b100000 0
b100000 %
0&
b1000000 '
#65000000
b100001 !
b100001 0
1&
b1000001 '
#66000000
b11 2
b100001 .
b100010 /
b100001 -
b100001 )
b100001 !
b100001 0
b100001 %
0&
b1000010 '
#67000000
b100010 !
b100010 0
1&
b1000011 '
#68000000
b1 2
b100010 .
b100011 /
b100010 -
b100010 )
b100010 !
b100010 0
b100010 %
0&
b1000100 '
#69000000
b100011 !
b100011 0
1&
b1000101 '
#70000000
b111 2
b100011 .
b100100 /
b100011 -
b100011 )
b100011 !
b100011 0
b100011 %
0&
b1000110 '
#71000000
b100100 !
b100100 0
1&
b1000111 '
#72000000
b1 2
b100100 .
b100101 /
b100100 -
b100100 )
b100100 !
b100100 0
b100100 %
0&
b1001000 '
#73000000
b100101 !
b100101 0
1&
b1001001 '
#74000000
b11 2
b100101 .
b100110 /
b100101 -
b100101 )
b100101 !
b100101 0
b100101 %
0&
b1001010 '
#75000000
b100110 !
b100110 0
1&
b1001011 '
#76000000
b1 2
b100110 .
b100111 /
b100110 -
b100110 )
b100110 !
b100110 0
b100110 %
0&
b1001100 '
#77000000
b100111 !
b100111 0
1&
b1001101 '
#78000000
b1111 2
b100111 .
b101000 /
b100111 -
b100111 )
b100111 !
b100111 0
b100111 %
0&
b1001110 '
#79000000
b101000 !
b101000 0
1&
b1001111 '
#80000000
b1 2
b101000 .
b101001 /
b101000 -
b101000 )
b101000 !
b101000 0
b101000 %
0&
b1010000 '
#81000000
b101001 !
b101001 0
1&
b1010001 '
#82000000
b11 2
b101001 .
b101010 /
b101001 -
b101001 )
b101001 !
b101001 0
b101001 %
0&
b1010010 '
#83000000
b101010 !
b101010 0
1&
b1010011 '
#84000000
b1 2
b101010 .
b101011 /
b101010 -
b101010 )
b101010 !
b101010 0
b101010 %
0&
b1010100 '
#85000000
b101011 !
b101011 0
1&
b1010101 '
#86000000
b111 2
b101011 .
b101100 /
b101011 -
b101011 )
b101011 !
b101011 0
b101011 %
0&
b1010110 '
#87000000
b101100 !
b101100 0
1&
b1010111 '
#88000000
b1 2
b101100 .
b101101 /
b101100 -
b101100 )
b101100 !
b101100 0
b101100 %
0&
b1011000 '
#89000000
b101101 !
b101101 0
1&
b1011001 '
#90000000
b11 2
b101101 .
b101110 /
b101101 -
b101101 )
b101101 !
b101101 0
b101101 %
0&
b1011010 '
#91000000
b101110 !
b101110 0
1&
b1011011 '
#92000000
b1 2
b101110 .
b101111 /
b101110 -
b101110 )
b101110 !
b101110 0
b101110 %
0&
b1011100 '
#93000000
b101111 !
b101111 0
1&
b1011101 '
#94000000
b11111 2
b101111 .
b110000 /
b101111 -
b101111 )
b101111 !
b101111 0
b101111 %
0&
b1011110 '
#95000000
b110000 !
b110000 0
1&
b1011111 '
#96000000
b1 2
b110000 .
b110001 /
b110000 -
b110000 )
b110000 !
b110000 0
b110000 %
0&
b1100000 '
#97000000
b110001 !
b110001 0
1&
b1100001 '
#98000000
b11 2
b110001 .
b110010 /
b110001 -
b110001 )
b110001 !
b110001 0
b110001 %
0&
b1100010 '
#99000000
b110010 !
b110010 0
1&
b1100011 '
#100000000
b1 2
b110010 .
b110011 /
b110010 -
b110010 )
b110010 !
b110010 0
b110010 %
0&
b1100100 '
#101000000
b110011 !
b110011 0
1&
b1100101 '
#102000000
b111 2
b110011 .
b110100 /
b110011 -
b110011 )
b110011 !
b110011 0
b110011 %
0&
b1100110 '
#103000000
b110100 !
b110100 0
1&
b1100111 '
#104000000
b1 2
b110100 .
b110101 /
b110100 -
b110100 )
b110100 !
b110100 0
b110100 %
0&
b1101000 '
#105000000
b110101 !
b110101 0
1&
b1101001 '
#106000000
b11 2
b110101 .
b110110 /
b110101 -
b110101 )
b110101 !
b110101 0
b110101 %
0&
b1101010 '
#107000000
b110110 !
b110110 0
1&
b1101011 '
#108000000
b1 2
b110110 .
b110111 /
b110110 -
b110110 )
b110110 !
b110110 0
b110110 %
0&
b1101100 '
#109000000
b110111 !
b110111 0
1&
b1101101 '
#110000000
b1111 2
b110111 .
b111000 /
b110111 -
b110111 )
b110111 !
b110111 0
b110111 %
0&
b1101110 '
#111000000
b111000 !
b111000 0
1&
b1101111 '
#112000000
b1 2
b111000 .
b111001 /
b111000 -
b111000 )
b111000 !
b111000 0
b111000 %
0&
b1110000 '
#113000000
b111001 !
b111001 0
1&
b1110001 '
#114000000
b11 2
b111001 .
b111010 /
b111001 -
b111001 )
b111001 !
b111001 0
b111001 %
0&
b1110010 '
#115000000
b111010 !
b111010 0
1&
b1110011 '
#116000000
b1 2
b111010 .
b111011 /
b111010 -
b111010 )
b111010 !
b111010 0
b111010 %
0&
b1110100 '
#117000000
b111011 !
b111011 0
1&
b1110101 '
#118000000
b111 2
b111011 .
b111100 /
b111011 -
b111011 )
b111011 !
b111011 0
b111011 %
0&
b1110110 '
#119000000
b111100 !
b111100 0
1&
b1110111 '
#120000000
b1 2
b111100 .
b111101 /
b111100 -
b111100 )
b111100 !
b111100 0
b111100 %
0&
b1111000 '
#121000000
b111101 !
b111101 0
1&
b1111001 '
#122000000
b11 2
b111101 .
b111110 /
b111101 -
b111101 )
b111101 !
b111101 0
b111101 %
0&
b1111010 '
#123000000
b111110 !
b111110 0
1&
b1111011 '
#124000000
b1 2
b111110 .
b111111 /
b111110 -
b111110 )
b111110 !
b111110 0
b111110 %
0&
b1111100 '
#125000000
b111111 !
b111111 0
1&
b1111101 '
#126000000
b1111111 2
b111111 .
b1000000 /
b111111 -
b111111 )
b111111 !
b111111 0
b111111 %
0&
b1111110 '
#127000000
b1000000 !
b1000000 0
1&
b1111111 '
#128000000
b1 2
b1000000 .
b1000001 /
b1000000 -
b1000000 )
b1000000 !
b1000000 0
b1000000 %
0&
b10000000 '
#129000000
b1000001 !
b1000001 0
1&
b10000001 '
#130000000
b11 2
b1000001 .
b1000010 /
b1000001 -
b1000001 )
b1000001 !
b1000001 0
b1000001 %
0&
b10000010 '
#131000000
b1000010 !
b1000010 0
1&
b10000011 '
#132000000
b1 2
b1000010 .
b1000011 /
b1000010 -
b1000010 )
b1000010 !
b1000010 0
b1000010 %
0&
b10000100 '
#133000000
b1000011 !
b1000011 0
1&
b10000101 '
#134000000
b111 2
b1000011 .
b1000100 /
b1000011 -
b1000011 )
b1000011 !
b1000011 0
b1000011 %
0&
b10000110 '
#135000000
b1000100 !
b1000100 0
1&
b10000111 '
#136000000
b1 2
b1000100 .
b1000101 /
b1000100 -
b1000100 )
b1000100 !
b1000100 0
b1000100 %
0&
b10001000 '
#137000000
b1000101 !
b1000101 0
1&
b10001001 '
#138000000
b11 2
b1000101 .
b1000110 /
b1000101 -
b1000101 )
b1000101 !
b1000101 0
b1000101 %
0&
b10001010 '
#139000000
b1000110 !
b1000110 0
1&
b10001011 '
#140000000
b1 2
b1000110 .
b1000111 /
b1000110 -
b1000110 )
b1000110 !
b1000110 0
b1000110 %
0&
b10001100 '
#141000000
b1000111 !
b1000111 0
1&
b10001101 '
#142000000
b1111 2
b1000111 .
b1001000 /
b1000111 -
b1000111 )
b1000111 !
b1000111 0
b1000111 %
0&
b10001110 '
#143000000
b1001000 !
b1001000 0
1&
b10001111 '
#144000000
b1 2
b1001000 .
b1001001 /
b1001000 -
b1001000 )
b1001000 !
b1001000 0
b1001000 %
0&
b10010000 '
#145000000
b1001001 !
b1001001 0
1&
b10010001 '
#146000000
b11 2
b1001001 .
b1001010 /
b1001001 -
b1001001 )
b1001001 !
b1001001 0
b1001001 %
0&
b10010010 '
#147000000
b1001010 !
b1001010 0
1&
b10010011 '
#148000000
b1 2
b1001010 .
b1001011 /
b1001010 -
b1001010 )
b1001010 !
b1001010 0
b1001010 %
0&
b10010100 '
#149000000
b1001011 !
b1001011 0
1&
b10010101 '
#150000000
b111 2
b1001011 .
b1001100 /
b1001011 -
b1001011 )
b1001011 !
b1001011 0
b1001011 %
0&
b10010110 '
#151000000
b1001100 !
b1001100 0
1&
b10010111 '
#152000000
b1 2
b1001100 .
b1001101 /
b1001100 -
b1001100 )
b1001100 !
b1001100 0
b1001100 %
0&
b10011000 '
#153000000
b1001101 !
b1001101 0
1&
b10011001 '
#154000000
b11 2
b1001101 .
b1001110 /
b1001101 -
b1001101 )
b1001101 !
b1001101 0
b1001101 %
0&
b10011010 '
#155000000
b1001110 !
b1001110 0
1&
b10011011 '
#156000000
b1 2
b1001110 .
b1001111 /
b1001110 -
b1001110 )
b1001110 !
b1001110 0
b1001110 %
0&
b10011100 '
#157000000
b1001111 !
b1001111 0
1&
b10011101 '
#158000000
b11111 2
b1001111 .
b1010000 /
b1001111 -
b1001111 )
b1001111 !
b1001111 0
b1001111 %
0&
b10011110 '
#159000000
b1010000 !
b1010000 0
1&
b10011111 '
#160000000
b1 2
b1010000 .
b1010001 /
b1010000 -
b1010000 )
b1010000 !
b1010000 0
b1010000 %
0&
b10100000 '
#161000000
b1010001 !
b1010001 0
1&
b10100001 '
#162000000
b11 2
b1010001 .
b1010010 /
b1010001 -
b1010001 )
b1010001 !
b1010001 0
b1010001 %
0&
b10100010 '
#163000000
b1010010 !
b1010010 0
1&
b10100011 '
#164000000
b1 2
b1010010 .
b1010011 /
b1010010 -
b1010010 )
b1010010 !
b1010010 0
b1010010 %
0&
b10100100 '
#165000000
b1010011 !
b1010011 0
1&
b10100101 '
#166000000
b111 2
b1010011 .
b1010100 /
b1010011 -
b1010011 )
b1010011 !
b1010011 0
b1010011 %
0&
b10100110 '
#167000000
b1010100 !
b1010100 0
1&
b10100111 '
#168000000
b1 2
b1010100 .
b1010101 /
b1010100 -
b1010100 )
b1010100 !
b1010100 0
b1010100 %
0&
b10101000 '
#169000000
b1010101 !
b1010101 0
1&
b10101001 '
#170000000
b11 2
b1010101 .
b1010110 /
b1010101 -
b1010101 )
b1010101 !
b1010101 0
b1010101 %
0&
b10101010 '
#171000000
b1010110 !
b1010110 0
1&
b10101011 '
#172000000
b1 2
b1010110 .
b1010111 /
b1010110 -
b1010110 )
b1010110 !
b1010110 0
b1010110 %
0&
b10101100 '
#173000000
b1010111 !
b1010111 0
1&
b10101101 '
#174000000
b1111 2
b1010111 .
b1011000 /
b1010111 -
b1010111 )
b1010111 !
b1010111 0
b1010111 %
0&
b10101110 '
#175000000
b1011000 !
b1011000 0
1&
b10101111 '
#176000000
b1 2
b1011000 .
b1011001 /
b1011000 -
b1011000 )
b1011000 !
b1011000 0
b1011000 %
0&
b10110000 '
#177000000
b1011001 !
b1011001 0
1&
b10110001 '
#178000000
b11 2
b1011001 .
b1011010 /
b1011001 -
b1011001 )
b1011001 !
b1011001 0
b1011001 %
0&
b10110010 '
#179000000
b1011010 !
b1011010 0
1&
b10110011 '
#180000000
b1 2
b1011010 .
b1011011 /
b1011010 -
b1011010 )
b1011010 !
b1011010 0
b1011010 %
0&
b10110100 '
#181000000
b1011011 !
b1011011 0
1&
b10110101 '
#182000000
b111 2
b1011011 .
b1011100 /
b1011011 -
b1011011 )
b1011011 !
b1011011 0
b1011011 %
0&
b10110110 '
#183000000
b1011100 !
b1011100 0
1&
b10110111 '
#184000000
b1 2
b1011100 .
b1011101 /
b1011100 -
b1011100 )
b1011100 !
b1011100 0
b1011100 %
0&
b10111000 '
#185000000
b1011101 !
b1011101 0
1&
b10111001 '
#186000000
b11 2
b1011101 .
b1011110 /
b1011101 -
b1011101 )
b1011101 !
b1011101 0
b1011101 %
0&
b10111010 '
#187000000
b1011110 !
b1011110 0
1&
b10111011 '
#188000000
b1 2
b1011110 .
b1011111 /
b1011110 -
b1011110 )
b1011110 !
b1011110 0
b1011110 %
0&
b10111100 '
#189000000
b1011111 !
b1011111 0
1&
b10111101 '
#190000000
b111111 2
b1011111 .
b1100000 /
b1011111 -
b1011111 )
b1011111 !
b1011111 0
b1011111 %
0&
b10111110 '
#191000000
b1100000 !
b1100000 0
1&
b10111111 '
#192000000
b1 2
b1100000 .
b1100001 /
b1100000 -
b1100000 )
b1100000 !
b1100000 0
b1100000 %
0&
b11000000 '
#193000000
b1100001 !
b1100001 0
1&
b11000001 '
#194000000
b11 2
b1100001 .
b1100010 /
b1100001 -
b1100001 )
b1100001 !
b1100001 0
b1100001 %
0&
b11000010 '
#195000000
b1100010 !
b1100010 0
1&
b11000011 '
#196000000
b1 2
b1100010 .
b1100011 /
b1100010 -
b1100010 )
b1100010 !
b1100010 0
b1100010 %
0&
b11000100 '
#197000000
b1100011 !
b1100011 0
1&
b11000101 '
#198000000
b111 2
b1100011 .
b1100100 /
b1100011 -
b1100011 )
b1100011 !
b1100011 0
b1100011 %
0&
b11000110 '
#199000000
b1100100 !
b1100100 0
1&
b11000111 '
#200000000
b1 2
b1100100 .
b1100101 /
b1100100 -
b1100100 )
b1100100 !
b1100100 0
b1100100 %
0&
b11001000 '
#201000000
b1100101 !
b1100101 0
1&
b11001001 '
#202000000
b11 2
b1100101 .
b1100110 /
b1100101 -
b1100101 )
b1100101 !
b1100101 0
b1100101 %
0&
b11001010 '
#203000000
b1100110 !
b1100110 0
1&
b11001011 '
#204000000
b1 2
b1100110 .
b1100111 /
b1100110 -
b1100110 )
b1100110 !
b1100110 0
b1100110 %
0&
b11001100 '
#205000000
b1100111 !
b1100111 0
1&
b11001101 '
#206000000
b1111 2
b1100111 .
b1101000 /
b1100111 -
b1100111 )
b1100111 !
b1100111 0
b1100111 %
0&
b11001110 '
#207000000
b1101000 !
b1101000 0
1&
b11001111 '
#208000000
b1 2
b1101000 .
b1101001 /
b1101000 -
b1101000 )
b1101000 !
b1101000 0
b1101000 %
0&
b11010000 '
#209000000
b1101001 !
b1101001 0
1&
b11010001 '
#210000000
b11 2
b1101001 .
b1101010 /
b1101001 -
b1101001 )
b1101001 !
b1101001 0
b1101001 %
0&
b11010010 '
#211000000
b1101010 !
b1101010 0
1&
b11010011 '
#212000000
b1 2
b1101010 .
b1101011 /
b1101010 -
b1101010 )
b1101010 !
b1101010 0
b1101010 %
0&
b11010100 '
#213000000
b1101011 !
b1101011 0
1&
b11010101 '
#214000000
b111 2
b1101011 .
b1101100 /
b1101011 -
b1101011 )
b1101011 !
b1101011 0
b1101011 %
0&
b11010110 '
#215000000
b1101100 !
b1101100 0
1&
b11010111 '
#216000000
b1 2
b1101100 .
b1101101 /
b1101100 -
b1101100 )
b1101100 !
b1101100 0
b1101100 %
0&
b11011000 '
#217000000
b1101101 !
b1101101 0
1&
b11011001 '
#218000000
b11 2
b1101101 .
b1101110 /
b1101101 -
b1101101 )
b1101101 !
b1101101 0
b1101101 %
0&
b11011010 '
#219000000
b1101110 !
b1101110 0
1&
b11011011 '
#220000000
b1 2
b1101110 .
b1101111 /
b1101110 -
b1101110 )
b1101110 !
b1101110 0
b1101110 %
0&
b11011100 '
#221000000
b1101111 !
b1101111 0
1&
b11011101 '
#222000000
b11111 2
b1101111 .
b1110000 /
b1101111 -
b1101111 )
b1101111 !
b1101111 0
b1101111 %
0&
b11011110 '
#223000000
b1110000 !
b1110000 0
1&
b11011111 '
#224000000
b1 2
b1110000 .
b1110001 /
b1110000 -
b1110000 )
b1110000 !
b1110000 0
b1110000 %
0&
b11100000 '
#225000000
b1110001 !
b1110001 0
1&
b11100001 '
#226000000
b11 2
b1110001 .
b1110010 /
b1110001 -
b1110001 )
b1110001 !
b1110001 0
b1110001 %
0&
b11100010 '
#227000000
b1110010 !
b1110010 0
1&
b11100011 '
#228000000
b1 2
b1110010 .
b1110011 /
b1110010 -
b1110010 )
b1110010 !
b1110010 0
b1110010 %
0&
b11100100 '
#229000000
b1110011 !
b1110011 0
1&
b11100101 '
#230000000
b111 2
b1110011 .
b1110100 /
b1110011 -
b1110011 )
b1110011 !
b1110011 0
b1110011 %
0&
b11100110 '
#231000000
b1110100 !
b1110100 0
1&
b11100111 '
#232000000
b1 2
b1110100 .
b1110101 /
b1110100 -
b1110100 )
b1110100 !
b1110100 0
b1110100 %
0&
b11101000 '
#233000000
b1110101 !
b1110101 0
1&
b11101001 '
#234000000
b11 2
b1110101 .
b1110110 /
b1110101 -
b1110101 )
b1110101 !
b1110101 0
b1110101 %
0&
b11101010 '
#235000000
b1110110 !
b1110110 0
1&
b11101011 '
#236000000
b1 2
b1110110 .
b1110111 /
b1110110 -
b1110110 )
b1110110 !
b1110110 0
b1110110 %
0&
b11101100 '
#237000000
b1110111 !
b1110111 0
1&
b11101101 '
#238000000
b1111 2
b1110111 .
b1111000 /
b1110111 -
b1110111 )
b1110111 !
b1110111 0
b1110111 %
0&
b11101110 '
#239000000
b1111000 !
b1111000 0
1&
b11101111 '
#240000000
b1 2
b1111000 .
b1111001 /
b1111000 -
b1111000 )
b1111000 !
b1111000 0
b1111000 %
0&
b11110000 '
#241000000
b1111001 !
b1111001 0
1&
b11110001 '
#242000000
b11 2
b1111001 .
b1111010 /
b1111001 -
b1111001 )
b1111001 !
b1111001 0
b1111001 %
0&
b11110010 '
#243000000
b1111010 !
b1111010 0
1&
b11110011 '
#244000000
b1 2
b1111010 .
b1111011 /
b1111010 -
b1111010 )
b1111010 !
b1111010 0
b1111010 %
0&
b11110100 '
#245000000
b1111011 !
b1111011 0
1&
b11110101 '
#246000000
b111 2
b1111011 .
b1111100 /
b1111011 -
b1111011 )
b1111011 !
b1111011 0
b1111011 %
0&
b11110110 '
#247000000
b1111100 !
b1111100 0
1&
b11110111 '
#248000000
b1 2
b1111100 .
b1111101 /
b1111100 -
b1111100 )
b1111100 !
b1111100 0
b1111100 %
0&
b11111000 '
#249000000
b1111101 !
b1111101 0
1&
b11111001 '
#250000000
b11 2
b1111101 .
b1111110 /
b1111101 -
b1111101 )
b1111101 !
b1111101 0
b1111101 %
0&
b11111010 '
#251000000
b1111110 !
b1111110 0
1&
b11111011 '
#252000000
b1 2
b1111110 .
b1111111 /
b1111110 -
b1111110 )
b1111110 !
b1111110 0
b1111110 %
0&
b11111100 '
#253000000
b1111111 !
b1111111 0
1&
b11111101 '
#254000000
b11111111 2
b1111111 .
b10000000 /
b1111111 -
b1111111 )
b1111111 !
b1111111 0
b1111111 %
0&
b11111110 '
#255000000
b10000000 !
b10000000 0
1&
b11111111 '
#256000000
b1 2
0+
b10000000 .
b10000001 /
b10000000 -
b10000000 )
b10000000 !
b10000000 0
b10000000 %
0&
b100000000 '
#257000000
b10000001 !
b10000001 0
1&
b100000001 '
#258000000
b11 2
b10000001 .
b10000010 /
b10000001 -
b10000001 )
b10000001 !
b10000001 0
b10000001 %
0&
b100000010 '
#259000000
b10000010 !
b10000010 0
1&
b100000011 '
#260000000
b1 2
b10000010 .
b10000011 /
b10000010 -
b10000010 )
b10000010 !
b10000010 0
b10000010 %
0&
b100000100 '
#261000000
b10000011 !
b10000011 0
1&
b100000101 '
