assignment2/cra.v
module cra(
    input a, b, cin,
    output sum, cout
);
    assign sum = a ^ b ^ cin;
    assign cout = (a & b) | (b & cin) | (a & cin);
endmodule

assignment 2/cratb.v
`timescale 1ns/1ps
module cratb;
    reg [7:0] a, b;
    reg cin;
    wire [7:0] sum;
    wire cout;
    wire [6:0] c ;

    
    cra cra0(
        .a(a[0]), .b(b[0]), .cin(cin), .sum(sum[0]), .cout(c[0])
    );
    cra cra1(
        .a(a[1]), .b(b[1]), .cin(c[0]), .sum(sum[1]), .cout(c[1])
    );
    cra cra2(
        .a(a[2]), .b(b[2]), .cin(c[1]), .sum(sum[2]), .cout(c[2])
    );
    cra cra3(
        .a(a[3]), .b(b[3]), .cin(c[2]), .sum(sum[3]), .cout(c[3])
    );
    cra cra4(
        .a(a[4]), .b(b[4]), .cin(c[3]), .sum(sum[4]), .cout(c[4])
    );
    cra cra5(
        .a(a[5]), .b(b[5]), .cin(c[4]), .sum(sum[5]), .cout(c[5])
    );
    cra cra6(
        .a(a[6]), .b(b[6]), .cin(c[5]), .sum(sum[6]), .cout(c[6])
    );  
    cra cra7(
        .a(a[7]), .b(b[7]), .cin(c[6]), .sum(sum[7]), .cout(cout)
    ); 
    integer i;
    initial begin 
        $dumpfile("cratb.vcd");
        $dumpvars(0, cratb);
        $display(" a  b  cin | sum cout");
        $display("----------------------");
        for (i =0; i<1026; i = i +1 ) 
        begin
            {a ,b , cin} = i;
            #1;
            $display("%b %b  %b  | %b  %b", a, b, cin, sum, cout);
            end
            $finish;
    end

endmodule

assignment 2/cratb.vcd
$date
	Wed Jun 04 21:48:29 2025
$end
$version
	Icarus Verilog
$end
$timescale
	1ps
$end
$scope module cratb $end
$var wire 8 ! sum [7:0] $end
$var wire 1 " cout $end
$var wire 7 # c [6:0] $end
$var reg 8 $ a [7:0] $end
$var reg 8 % b [7:0] $end
$var reg 1 & cin $end
$var integer 32 ' i [31:0] $end
$scope module cra0 $end
$var wire 1 ( a $end
$var wire 1 ) b $end
$var wire 1 & cin $end
$var wire 1 * cout $end
$var wire 1 + sum $end
$upscope $end
$scope module cra1 $end
$var wire 1 , a $end
$var wire 1 - b $end
$var wire 1 . cin $end
$var wire 1 / cout $end
$var wire 1 0 sum $end
$upscope $end
$scope module cra2 $end
$var wire 1 1 a $end
$var wire 1 2 b $end
$var wire 1 3 cin $end
$var wire 1 4 cout $end
$var wire 1 5 sum $end
$upscope $end
$scope module cra3 $end
$var wire 1 6 a $end
$var wire 1 7 b $end
$var wire 1 8 cin $end
$var wire 1 9 cout $end
$var wire 1 : sum $end
$upscope $end
$scope module cra4 $end
$var wire 1 ; a $end
$var wire 1 < b $end
$var wire 1 = cin $end
$var wire 1 > cout $end
$var wire 1 ? sum $end
$upscope $end
$scope module cra5 $end
$var wire 1 @ a $end
$var wire 1 A b $end
$var wire 1 B cin $end
$var wire 1 C cout $end
$var wire 1 D sum $end
$upscope $end
$scope module cra6 $end
$var wire 1 E a $end
$var wire 1 F b $end
$var wire 1 G cin $end
$var wire 1 H cout $end
$var wire 1 I sum $end
$upscope $end
$scope module cra7 $end
$var wire 1 J a $end
$var wire 1 K b $end
$var wire 1 L cin $end
$var wire 1 " cout $end
$var wire 1 M sum $end
$upscope $end
$upscope $end
$enddefinitions $end
$comment Show the parameter values. $end
$dumpall
$end
#0
$dumpvars
0M
0L
0K
0J
0I
0H
0G
0F
0E
0D
0C
0B
0A
0@
0?
0>
0=
0<
0;
0:
09
08
07
06
05
04
03
02
01
00
0/
0.
0-
0,
0+
0*
0)
0(
b0 '
0&
b0 %
b0 $
b0 #
0"
b0 !
$end
#1000
b1 !
1+
1&
b1 '
#2000
1)
b1 !
1+
b1 %
0&
b10 '
#3000
10
1.
b1 #
1*
b10 !
0+
1&
b11 '
#4000
05
03
0/
0.
10
b0 #
0*
0)
1-
b10 !
0+
b10 %
0&
b100 '
#5000
b11 !
1+
1&
b101 '
#6000
1)
b11 !
1+
b11 %
0&
b110 '
#7000
15
13
1/
00
1.
b11 #
1*
b100 !
0+
1&
b111 '
#8000
0:
03
08
0/
04
0.
00
15
b0 #
0*
0)
0-
12
b100 !
0+
b100 %
0&
b1000 '
#9000
b101 !
1+
1&
b1001 '
#10000
1)
b101 !
1+
b101 %
0&
b1010 '
#11000
10
1.
b1 #
1*
b110 !
0+
1&
b1011 '
#12000
0:
08
04
15
03
0/
0.
10
b0 #
0*
0)
1-
b110 !
0+
b110 %
0&
b1100 '
#13000
b111 !
1+
1&
b1101 '
#14000
1)
b111 !
1+
b111 %
0&
b1110 '
#15000
1:
18
14
05
13
1/
00
1.
b111 #
1*
b1000 !
0+
1&
b1111 '
#16000
0?
03
08
0=
0/
04
09
0.
00
05
1:
b0 #
0*
0)
0-
02
17
b1000 !
0+
b1000 %
0&
b10000 '
#17000
b1001 !
1+
1&
b10001 '
#18000
1)
b1001 !
1+
b1001 %
0&
b10010 '
#19000
10
1.
b1 #
1*
b1010 !
0+
1&
b10011 '
#20000
05
03
0/
0.
10
b0 #
0*
0)
1-
b1010 !
0+
b1010 %
0&
b10100 '
#21000
b1011 !
1+
1&
b10101 '
#22000
1)
b1011 !
1+
b1011 %
0&
b10110 '
#23000
15
13
1/
00
1.
b11 #
1*
b1100 !
0+
1&
b10111 '
#24000
0?
0=
09
1:
03
08
0/
04
0.
00
15
b0 #
0*
0)
0-
12
b1100 !
0+
b1100 %
0&
b11000 '
#25000
b1101 !
1+
1&
b11001 '
#26000
1)
b1101 !
1+
b1101 %
0&
b11010 '
#27000
10
1.
b1 #
1*
b1110 !
0+
1&
b11011 '
#28000
0?
0=
09
1:
08
04
15
03
0/
0.
10
b0 #
0*
0)
1-
b1110 !
0+
b1110 %
0&
b11100 '
#29000
b1111 !
1+
1&
b11101 '
#30000
1)
b1111 !
1+
b1111 %
0&
b11110 '
#31000
1?
1=
19
0:
18
14
05
13
1/
00
1.
b1111 #
1*
b10000 !
0+
1&
b11111 '
#32000
0D
03
08
0=
0B
0/
04
09
0>
0.
00
05
0:
1?
b0 #
0*
0)
0-
02
07
1<
b10000 !
0+
b10000 %
0&
b100000 '
#33000
b10001 !
1+
1&
b100001 '
#34000
1)
b10001 !
1+
b10001 %
0&
b100010 '
#35000
10
1.
b1 #
1*
b10010 !
0+
1&
b100011 '
#36000
05
03
0/
0.
10
b0 #
0*
0)
1-
b10010 !
0+
b10010 %
0&
b100100 '
#37000
b10011 !
1+
1&
b100101 '
#38000
1)
b10011 !
1+
b10011 %
0&
b100110 '
#39000
15
13
1/
00
1.
b11 #
1*
b10100 !
0+
1&
b100111 '
#40000
0:
03
08
0/
04
0.
00
15
b0 #
0*
0)
0-
12
b10100 !
0+
b10100 %
0&
b101000 '
#41000
b10101 !
1+
1&
b101001 '
#42000
1)
b10101 !
1+
b10101 %
0&
b101010 '
#43000
10
1.
b1 #
1*
b10110 !
0+
1&
b101011 '
#44000
0:
08
04
15
03
0/
0.
10
b0 #
0*
0)
1-
b10110 !
0+
b10110 %
0&
b101100 '
#45000
b10111 !
1+
1&
b101101 '
#46000
1)
b10111 !
1+
b10111 %
0&
b101110 '
#47000
1:
18
14
05
13
1/
00
1.
b111 #
1*
b11000 !
0+
1&
b101111 '
#48000
0D
0B
0>
1?
03
08
0=
0/
04
09
0.
00
05
1:
b0 #
0*
0)
0-
02
17
b11000 !
0+
b11000 %
0&
b110000 '
#49000
b11001 !
1+
1&
b110001 '
#50000
1)
b11001 !
1+
b11001 %
0&
b110010 '
#51000
10
1.
b1 #
1*
b11010 !
0+
1&
b110011 '
#52000
05
03
0/
0.
10
b0 #
0*
0)
1-
b11010 !
0+
b11010 %
0&
b110100 '
#53000
b11011 !
1+
1&
b110101 '
#54000
1)
b11011 !
1+
b11011 %
0&
b110110 '
#55000
15
13
1/
00
1.
b11 #
1*
b11100 !
0+
1&
b110111 '
#56000
0D
0B
0>
1?
0=
09
1:
03
08
0/
04
0.
00
15
b0 #
0*
0)
0-
12
b11100 !
0+
b11100 %
0&
b111000 '
#57000
b11101 !
1+
1&
b111001 '
#58000
1)
b11101 !
1+
b11101 %
0&
b111010 '
#59000
10
1.
b1 #
1*
b11110 !
0+
1&
b111011 '
#60000
0D
0B
0>
1?
0=
09
1:
08
04
15
03
0/
0.
10
b0 #
0*
0)
1-
b11110 !
0+
b11110 %
0&
b111100 '
#61000
b11111 !
1+
1&
b111101 '
#62000
1)
b11111 !
1+
b11111 %
0&
b111110 '
#63000
1D
1B
1>
0?
1=
19
0:
18
14
05
13
1/
00
1.
b11111 #
1*
b100000 !
0+
1&
b111111 '
#64000
0I
03
08
0=
0B
0G
0/
04
09
0>
0C
0.
00
05
0:
0?
1D
b0 #
0*
0)
0-
02
07
0<
1A
b100000 !
0+
b100000 %
0&
b1000000 '
#65000
b100001 !
1+
1&
b1000001 '
#66000
1)
b100001 !
1+
b100001 %
0&
b1000010 '
#67000
10
1.
b1 #
1*
b100010 !
0+
1&
b1000011 '
#68000
05
03
0/
0.
10
b0 #
0*
0)
1-
b100010 !
0+
b100010 %
0&
b1000100 '
#69000
b100011 !
1+
1&
b1000101 '
#70000
1)
b100011 !
1+
b100011 %
0&
b1000110 '
#71000
15
13
1/
00
1.
b11 #
1*
b100100 !
0+
1&
b1000111 '
#72000
0:
03
08
0/
04
0.
00
15
b0 #
0*
0)
0-
12
b100100 !
0+
b100100 %
0&
b1001000 '
#73000
b100101 !
1+
1&
b1001001 '
#74000
1)
b100101 !
1+
b100101 %
0&
b1001010 '
#75000
10
1.
b1 #
1*
b100110 !
0+
1&
b1001011 '
#76000
0:
08
04
15
03
0/
0.
10
b0 #
0*
0)
1-
b100110 !
0+
b100110 %
0&
b1001100 '
#77000
b100111 !
1+
1&
b1001101 '
#78000
1)
b100111 !
1+
b100111 %
0&
b1001110 '
#79000
1:
18
14
05
13
1/
00
1.
b111 #
1*
b101000 !
0+
1&
b1001111 '
#80000
0?
03
08
0=
0/
04
09
0.
00
05
1:
b0 #
0*
0)
0-
02
17
b101000 !
0+
b101000 %
0&
b1010000 '
#81000
b101001 !
1+
1&
b1010001 '
#82000
1)
b101001 !
1+
b101001 %
0&
b1010010 '
#83000
10
1.
b1 #
1*
b101010 !
0+
1&
b1010011 '
#84000
05
03
0/
0.
10
b0 #
0*
0)
1-
b101010 !
0+
b101010 %
0&
b1010100 '
#85000
b101011 !
1+
1&
b1010101 '
#86000
1)
b101011 !
1+
b101011 %
0&
b1010110 '
#87000
15
13
1/
00
1.
b11 #
1*
b101100 !
0+
1&
b1010111 '
#88000
0?
0=
09
1:
03
08
0/
04
0.
00
15
b0 #
0*
0)
0-
12
b101100 !
0+
b101100 %
0&
b1011000 '
#89000
b101101 !
1+
1&
b1011001 '
#90000
1)
b101101 !
1+
b101101 %
0&
b1011010 '
#91000
10
1.
b1 #
1*
b101110 !
0+
1&
b1011011 '
#92000
0?
0=
09
1:
08
04
15
03
0/
0.
10
b0 #
0*
0)
1-
b101110 !
0+
b101110 %
0&
b1011100 '
#93000
b101111 !
1+
1&
b1011101 '
#94000
1)
b101111 !
1+
b101111 %
0&
b1011110 '
#95000
1?
1=
19
0:
18
14
05
13
1/
00
1.
b1111 #
1*
b110000 !
0+
1&
b1011111 '
#96000
0I
0G
0C
1D
03
08
0=
0B
0/
04
09
0>
0.
00
05
0:
1?
b0 #
0*
0)
0-
02
07
1<
b110000 !
0+
b110000 %
0&
b1100000 '
#97000
b110001 !
1+
1&
b1100001 '
#98000
1)
b110001 !
1+
b110001 %
0&
b1100010 '
#99000
10
1.
b1 #
1*
b110010 !
0+
1&
b1100011 '
#100000
05
03
0/
0.
10
b0 #
0*
0)
1-
b110010 !
0+
b110010 %
0&
b1100100 '
#101000
b110011 !
1+
1&
b1100101 '
#102000
1)
b110011 !
1+
b110011 %
0&
b1100110 '
#103000
15
13
1/
00
1.
b11 #
1*
b110100 !
0+
1&
b1100111 '
#104000
0:
03
08
0/
04
0.
00
15
b0 #
0*
0)
0-
12
b110100 !
0+
b110100 %
0&
b1101000 '
#105000
b110101 !
1+
1&
b1101001 '
#106000
1)
b110101 !
1+
b110101 %
0&
b1101010 '
#107000
10
1.
b1 #
1*
b110110 !
0+
1&
b1101011 '
#108000
0:
08
04
15
03
0/
0.
10
b0 #
0*
0)
1-
b110110 !
0+
b110110 %
0&
b1101100 '
#109000
b110111 !
1+
1&
b1101101 '
#110000
1)
b110111 !
1+
b110111 %
0&
b1101110 '
#111000
1:
18
14
05
13
1/
00
1.
b111 #
1*
b111000 !
0+
1&
b1101111 '
#112000
0I
0G
0C
1D
0B
0>
1?
03
08
0=
0/
04
09
0.
00
05
1:
b0 #
0*
0)
0-
02
17
b111000 !
0+
b111000 %
0&
b1110000 '
#113000
b111001 !
1+
1&
b1110001 '
#114000
1)
b111001 !
1+
b111001 %
0&
b1110010 '
#115000
10
1.
b1 #
1*
b111010 !
0+
1&
b1110011 '
#116000
05
03
0/
0.
10
b0 #
0*
0)
1-
b111010 !
0+
b111010 %
0&
b1110100 '
#117000
b111011 !
1+
1&
b1110101 '
#118000
1)
b111011 !
1+
b111011 %
0&
b1110110 '
#119000
15
13
1/
00
1.
b11 #
1*
b111100 !
0+
1&
b1110111 '
#120000
0I
0G
0C
1D
0B
0>
1?
0=
09
1:
03
08
0/
04
0.
00
15
b0 #
0*
0)
0-
12
b111100 !
0+
b111100 %
0&
b1111000 '
#121000
b111101 !
1+
1&
b1111001 '
#122000
1)
b111101 !
1+
b111101 %
0&
b1111010 '
#123000
10
1.
b1 #
1*
b111110 !
0+
1&
b1111011 '
#124000
0I
0G
0C
1D
0B
0>
1?
0=
09
1:
08
04
15
03
0/
0.
10
b0 #
0*
0)
1-
b111110 !
0+
b111110 %
0&
b1111100 '
#125000
b111111 !
1+
1&
b1111101 '
#126000
1)
b111111 !
1+
b111111 %
0&
b1111110 '
#127000
1I
1G
1C
0D
1B
1>
0?
1=
19
0:
18
14
05
13
1/
00
1.
b111111 #
1*
b1000000 !
0+
1&
b1111111 '
#128000
0M
03
08
0=
0B
0G
0L
0/
04
09
0>
0C
0H
0.
00
05
0:
0?
0D
1I
b0 #
0*
0)
0-
02
07
0<
0A
1F
b1000000 !
0+
b1000000 %
0&
b10000000 '
#129000
b1000001 !
1+
1&
b10000001 '
#130000
1)
b1000001 !
1+
b1000001 %
0&
b10000010 '
#131000
10
1.
b1 #
1*
b1000010 !
0+
1&
b10000011 '
#132000
05
03
0/
0.
10
b0 #
0*
0)
1-
b1000010 !
0+
b1000010 %
0&
b10000100 '
#133000
b1000011 !
1+
1&
b10000101 '
#134000
1)
b1000011 !
1+
b1000011 %
0&
b10000110 '
#135000
15
13
1/
00
1.
b11 #
1*
b1000100 !
0+
1&
b10000111 '
#136000
0:
03
08
0/
04
0.
00
15
b0 #
0*
0)
0-
12
b1000100 !
0+
b1000100 %
0&
b10001000 '
#137000
b1000101 !
1+
1&
b10001001 '
#138000
1)
b1000101 !
1+
b1000101 %
0&
b10001010 '
#139000
10
1.
b1 #
1*
b1000110 !
0+
1&
b10001011 '
#140000
0:
08
04
15
03
0/
0.
10
b0 #
0*
0)
1-
b1000110 !
0+
b1000110 %
0&
b10001100 '
#141000
b1000111 !
1+
1&
b10001101 '
#142000
1)
b1000111 !
1+
b1000111 %
0&
b10001110 '
#143000
1:
18
14
05
13
1/
00
1.
b111 #
1*
b1001000 !
0+
1&
b10001111 '
#144000
0?
03
08
0=
0/
04
09
0.
00
05
1:
b0 #
0*
0)
0-
02
17
b1001000 !
0+
b1001000 %
0&
b10010000 '
#145000
b1001001 !
1+
1&
b10010001 '
#146000
1)
b1001001 !
1+
b1001001 %
0&
b10010010 '
#147000
10
1.
b1 #
1*
b1001010 !
0+
1&
b10010011 '
#148000
05
03
0/
0.
10
b0 #
0*
0)
1-
b1001010 !
0+
b1001010 %
0&
b10010100 '
#149000
b1001011 !
1+
1&
b10010101 '
#150000
1)
b1001011 !
1+
b1001011 %
0&
b10010110 '
#151000
15
13
1/
00
1.
b11 #
1*
b1001100 !
0+
1&
b10010111 '
#152000
0?
0=
09
1:
03
08
0/
04
0.
00
15
b0 #
0*
0)
0-
12
b1001100 !
0+
b1001100 %
0&
b10011000 '
#153000
b1001101 !
1+
1&
b10011001 '
#154000
1)
b1001101 !
1+
b1001101 %
0&
b10011010 '
#155000
10
1.
b1 #
1*
b1001110 !
0+
1&
b10011011 '
#156000
0?
0=
09
1:
08
04
15
03
0/
0.
10
b0 #
0*
0)
1-
b1001110 !
0+
b1001110 %
0&
b10011100 '
#157000
b1001111 !
1+
1&
b10011101 '
#158000
1)
b1001111 !
1+
b1001111 %
0&
b10011110 '
#159000
1?
1=
19
0:
18
14
05
13
1/
00
1.
b1111 #
1*
b1010000 !
0+
1&
b10011111 '
#160000
0D
03
08
0=
0B
0/
04
09
0>
0.
00
05
0:
1?
b0 #
0*
0)
0-
02
07
1<
b1010000 !
0+
b1010000 %
0&
b10100000 '
#161000
b1010001 !
1+
1&
b10100001 '
#162000
1)
b1010001 !
1+
b1010001 %
0&
b10100010 '
#163000
10
1.
b1 #
1*
b1010010 !
0+
1&
b10100011 '
#164000
05
03
0/
0.
10
b0 #
0*
0)
1-
b1010010 !
0+
b1010010 %
0&
b10100100 '
#165000
b1010011 !
1+
1&
b10100101 '
#166000
1)
b1010011 !
1+
b1010011 %
0&
b10100110 '
#167000
15
13
1/
00
1.
b11 #
1*
b1010100 !
0+
1&
b10100111 '
#168000
0:
03
08
0/
04
0.
00
15
b0 #
0*
0)
0-
12
b1010100 !
0+
b1010100 %
0&
b10101000 '
#169000
b1010101 !
1+
1&
b10101001 '
#170000
1)
b1010101 !
1+
b1010101 %
0&
b10101010 '
#171000
10
1.
b1 #
1*
b1010110 !
0+
1&
b10101011 '
#172000
0:
08
04
15
03
0/
0.
10
b0 #
0*
0)
1-
b1010110 !
0+
b1010110 %
0&
b10101100 '
#173000
b1010111 !
1+
1&
b10101101 '
#174000
1)
b1010111 !
1+
b1010111 %
0&
b10101110 '
#175000
1:
18
14
05
13
1/
00
1.
b111 #
1*
b1011000 !
0+
1&
b10101111 '
#176000
0D
0B
0>
1?
03
08
0=
0/
04
09
0.
00
05
1:
b0 #
0*
0)
0-
02
17
b1011000 !
0+
b1011000 %
0&
b10110000 '
#177000
b1011001 !
1+
1&
b10110001 '
#178000
1)
b1011001 !
1+
b1011001 %
0&
b10110010 '
#179000
10
1.
b1 #
1*
b1011010 !
0+
1&
b10110011 '
#180000
05
03
0/
0.
10
b0 #
0*
0)
1-
b1011010 !
0+
b1011010 %
0&
b10110100 '
#181000
b1011011 !
1+
1&
b10110101 '
#182000
1)
b1011011 !
1+
b1011011 %
0&
b10110110 '
#183000
15
13
1/
00
1.
b11 #
1*
b1011100 !
0+
1&
b10110111 '
#184000
0D
0B
0>
1?
0=
09
1:
03
08
0/
04
0.
00
15
b0 #
0*
0)
0-
12
b1011100 !
0+
b1011100 %
0&
b10111000 '
#185000
b1011101 !
1+
1&
b10111001 '
#186000
1)
b1011101 !
1+
b1011101 %
0&
b10111010 '
#187000
10
1.
b1 #
1*
b1011110 !
0+
1&
b10111011 '
#188000
0D
0B
0>
1?
0=
09
1:
08
04
15
03
0/
0.
10
b0 #
0*
0)
1-
b1011110 !
0+
b1011110 %
0&
b10111100 '
#189000
b1011111 !
1+
1&
b10111101 '
#190000
1)
b1011111 !
1+
b1011111 %
0&
b10111110 '
#191000
1D
1B
1>
0?
1=
19
0:
18
14
05
13
1/
00
1.
b11111 #
1*
b1100000 !
0+
1&
b10111111 '
#192000
0M
0L
0H
1I
03
08
0=
0B
0G
0/
04
09
0>
0C
0.
00
05
0:
0?
1D
b0 #
0*
0)
0-
02
07
0<
1A
b1100000 !
0+
b1100000 %
0&
b11000000 '
#193000
b1100001 !
1+
1&
b11000001 '
#194000
1)
b1100001 !
1+
b1100001 %
0&
b11000010 '
#195000
10
1.
b1 #
1*
b1100010 !
0+
1&
b11000011 '
#196000
05
03
0/
0.
10
b0 #
0*
0)
1-
b1100010 !
0+
b1100010 %
0&
b11000100 '
#197000
b1100011 !
1+
1&
b11000101 '
#198000
1)
b1100011 !
1+
b1100011 %
0&
b11000110 '
#199000
15
13
1/
00
1.
b11 #
1*
b1100100 !
0+
1&
b11000111 '
#200000
0:
03
08
0/
04
0.
00
15
b0 #
0*
0)
0-
12
b1100100 !
0+
b1100100 %
0&
b11001000 '
#201000
b1100101 !
1+
1&
b11001001 '
#202000
1)
b1100101 !
1+
b1100101 %
0&
b11001010 '
#203000
10
1.
b1 #
1*
b1100110 !
0+
1&
b11001011 '
#204000
0:
08
04
15
03
0/
0.
10
b0 #
0*
0)
1-
b1100110 !
0+
b1100110 %
0&
b11001100 '
#205000
b1100111 !
1+
1&
b11001101 '
#206000
1)
b1100111 !
1+
b1100111 %
0&
b11001110 '
#207000
1:
18
14
05
13
1/
00
1.
b111 #
1*
b1101000 !
0+
1&
b11001111 '
#208000
0?
03
08
0=
0/
04
09
0.
00
05
1:
b0 #
0*
0)
0-
02
17
b1101000 !
0+
b1101000 %
0&
b11010000 '
#209000
b1101001 !
1+
1&
b11010001 '
#210000
1)
b1101001 !
1+
b1101001 %
0&
b11010010 '
#211000
10
1.
b1 #
1*
b1101010 !
0+
1&
b11010011 '
#212000
05
03
0/
0.
10
b0 #
0*
0)
1-
b1101010 !
0+
b1101010 %
0&
b11010100 '
#213000
b1101011 !
1+
1&
b11010101 '
#214000
1)
b1101011 !
1+
b1101011 %
0&
b11010110 '
#215000
15
13
1/
00
1.
b11 #
1*
b1101100 !
0+
1&
b11010111 '
#216000
0?
0=
09
1:
03
08
0/
04
0.
00
15
b0 #
0*
0)
0-
12
b1101100 !
0+
b1101100 %
0&
b11011000 '
#217000
b1101101 !
1+
1&
b11011001 '
#218000
1)
b1101101 !
1+
b1101101 %
0&
b11011010 '
#219000
10
1.
b1 #
1*
b1101110 !
0+
1&
b11011011 '
#220000
0?
0=
09
1:
08
04
15
03
0/
0.
10
b0 #
0*
0)
1-
b1101110 !
0+
b1101110 %
0&
b11011100 '
#221000
b1101111 !
1+
1&
b11011101 '
#222000
1)
b1101111 !
1+
b1101111 %
0&
b11011110 '
#223000
1?
1=
19
0:
18
14
05
13
1/
00
1.
b1111 #
1*
b1110000 !
0+
1&
b11011111 '
#224000
0M
0L
0H
1I
0G
0C
1D
03
08
0=
0B
0/
04
09
0>
0.
00
05
0:
1?
b0 #
0*
0)
0-
02
07
1<
b1110000 !
0+
b1110000 %
0&
b11100000 '
#225000
b1110001 !
1+
1&
b11100001 '
#226000
1)
b1110001 !
1+
b1110001 %
0&
b11100010 '
#227000
10
1.
b1 #
1*
b1110010 !
0+
1&
b11100011 '
#228000
05
03
0/
0.
10
b0 #
0*
0)
1-
b1110010 !
0+
b1110010 %
0&
b11100100 '
#229000
b1110011 !
1+
1&
b11100101 '
#230000
1)
b1110011 !
1+
b1110011 %
0&
b11100110 '
#231000
15
13
1/
00
1.
b11 #
1*
b1110100 !
0+
1&
b11100111 '
#232000
0:
03
08
0/
04
0.
00
15
b0 #
0*
0)
0-
12
b1110100 !
0+
b1110100 %
0&
b11101000 '
#233000
b1110101 !
1+
1&
b11101001 '
#234000
1)
b1110101 !
1+
b1110101 %
0&
b11101010 '
#235000
10
1.
b1 #
1*
b1110110 !
0+
1&
b11101011 '
#236000
0:
08
04
15
03
0/
0.
10
b0 #
0*
0)
1-
b1110110 !
0+
b1110110 %
0&
b11101100 '
#237000
b1110111 !
1+
1&
b11101101 '
#238000
1)
b1110111 !
1+
b1110111 %
0&
b11101110 '
#239000
1:
18
14
05
13
1/
00
1.
b111 #
1*
b1111000 !
0+
1&
b11101111 '
#240000
0M
0L
0H
1I
0G
0C
1D
0B
0>
1?
03
08
0=
0/
04
09
0.
00
05
1:
b0 #
0*
0)
0-
02
17
b1111000 !
0+
b1111000 %
0&
b11110000 '
#241000
b1111001 !
1+
1&
b11110001 '
#242000
1)
b1111001 !
1+
b1111001 %
0&
b11110010 '
#243000
10
1.
b1 #
1*
b1111010 !
0+
1&
b11110011 '
#244000
05
03
0/
0.
10
b0 #
0*
0)
1-
b1111010 !
0+
b1111010 %
0&
b11110100 '
#245000
b1111011 !
1+
1&
b11110101 '
#246000
1)
b1111011 !
1+
b1111011 %
0&
b11110110 '
#247000
15
13
1/
00
1.
b11 #
1*
b1111100 !
0+
1&
b11110111 '
#248000
0M
0L
0H
1I
0G
0C
1D
0B
0>
1?
0=
09
1:
03
08
0/
04
0.
00
15
b0 #
0*
0)
0-
12
b1111100 !
0+
b1111100 %
0&
b11111000 '
#249000
b1111101 !
1+
1&
b11111001 '
#250000
1)
b1111101 !
1+
b1111101 %
0&
b11111010 '
#251000
10
1.
b1 #
1*
b1111110 !
0+
1&
b11111011 '
#252000
0M
0L
0H
1I
0G
0C
1D
0B
0>
1?
0=
09
1:
08
04
15
03
0/
0.
10
b0 #
0*
0)
1-
b1111110 !
0+
b1111110 %
0&
b11111100 '
#253000
b1111111 !
1+
1&
b11111101 '
#254000
1)
b1111111 !
1+
b1111111 %
0&
b11111110 '
#255000
1M
1L
1H
0I
1G
1C
0D
1B
1>
0?
1=
19
0:
18
14
05
13
1/
00
1.
b1111111 #
1*
b10000000 !
0+
1&
b11111111 '
#256000
03
08
0=
0B
0G
0L
0/
04
09
0>
0C
0H
0"
0.
00
05
0:
0?
0D
0I
1M
b0 #
0*
0)
0-
02
07
0<
0A
0F
1K
b10000000 !
0+
b10000000 %
0&
b100000000 '
#257000
b10000001 !
1+
1&
b100000001 '
#258000
1)
b10000001 !
1+
b10000001 %
0&
b100000010 '
#259000
10
1.
b1 #
1*
b10000010 !
0+
1&
b100000011 '
#260000
05
03
0/
0.
10
b0 #
0*
0)
1-
b10000010 !
0+
b10000010 %
0&
b100000100 '
#261000
b10000011 !
1+
1&
b100000101 '
#262000
1)
b10000011 !
1+
b10000011 %
0&
b100000110 '
#263000
15
13
1/
00
1.
b11 #
1*
b10000100 !
0+
1&
b100000111 '
#264000
0:
03
08
0/
04
0.
00
15
b0 #
0*
0)
0-
12
b10000100 !
0+
b10000100 %
0&
b100001000 '
#265000
b10000101 !
1+
1&
b100001001 '
#266000
1)
b10000101 !
1+
b10000101 %
0&
b100001010 '
#267000
10
1.
b1 #
1*
b10000110 !
0+
1&
b100001011 '
#268000
0:
08
04
15
03
0/
0.
10
b0 #
0*
0)
1-
b10000110 !
0+
b10000110 %
0&
b100001100 '
#269000
b10000111 !
1+
1&
b100001101 '
#270000
1)
b10000111 !
1+
b10000111 %
0&
b100001110 '
#271000
1:
18
14
05
13
1/
00
1.
b111 #
1*
b10001000 !
0+
1&
b100001111 '
#272000
0?
03
08
0=
0/
04
09
0.
00
05
1:
b0 #
0*
0)
0-
02
17
b10001000 !
0+
b10001000 %
0&
b100010000 '
#273000
b10001001 !
1+
1&
b100010001 '
#274000
1)
b10001001 !
1+
b10001001 %
0&
b100010010 '
#275000
10
1.
b1 #
1*
b10001010 !
0+
1&
b100010011 '
#276000
05
03
0/
0.
10
b0 #
0*
0)
1-
b10001010 !
0+
b10001010 %
0&
b100010100 '
#277000
b10001011 !
1+
1&
b100010101 '
#278000
1)
b10001011 !
1+
b10001011 %
0&
b100010110 '
#279000
15
13
1/
00
1.
b11 #
1*
b10001100 !
0+
1&
b100010111 '
#280000
0?
0=
09
1:
03
08
0/
04
0.
00
15
b0 #
0*
0)
0-
12
b10001100 !
0+
b10001100 %
0&
b100011000 '
#281000
b10001101 !
1+
1&
b100011001 '
#282000
1)
b10001101 !
1+
b10001101 %
0&
b100011010 '
#283000
10
1.
b1 #
1*
b10001110 !
0+
1&
b100011011 '
#284000
0?
0=
09
1:
08
04
15
03
0/
0.
10
b0 #
0*
0)
1-
b10001110 !
0+
b10001110 %
0&
b100011100 '
#285000
b10001111 !
1+
1&
b100011101 '
#286000
1)
b10001111 !
1+
b10001111 %
0&
b100011110 '
#287000
1?
1=
19
0:
18
14
05
13
1/
00
1.
b1111 #
1*
b10010000 !
0+
1&
b100011111 '
#288000
0D
03
08
0=
0B
0/
04
09
0>
0.
00
05
0:
1?
b0 #
0*
0)
0-
02
07
1<
b10010000 !
0+
b10010000 %
0&
b100100000 '
#289000
b10010001 !
1+
1&
b100100001 '
#290000
1)
b10010001 !
1+
b10010001 %
0&
b100100010 '
#291000
10
1.
b1 #
1*
b10010010 !
0+
1&
b100100011 '
#292000
05
03
0/
0.
10
b0 #
0*
0)
1-
b10010010 !
0+
b10010010 %
0&
b100100100 '
#293000
b10010011 !
1+
1&
b100100101 '
#294000
1)
b10010011 !
1+
b10010011 %
0&
b100100110 '
#295000
15
13
1/
00
1.
b11 #
1*
b10010100 !
0+
1&
b100100111 '
#296000
0:
03
08
0/
04
0.
00
15
b0 #
0*
0)
0-
12
b10010100 !
0+
b10010100 %
0&
b100101000 '
#297000
b10010101 !
1+
1&
b100101001 '
#298000
1)
b10010101 !
1+
b10010101 %
0&
b100101010 '
#299000
10
1.
b1 #
1*
b10010110 !
0+
1&
b100101011 '
#300000
0:
08
04
15
03
0/
0.
10
b0 #
0*
0)
1-
b10010110 !
0+
b10010110 %
0&
b100101100 '
#301000
b10010111 !
1+
1&
b100101101 '
#302000
1)
b10010111 !
1+
b10010111 %
0&
b100101110 '
#303000
1:
18
14
05
13
1/
00
1.
b111 #
1*
b10011000 !
0+
1&
b100101111 '
#304000
0D
0B
0>
1?
03
08
0=
0/
04
09
0.
00
05
1:
b0 #
0*
0)
0-
02
17
b10011000 !
0+
b10011000 %
0&
b100110000 '
#305000
b10011001 !
1+
1&
b100110001 '
#306000
1)
b10011001 !
1+
b10011001 %
0&
b100110010 '
#307000
10
1.
b1 #
1*
b10011010 !
0+
1&
b100110011 '
