assignment3/encoders/special encoder/bcden.v
module bcden(
    input en,
    input [99:0] i,
    output [7:0] y,
    output act
);
    integer z;
    integer tens, units, temp;
    reg [7:0] a;
    always @(*) begin
        a = 0;
        if (en == 1) begin
             for (z = 99; z >= 0; z = z - 1) begin
                if (i[z] == 1) begin
                    // Calculate tens and units without / or %
                    
                    temp = z;
                    tens = 0;
                    while (temp >= 10) begin
                        temp = temp - 10;
                        tens = tens + 1;
                    end
                    units = temp;
                    a[3:0] = units; // lsb
                    a[7:4] = tens;  // msb
                end 
            end
        end
    end
    assign y = a;
    assign act = en&(|i);
endmodule

assignment3/encoders/special encoder/bcdentb.v
`timescale 1ns/1ps

module bcdentb;
    reg en;
    reg [99:0] i;
    wire [7:0] y;
    wire act;

    bcden bcden(
        .en(en) , .i(i) , .y(y) , .act(act)
    );
    integer z;
    initial begin
        $dumpfile("bcdenv.vcd");
        $dumpvars(0 , bcdentb);
        en =1;
        for (z = 0; z<100; z = z+1) begin
            i = 1<<z;
            #1;
        end
        $finish;
    end
endmodule

assignment3/encoders/special encoder/bcdenv.vcd
$date
	Fri Jun 06 18:14:15 2025
$end
$version
	Icarus Verilog
$end
$timescale
	1ps
$end
$scope module bcdentb $end
$var wire 8 ! y [7:0] $end
$var wire 1 " act $end
$var reg 1 # en $end
$var reg 100 $ i [99:0] $end
$var integer 32 % z [31:0] $end
$scope module bcden $end
$var wire 1 " act $end
$var wire 1 # en $end
$var wire 100 & i [99:0] $end
$var wire 8 ' y [7:0] $end
$var reg 8 ( a [7:0] $end
$var integer 32 ) temp [31:0] $end
$var integer 32 * tens [31:0] $end
$var integer 32 + units [31:0] $end
$var integer 32 , z [31:0] $end
$upscope $end
$upscope $end
$enddefinitions $end
$comment Show the parameter values. $end
$dumpall
$end
#0
$dumpvars
b11111111111111111111111111111111 ,
b0 +
b0 *
b0 )
b0 (
b0 '
b1 &
b0 %
b1 $
1#
1"
b0 !
$end
#1000
b1 !
b1 '
b1 (
b1 +
b1 )
b11111111111111111111111111111111 ,
b10 $
b10 &
b1 %
#2000
b10 +
b10 )
b11111111111111111111111111111111 ,
b10 !
b10 '
b10 (
b100 $
b100 &
b10 %
#3000
b11 +
b11 )
b11111111111111111111111111111111 ,
b11 !
b11 '
b11 (
b1000 $
b1000 &
b11 %
#4000
b100 +
b100 )
b11111111111111111111111111111111 ,
b100 !
b100 '
b100 (
b10000 $
b10000 &
b100 %
#5000
b101 +
b101 )
b11111111111111111111111111111111 ,
b101 !
b101 '
b101 (
b100000 $
b100000 &
b101 %
#6000
b110 +
b110 )
b11111111111111111111111111111111 ,
b110 !
b110 '
b110 (
b1000000 $
b1000000 &
b110 %
#7000
b111 +
b111 )
b11111111111111111111111111111111 ,
b111 !
b111 '
b111 (
b10000000 $
b10000000 &
b111 %
#8000
b1000 +
b1000 )
b11111111111111111111111111111111 ,
b1000 !
b1000 '
b1000 (
b100000000 $
b100000000 &
b1000 %
#9000
b1001 +
b1001 )
b11111111111111111111111111111111 ,
b1001 !
b1001 '
b1001 (
b1000000000 $
b1000000000 &
b1001 %
#10000
b0 +
b1 *
b0 )
b11111111111111111111111111111111 ,
b10000 !
b10000 '
b10000 (
b10000000000 $
b10000000000 &
b1010 %
#11000
b1 +
b1 *
b1 )
b11111111111111111111111111111111 ,
b10001 !
b10001 '
b10001 (
b100000000000 $
b100000000000 &
b1011 %
#12000
b10 +
b1 *
b10 )
b11111111111111111111111111111111 ,
b10010 !
b10010 '
b10010 (
b1000000000000 $
b1000000000000 &
b1100 %
#13000
b11 +
b1 *
b11 )
b11111111111111111111111111111111 ,
b10011 !
b10011 '
b10011 (
b10000000000000 $
b10000000000000 &
b1101 %
#14000
b100 +
b1 *
b100 )
b11111111111111111111111111111111 ,
b10100 !
b10100 '
b10100 (
b100000000000000 $
b100000000000000 &
b1110 %
#15000
b101 +
b1 *
b101 )
b11111111111111111111111111111111 ,
b10101 !
b10101 '
b10101 (
b1000000000000000 $
b1000000000000000 &
b1111 %
#16000
b110 +
b1 *
b110 )
b11111111111111111111111111111111 ,
b10110 !
b10110 '
b10110 (
b10000000000000000 $
b10000000000000000 &
b10000 %
#17000
b111 +
b1 *
b111 )
b11111111111111111111111111111111 ,
b10111 !
b10111 '
b10111 (
b100000000000000000 $
b100000000000000000 &
b10001 %
#18000
b1000 +
b1 *
b1000 )
b11111111111111111111111111111111 ,
b11000 !
b11000 '
b11000 (
b1000000000000000000 $
b1000000000000000000 &
b10010 %
#19000
b1001 +
b1 *
b1001 )
b11111111111111111111111111111111 ,
b11001 !
b11001 '
b11001 (
b10000000000000000000 $
b10000000000000000000 &
b10011 %
#20000
b0 +
b10 *
b0 )
b11111111111111111111111111111111 ,
b100000 !
b100000 '
b100000 (
b100000000000000000000 $
b100000000000000000000 &
b10100 %
#21000
b1 +
b10 *
b1 )
b11111111111111111111111111111111 ,
b100001 !
b100001 '
b100001 (
b1000000000000000000000 $
b1000000000000000000000 &
b10101 %
#22000
b10 +
b10 *
b10 )
b11111111111111111111111111111111 ,
b100010 !
b100010 '
b100010 (
b10000000000000000000000 $
b10000000000000000000000 &
b10110 %
#23000
b11 +
b10 *
b11 )
b11111111111111111111111111111111 ,
b100011 !
b100011 '
b100011 (
b100000000000000000000000 $
b100000000000000000000000 &
b10111 %
#24000
b100 +
b10 *
b100 )
b11111111111111111111111111111111 ,
b100100 !
b100100 '
b100100 (
b1000000000000000000000000 $
b1000000000000000000000000 &
b11000 %
#25000
b101 +
b10 *
b101 )
b11111111111111111111111111111111 ,
b100101 !
b100101 '
b100101 (
b10000000000000000000000000 $
b10000000000000000000000000 &
b11001 %
#26000
b110 +
b10 *
b110 )
b11111111111111111111111111111111 ,
b100110 !
b100110 '
b100110 (
b100000000000000000000000000 $
b100000000000000000000000000 &
b11010 %
#27000
b111 +
b10 *
b111 )
b11111111111111111111111111111111 ,
b100111 !
b100111 '
b100111 (
b1000000000000000000000000000 $
b1000000000000000000000000000 &
b11011 %
#28000
b1000 +
b10 *
b1000 )
b11111111111111111111111111111111 ,
b101000 !
b101000 '
b101000 (
b10000000000000000000000000000 $
b10000000000000000000000000000 &
b11100 %
#29000
b1001 +
b10 *
b1001 )
b11111111111111111111111111111111 ,
b101001 !
b101001 '
b101001 (
b100000000000000000000000000000 $
b100000000000000000000000000000 &
b11101 %
#30000
b0 +
b11 *
b0 )
b11111111111111111111111111111111 ,
b110000 !
b110000 '
b110000 (
b1000000000000000000000000000000 $
b1000000000000000000000000000000 &
b11110 %
#31000
b1 +
b11 *
b1 )
b11111111111111111111111111111111 ,
b110001 !
b110001 '
b110001 (
b10000000000000000000000000000000 $
b10000000000000000000000000000000 &
b11111 %
#32000
b10 +
b11 *
b10 )
b11111111111111111111111111111111 ,
b110010 !
b110010 '
b110010 (
b100000000000000000000000000000000 $
b100000000000000000000000000000000 &
b100000 %
#33000
b11 +
b11 *
b11 )
b11111111111111111111111111111111 ,
b110011 !
b110011 '
b110011 (
b1000000000000000000000000000000000 $
b1000000000000000000000000000000000 &
b100001 %
#34000
b100 +
b11 *
b100 )
b11111111111111111111111111111111 ,
b110100 !
b110100 '
b110100 (
b10000000000000000000000000000000000 $
b10000000000000000000000000000000000 &
b100010 %
#35000
b101 +
b11 *
b101 )
b11111111111111111111111111111111 ,
b110101 !
b110101 '
b110101 (
b100000000000000000000000000000000000 $
b100000000000000000000000000000000000 &
b100011 %
#36000
b110 +
b11 *
b110 )
b11111111111111111111111111111111 ,
b110110 !
b110110 '
b110110 (
b1000000000000000000000000000000000000 $
b1000000000000000000000000000000000000 &
b100100 %
#37000
b111 +
b11 *
b111 )
b11111111111111111111111111111111 ,
b110111 !
b110111 '
b110111 (
b10000000000000000000000000000000000000 $
b10000000000000000000000000000000000000 &
b100101 %
#38000
b1000 +
b11 *
b1000 )
b11111111111111111111111111111111 ,
b111000 !
b111000 '
b111000 (
b100000000000000000000000000000000000000 $
b100000000000000000000000000000000000000 &
b100110 %
#39000
b1001 +
b11 *
b1001 )
b11111111111111111111111111111111 ,
b111001 !
b111001 '
b111001 (
b1000000000000000000000000000000000000000 $
b1000000000000000000000000000000000000000 &
b100111 %
#40000
b0 +
b100 *
b0 )
b11111111111111111111111111111111 ,
b1000000 !
b1000000 '
b1000000 (
b10000000000000000000000000000000000000000 $
b10000000000000000000000000000000000000000 &
b101000 %
#41000
b1 +
b100 *
b1 )
b11111111111111111111111111111111 ,
b1000001 !
b1000001 '
b1000001 (
b100000000000000000000000000000000000000000 $
b100000000000000000000000000000000000000000 &
b101001 %
#42000
b10 +
b100 *
b10 )
b11111111111111111111111111111111 ,
b1000010 !
b1000010 '
b1000010 (
b1000000000000000000000000000000000000000000 $
b1000000000000000000000000000000000000000000 &
b101010 %
#43000
b11 +
b100 *
b11 )
b11111111111111111111111111111111 ,
b1000011 !
b1000011 '
b1000011 (
b10000000000000000000000000000000000000000000 $
b10000000000000000000000000000000000000000000 &
b101011 %
#44000
b100 +
b100 *
b100 )
b11111111111111111111111111111111 ,
b1000100 !
b1000100 '
b1000100 (
b100000000000000000000000000000000000000000000 $
b100000000000000000000000000000000000000000000 &
b101100 %
#45000
b101 +
b100 *
b101 )
b11111111111111111111111111111111 ,
b1000101 !
b1000101 '
b1000101 (
b1000000000000000000000000000000000000000000000 $
b1000000000000000000000000000000000000000000000 &
b101101 %
#46000
b110 +
b100 *
b110 )
b11111111111111111111111111111111 ,
b1000110 !
b1000110 '
b1000110 (
b10000000000000000000000000000000000000000000000 $
b10000000000000000000000000000000000000000000000 &
b101110 %
#47000
b111 +
b100 *
b111 )
b11111111111111111111111111111111 ,
b1000111 !
b1000111 '
b1000111 (
b100000000000000000000000000000000000000000000000 $
b100000000000000000000000000000000000000000000000 &
b101111 %
#48000
b1000 +
b100 *
b1000 )
b11111111111111111111111111111111 ,
b1001000 !
b1001000 '
b1001000 (
b1000000000000000000000000000000000000000000000000 $
b1000000000000000000000000000000000000000000000000 &
b110000 %
#49000
b1001 +
b100 *
b1001 )
b11111111111111111111111111111111 ,
b1001001 !
b1001001 '
b1001001 (
b10000000000000000000000000000000000000000000000000 $
b10000000000000000000000000000000000000000000000000 &
b110001 %
#50000
b0 +
b101 *
b0 )
b11111111111111111111111111111111 ,
b1010000 !
b1010000 '
b1010000 (
b100000000000000000000000000000000000000000000000000 $
b100000000000000000000000000000000000000000000000000 &
b110010 %
#51000
b1 +
b101 *
b1 )
b11111111111111111111111111111111 ,
b1010001 !
b1010001 '
b1010001 (
b1000000000000000000000000000000000000000000000000000 $
b1000000000000000000000000000000000000000000000000000 &
b110011 %
#52000
b10 +
b101 *
b10 )
b11111111111111111111111111111111 ,
b1010010 !
b1010010 '
b1010010 (
b10000000000000000000000000000000000000000000000000000 $
b10000000000000000000000000000000000000000000000000000 &
b110100 %
#53000
b11 +
b101 *
b11 )
b11111111111111111111111111111111 ,
b1010011 !
b1010011 '
b1010011 (
b100000000000000000000000000000000000000000000000000000 $
b100000000000000000000000000000000000000000000000000000 &
b110101 %
#54000
b100 +
b101 *
b100 )
b11111111111111111111111111111111 ,
b1010100 !
b1010100 '
b1010100 (
b1000000000000000000000000000000000000000000000000000000 $
b1000000000000000000000000000000000000000000000000000000 &
b110110 %
#55000
b101 +
b101 *
b101 )
b11111111111111111111111111111111 ,
b1010101 !
b1010101 '
b1010101 (
b10000000000000000000000000000000000000000000000000000000 $
b10000000000000000000000000000000000000000000000000000000 &
b110111 %
#56000
b110 +
b101 *
b110 )
b11111111111111111111111111111111 ,
b1010110 !
b1010110 '
b1010110 (
b100000000000000000000000000000000000000000000000000000000 $
b100000000000000000000000000000000000000000000000000000000 &
b111000 %
#57000
b111 +
b101 *
b111 )
b11111111111111111111111111111111 ,
b1010111 !
b1010111 '
b1010111 (
b1000000000000000000000000000000000000000000000000000000000 $
b1000000000000000000000000000000000000000000000000000000000 &
b111001 %
#58000
b1000 +
b101 *
b1000 )
b11111111111111111111111111111111 ,
b1011000 !
b1011000 '
b1011000 (
b10000000000000000000000000000000000000000000000000000000000 $
b10000000000000000000000000000000000000000000000000000000000 &
b111010 %
#59000
b1001 +
b101 *
b1001 )
b11111111111111111111111111111111 ,
b1011001 !
b1011001 '
b1011001 (
b100000000000000000000000000000000000000000000000000000000000 $
b100000000000000000000000000000000000000000000000000000000000 &
b111011 %
#60000
b0 +
b110 *
b0 )
b11111111111111111111111111111111 ,
b1100000 !
b1100000 '
b1100000 (
b1000000000000000000000000000000000000000000000000000000000000 $
b1000000000000000000000000000000000000000000000000000000000000 &
b111100 %
#61000
b1 +
b110 *
b1 )
b11111111111111111111111111111111 ,
b1100001 !
b1100001 '
b1100001 (
b10000000000000000000000000000000000000000000000000000000000000 $
b10000000000000000000000000000000000000000000000000000000000000 &
b111101 %
#62000
b10 +
b110 *
b10 )
b11111111111111111111111111111111 ,
b1100010 !
b1100010 '
b1100010 (
b100000000000000000000000000000000000000000000000000000000000000 $
b100000000000000000000000000000000000000000000000000000000000000 &
b111110 %
#63000
b11 +
b110 *
b11 )
b11111111111111111111111111111111 ,
b1100011 !
b1100011 '
b1100011 (
b1000000000000000000000000000000000000000000000000000000000000000 $
b1000000000000000000000000000000000000000000000000000000000000000 &
b111111 %
#64000
b100 +
b110 *
b100 )
b11111111111111111111111111111111 ,
b1100100 !
b1100100 '
b1100100 (
b10000000000000000000000000000000000000000000000000000000000000000 $
b10000000000000000000000000000000000000000000000000000000000000000 &
b1000000 %
#65000
b101 +
b110 *
b101 )
b11111111111111111111111111111111 ,
b1100101 !
b1100101 '
b1100101 (
b100000000000000000000000000000000000000000000000000000000000000000 $
b100000000000000000000000000000000000000000000000000000000000000000 &
b1000001 %
#66000
b110 +
b110 *
b110 )
b11111111111111111111111111111111 ,
b1100110 !
b1100110 '
b1100110 (
b1000000000000000000000000000000000000000000000000000000000000000000 $
b1000000000000000000000000000000000000000000000000000000000000000000 &
b1000010 %
#67000
b111 +
b110 *
b111 )
b11111111111111111111111111111111 ,
b1100111 !
b1100111 '
b1100111 (
b10000000000000000000000000000000000000000000000000000000000000000000 $
b10000000000000000000000000000000000000000000000000000000000000000000 &
b1000011 %
#68000
b1000 +
b110 *
b1000 )
b11111111111111111111111111111111 ,
b1101000 !
b1101000 '
b1101000 (
b100000000000000000000000000000000000000000000000000000000000000000000 $
b100000000000000000000000000000000000000000000000000000000000000000000 &
b1000100 %
#69000
b1001 +
b110 *
b1001 )
b11111111111111111111111111111111 ,
b1101001 !
b1101001 '
b1101001 (
b1000000000000000000000000000000000000000000000000000000000000000000000 $
b1000000000000000000000000000000000000000000000000000000000000000000000 &
b1000101 %
#70000
b0 +
b111 *
b0 )
b11111111111111111111111111111111 ,
b1110000 !
b1110000 '
b1110000 (
b10000000000000000000000000000000000000000000000000000000000000000000000 $
b10000000000000000000000000000000000000000000000000000000000000000000000 &
b1000110 %
#71000
b1 +
b111 *
b1 )
b11111111111111111111111111111111 ,
b1110001 !
b1110001 '
b1110001 (
b100000000000000000000000000000000000000000000000000000000000000000000000 $
b100000000000000000000000000000000000000000000000000000000000000000000000 &
b1000111 %
#72000
b10 +
b111 *
b10 )
b11111111111111111111111111111111 ,
b1110010 !
b1110010 '
b1110010 (
b1000000000000000000000000000000000000000000000000000000000000000000000000 $
b1000000000000000000000000000000000000000000000000000000000000000000000000 &
b1001000 %
#73000
b11 +
b111 *
b11 )
b11111111111111111111111111111111 ,
b1110011 !
b1110011 '
b1110011 (
b10000000000000000000000000000000000000000000000000000000000000000000000000 $
b10000000000000000000000000000000000000000000000000000000000000000000000000 &
b1001001 %
#74000
b100 +
b111 *
b100 )
b11111111111111111111111111111111 ,
b1110100 !
b1110100 '
b1110100 (
b100000000000000000000000000000000000000000000000000000000000000000000000000 $
b100000000000000000000000000000000000000000000000000000000000000000000000000 &
b1001010 %
#75000
b101 +
b111 *
b101 )
b11111111111111111111111111111111 ,
b1110101 !
b1110101 '
b1110101 (
b1000000000000000000000000000000000000000000000000000000000000000000000000000 $
b1000000000000000000000000000000000000000000000000000000000000000000000000000 &
b1001011 %
#76000
b110 +
b111 *
b110 )
b11111111111111111111111111111111 ,
b1110110 !
b1110110 '
b1110110 (
b10000000000000000000000000000000000000000000000000000000000000000000000000000 $
b10000000000000000000000000000000000000000000000000000000000000000000000000000 &
b1001100 %
#77000
b111 +
b111 *
b111 )
b11111111111111111111111111111111 ,
b1110111 !
b1110111 '
b1110111 (
b100000000000000000000000000000000000000000000000000000000000000000000000000000 $
b100000000000000000000000000000000000000000000000000000000000000000000000000000 &
b1001101 %
#78000
b1000 +
b111 *
b1000 )
b11111111111111111111111111111111 ,
b1111000 !
b1111000 '
b1111000 (
b1000000000000000000000000000000000000000000000000000000000000000000000000000000 $
b1000000000000000000000000000000000000000000000000000000000000000000000000000000 &
b1001110 %
#79000
b1001 +
b111 *
b1001 )
b11111111111111111111111111111111 ,
b1111001 !
b1111001 '
b1111001 (
b10000000000000000000000000000000000000000000000000000000000000000000000000000000 $
b10000000000000000000000000000000000000000000000000000000000000000000000000000000 &
b1001111 %
#80000
b0 +
b1000 *
b0 )
b11111111111111111111111111111111 ,
b10000000 !
b10000000 '
b10000000 (
b100000000000000000000000000000000000000000000000000000000000000000000000000000000 $
b100000000000000000000000000000000000000000000000000000000000000000000000000000000 &
b1010000 %
#81000
b1 +
b1000 *
b1 )
b11111111111111111111111111111111 ,
b10000001 !
b10000001 '
b10000001 (
b1000000000000000000000000000000000000000000000000000000000000000000000000000000000 $
b1000000000000000000000000000000000000000000000000000000000000000000000000000000000 &
b1010001 %
#82000
b10 +
b1000 *
b10 )
b11111111111111111111111111111111 ,
b10000010 !
b10000010 '
b10000010 (
b10000000000000000000000000000000000000000000000000000000000000000000000000000000000 $
b10000000000000000000000000000000000000000000000000000000000000000000000000000000000 &
b1010010 %
#83000
b11 +
b1000 *
b11 )
b11111111111111111111111111111111 ,
b10000011 !
b10000011 '
b10000011 (
b100000000000000000000000000000000000000000000000000000000000000000000000000000000000 $
b100000000000000000000000000000000000000000000000000000000000000000000000000000000000 &
b1010011 %
#84000
b100 +
b1000 *
b100 )
b11111111111111111111111111111111 ,
b10000100 !
b10000100 '
b10000100 (
b1000000000000000000000000000000000000000000000000000000000000000000000000000000000000 $
b1000000000000000000000000000000000000000000000000000000000000000000000000000000000000 &
b1010100 %
#85000
b101 +
b1000 *
b101 )
b11111111111111111111111111111111 ,
b10000101 !
b10000101 '
b10000101 (
b10000000000000000000000000000000000000000000000000000000000000000000000000000000000000 $
b10000000000000000000000000000000000000000000000000000000000000000000000000000000000000 &
b1010101 %
#86000
b110 +
b1000 *
b110 )
b11111111111111111111111111111111 ,
b10000110 !
b10000110 '
b10000110 (
b100000000000000000000000000000000000000000000000000000000000000000000000000000000000000 $
b100000000000000000000000000000000000000000000000000000000000000000000000000000000000000 &
b1010110 %
#87000
b111 +
b1000 *
b111 )
b11111111111111111111111111111111 ,
b10000111 !
b10000111 '
b10000111 (
b1000000000000000000000000000000000000000000000000000000000000000000000000000000000000000 $
b1000000000000000000000000000000000000000000000000000000000000000000000000000000000000000 &
b1010111 %
#88000
b1000 +
b1000 *
b1000 )
b11111111111111111111111111111111 ,
b10001000 !
b10001000 '
b10001000 (
b10000000000000000000000000000000000000000000000000000000000000000000000000000000000000000 $
b10000000000000000000000000000000000000000000000000000000000000000000000000000000000000000 &
b1011000 %
#89000
b1001 +
b1000 *
b1001 )
b11111111111111111111111111111111 ,
b10001001 !
b10001001 '
b10001001 (
b100000000000000000000000000000000000000000000000000000000000000000000000000000000000000000 $
b100000000000000000000000000000000000000000000000000000000000000000000000000000000000000000 &
b1011001 %
#90000
b0 +
b1001 *
b0 )
b11111111111111111111111111111111 ,
b10010000 !
b10010000 '
b10010000 (
b1000000000000000000000000000000000000000000000000000000000000000000000000000000000000000000 $
b1000000000000000000000000000000000000000000000000000000000000000000000000000000000000000000 &
b1011010 %
#91000
b1 +
b1001 *
b1 )
b11111111111111111111111111111111 ,
b10010001 !
b10010001 '
b10010001 (
b10000000000000000000000000000000000000000000000000000000000000000000000000000000000000000000 $
b10000000000000000000000000000000000000000000000000000000000000000000000000000000000000000000 &
b1011011 %
#92000
b10 +
b1001 *
b10 )
b11111111111111111111111111111111 ,
b10010010 !
b10010010 '
b10010010 (
b100000000000000000000000000000000000000000000000000000000000000000000000000000000000000000000 $
b100000000000000000000000000000000000000000000000000000000000000000000000000000000000000000000 &
b1011100 %
#93000
b11 +
b1001 *
b11 )
b11111111111111111111111111111111 ,
b10010011 !
b10010011 '
b10010011 (
b1000000000000000000000000000000000000000000000000000000000000000000000000000000000000000000000 $
b1000000000000000000000000000000000000000000000000000000000000000000000000000000000000000000000 &
b1011101 %
#94000
b100 +
b1001 *
b100 )
b11111111111111111111111111111111 ,
b10010100 !
b10010100 '
b10010100 (
b10000000000000000000000000000000000000000000000000000000000000000000000000000000000000000000000 $
b10000000000000000000000000000000000000000000000000000000000000000000000000000000000000000000000 &
b1011110 %
#95000
b101 +
b1001 *
b101 )
b11111111111111111111111111111111 ,
b10010101 !
b10010101 '
b10010101 (
b100000000000000000000000000000000000000000000000000000000000000000000000000000000000000000000000 $
b100000000000000000000000000000000000000000000000000000000000000000000000000000000000000000000000 &
b1011111 %
#96000
b110 +
b1001 *
b110 )
b11111111111111111111111111111111 ,
b10010110 !
b10010110 '
b10010110 (
b1000000000000000000000000000000000000000000000000000000000000000000000000000000000000000000000000 $
b1000000000000000000000000000000000000000000000000000000000000000000000000000000000000000000000000 &
b1100000 %
#97000
b111 +
b1001 *
b111 )
b11111111111111111111111111111111 ,
b10010111 !
b10010111 '
b10010111 (
b10000000000000000000000000000000000000000000000000000000000000000000000000000000000000000000000000 $
b10000000000000000000000000000000000000000000000000000000000000000000000000000000000000000000000000 &
b1100001 %
#98000
b1000 +
b1001 *
b1000 )
b11111111111111111111111111111111 ,
b10011000 !
b10011000 '
b10011000 (
b100000000000000000000000000000000000000000000000000000000000000000000000000000000000000000000000000 $
b100000000000000000000000000000000000000000000000000000000000000000000000000000000000000000000000000 &
b1100010 %
#99000
b1001 +
b1001 *
b1001 )
b11111111111111111111111111111111 ,
b10011001 !
b10011001 '
b10011001 (
b1000000000000000000000000000000000000000000000000000000000000000000000000000000000000000000000000000 $
b1000000000000000000000000000000000000000000000000000000000000000000000000000000000000000000000000000 &
b1100011 %
#100000
b1100100 %
