assignment3/encoders/special encoder/gren.v
module gren(
    input en,
    input [7:0] i ,
    output [2:0] y,
    output act
);

    reg [2:0] s1;
    reg [2:0] s2;
    assign act = en & (|i);
    always @(*) begin
        if (en) begin
            casex (i)
                8'b1xxxxxxx: s1 = 3'b111;
                8'b01xxxxxx: s1 = 3'b110;
                8'b001xxxxx: s1 = 3'b101;
                8'b0001xxxx: s1 = 3'b100;
                8'b00001xxx: s1 = 3'b011;
                8'b000001xx: s1 = 3'b010;
                8'b0000001x: s1 = 3'b001;
                8'b00000001: s1 = 3'b000;
                default:     s1 = 3'b000;
            endcase
        end else begin
            s1 = 3'b000;
        end
        s2 = s1 >> 1;
    end
        assign y = s1^s2;
endmodule

assignment3/encoders/special encoder/grentb.v
`timescale 1ns/1ps
module grentb;
    reg en;
    reg [7:0] i;
    wire act;
    wire [2:0] y;

    gren encoder(
        .en(en) , .i(i) , .act(act) , .y(y)
    );
    integer z;
    initial begin
        $dumpfile("grenv.vcd");
        $dumpvars(0 , grentb);
        for (z = 0; z<256; z =z+1) begin
            en =1;
            i = z;
            #1;
            en = 0;
            i =z;
            #1;
        end
        $finish;
    end
endmodule

assignment3/encoders/special encoder/grenv.vcd
$date
	Fri Jun 06 16:37:52 2025
$end
$version
	Icarus Verilog
$end
$timescale
	1ps
$end
$scope module grentb $end
$var wire 3 ! y [2:0] $end
$var wire 1 " act $end
$var reg 1 # en $end
$var reg 8 $ i [7:0] $end
$var integer 32 % z [31:0] $end
$scope module encoder $end
$var wire 1 " act $end
$var wire 1 # en $end
$var wire 8 & i [7:0] $end
$var wire 3 ' y [2:0] $end
$var reg 3 ( s1 [2:0] $end
$var reg 3 ) s2 [2:0] $end
$upscope $end
$upscope $end
$enddefinitions $end
$comment Show the parameter values. $end
$dumpall
$end
#0
$dumpvars
b0 )
b0 (
b0 '
b0 &
b0 %
b0 $
1#
0"
b0 !
$end
#1000
0#
#2000
1"
b1 $
b1 &
1#
b1 %
#3000
0"
0#
#4000
b1 !
b1 '
1"
b1 (
b10 $
b10 &
1#
b10 %
#5000
b0 !
b0 '
0"
b0 (
0#
#6000
b1 !
b1 '
1"
b1 (
b11 $
b11 &
1#
b11 %
#7000
b0 !
b0 '
0"
b0 (
0#
#8000
b11 !
b11 '
1"
b1 )
b10 (
b100 $
b100 &
1#
b100 %
#9000
b0 !
b0 '
0"
b0 )
b0 (
0#
#10000
b11 !
b11 '
1"
b1 )
b10 (
b101 $
b101 &
1#
b101 %
#11000
b0 !
b0 '
0"
b0 )
b0 (
0#
#12000
b11 !
b11 '
1"
b1 )
b10 (
b110 $
b110 &
1#
b110 %
#13000
b0 !
b0 '
0"
b0 )
b0 (
0#
#14000
b11 !
b11 '
1"
b1 )
b10 (
b111 $
b111 &
1#
b111 %
#15000
b0 !
b0 '
0"
b0 )
b0 (
0#
#16000
b10 !
b10 '
1"
b1 )
b11 (
b1000 $
b1000 &
1#
b1000 %
#17000
b0 !
b0 '
0"
b0 )
b0 (
0#
#18000
b10 !
b10 '
1"
b1 )
b11 (
b1001 $
b1001 &
1#
b1001 %
#19000
b0 !
b0 '
0"
b0 )
b0 (
0#
#20000
b10 !
b10 '
1"
b1 )
b11 (
b1010 $
b1010 &
1#
b1010 %
#21000
b0 !
b0 '
0"
b0 )
b0 (
0#
#22000
b10 !
b10 '
1"
b1 )
b11 (
b1011 $
b1011 &
1#
b1011 %
#23000
b0 !
b0 '
0"
b0 )
b0 (
0#
#24000
b10 !
b10 '
1"
b1 )
b11 (
b1100 $
b1100 &
1#
b1100 %
#25000
b0 !
b0 '
0"
b0 )
b0 (
0#
#26000
b10 !
b10 '
1"
b1 )
b11 (
b1101 $
b1101 &
1#
b1101 %
#27000
b0 !
b0 '
0"
b0 )
b0 (
0#
#28000
b10 !
b10 '
1"
b1 )
b11 (
b1110 $
b1110 &
1#
b1110 %
#29000
b0 !
b0 '
0"
b0 )
b0 (
0#
#30000
b10 !
b10 '
1"
b1 )
b11 (
b1111 $
b1111 &
1#
b1111 %
#31000
b0 !
b0 '
0"
b0 )
b0 (
0#
#32000
b110 !
b110 '
1"
b10 )
b100 (
b10000 $
b10000 &
1#
b10000 %
#33000
b0 !
b0 '
0"
b0 )
b0 (
0#
#34000
b110 !
b110 '
1"
b10 )
b100 (
b10001 $
b10001 &
1#
b10001 %
#35000
b0 !
b0 '
0"
b0 )
b0 (
0#
#36000
b110 !
b110 '
1"
b10 )
b100 (
b10010 $
b10010 &
1#
b10010 %
#37000
b0 !
b0 '
0"
b0 )
b0 (
0#
#38000
b110 !
b110 '
1"
b10 )
b100 (
b10011 $
b10011 &
1#
b10011 %
#39000
b0 !
b0 '
0"
b0 )
b0 (
0#
#40000
b110 !
b110 '
1"
b10 )
b100 (
b10100 $
b10100 &
1#
b10100 %
#41000
b0 !
b0 '
0"
b0 )
b0 (
0#
#42000
b110 !
b110 '
1"
b10 )
b100 (
b10101 $
b10101 &
1#
b10101 %
#43000
b0 !
b0 '
0"
b0 )
b0 (
0#
#44000
b110 !
b110 '
1"
b10 )
b100 (
b10110 $
b10110 &
1#
b10110 %
#45000
b0 !
b0 '
0"
b0 )
b0 (
0#
#46000
b110 !
b110 '
1"
b10 )
b100 (
b10111 $
b10111 &
1#
b10111 %
#47000
b0 !
b0 '
0"
b0 )
b0 (
0#
#48000
b110 !
b110 '
1"
b10 )
b100 (
b11000 $
b11000 &
1#
b11000 %
#49000
b0 !
b0 '
0"
b0 )
b0 (
0#
#50000
b110 !
b110 '
1"
b10 )
b100 (
b11001 $
b11001 &
1#
b11001 %
#51000
b0 !
b0 '
0"
b0 )
b0 (
0#
#52000
b110 !
b110 '
1"
b10 )
b100 (
b11010 $
b11010 &
1#
b11010 %
#53000
b0 !
b0 '
0"
b0 )
b0 (
0#
#54000
b110 !
b110 '
1"
b10 )
b100 (
b11011 $
b11011 &
1#
b11011 %
#55000
b0 !
b0 '
0"
b0 )
b0 (
0#
#56000
b110 !
b110 '
1"
b10 )
b100 (
b11100 $
b11100 &
1#
b11100 %
#57000
b0 !
b0 '
0"
b0 )
b0 (
0#
#58000
b110 !
b110 '
1"
b10 )
b100 (
b11101 $
b11101 &
1#
b11101 %
#59000
b0 !
b0 '
0"
b0 )
b0 (
0#
#60000
b110 !
b110 '
1"
b10 )
b100 (
b11110 $
b11110 &
1#
b11110 %
#61000
b0 !
b0 '
0"
b0 )
b0 (
0#
#62000
b110 !
b110 '
1"
b10 )
b100 (
b11111 $
b11111 &
1#
b11111 %
#63000
b0 !
b0 '
0"
b0 )
b0 (
0#
#64000
b111 !
b111 '
1"
b10 )
b101 (
b100000 $
b100000 &
1#
b100000 %
#65000
b0 !
b0 '
0"
b0 )
b0 (
0#
#66000
b111 !
b111 '
1"
b10 )
b101 (
b100001 $
b100001 &
1#
b100001 %
#67000
b0 !
b0 '
0"
b0 )
b0 (
0#
#68000
b111 !
b111 '
1"
b10 )
b101 (
b100010 $
b100010 &
1#
b100010 %
#69000
b0 !
b0 '
0"
b0 )
b0 (
0#
#70000
b111 !
b111 '
1"
b10 )
b101 (
b100011 $
b100011 &
1#
b100011 %
#71000
b0 !
b0 '
0"
b0 )
b0 (
0#
#72000
b111 !
b111 '
1"
b10 )
b101 (
b100100 $
b100100 &
1#
b100100 %
#73000
b0 !
b0 '
0"
b0 )
b0 (
0#
#74000
b111 !
b111 '
1"
b10 )
b101 (
b100101 $
b100101 &
1#
b100101 %
#75000
b0 !
b0 '
0"
b0 )
b0 (
0#
#76000
b111 !
b111 '
1"
b10 )
b101 (
b100110 $
b100110 &
1#
b100110 %
#77000
b0 !
b0 '
0"
b0 )
b0 (
0#
#78000
b111 !
b111 '
1"
b10 )
b101 (
b100111 $
b100111 &
1#
b100111 %
#79000
b0 !
b0 '
0"
b0 )
b0 (
0#
#80000
b111 !
b111 '
1"
b10 )
b101 (
b101000 $
b101000 &
1#
b101000 %
#81000
b0 !
b0 '
0"
b0 )
b0 (
0#
#82000
b111 !
b111 '
1"
b10 )
b101 (
b101001 $
b101001 &
1#
b101001 %
#83000
b0 !
b0 '
0"
b0 )
b0 (
0#
#84000
b111 !
b111 '
1"
b10 )
b101 (
b101010 $
b101010 &
1#
b101010 %
#85000
b0 !
b0 '
0"
b0 )
b0 (
0#
#86000
b111 !
b111 '
1"
b10 )
b101 (
b101011 $
b101011 &
1#
b101011 %
#87000
b0 !
b0 '
0"
b0 )
b0 (
0#
#88000
b111 !
b111 '
1"
b10 )
b101 (
b101100 $
b101100 &
1#
b101100 %
#89000
b0 !
b0 '
0"
b0 )
b0 (
0#
#90000
b111 !
b111 '
1"
b10 )
b101 (
b101101 $
b101101 &
1#
b101101 %
#91000
b0 !
b0 '
0"
b0 )
b0 (
0#
#92000
b111 !
b111 '
1"
b10 )
b101 (
b101110 $
b101110 &
1#
b101110 %
#93000
b0 !
b0 '
0"
b0 )
b0 (
0#
#94000
b111 !
b111 '
1"
b10 )
b101 (
b101111 $
b101111 &
1#
b101111 %
#95000
b0 !
b0 '
0"
b0 )
b0 (
0#
#96000
b111 !
b111 '
1"
b10 )
b101 (
b110000 $
b110000 &
1#
b110000 %
#97000
b0 !
b0 '
0"
b0 )
b0 (
0#
#98000
b111 !
b111 '
1"
b10 )
b101 (
b110001 $
b110001 &
1#
b110001 %
#99000
b0 !
b0 '
0"
b0 )
b0 (
0#
#100000
b111 !
b111 '
1"
b10 )
b101 (
b110010 $
b110010 &
1#
b110010 %
#101000
b0 !
b0 '
0"
b0 )
b0 (
0#
#102000
b111 !
b111 '
1"
b10 )
b101 (
b110011 $
b110011 &
1#
b110011 %
#103000
b0 !
b0 '
0"
b0 )
b0 (
0#
#104000
b111 !
b111 '
1"
b10 )
b101 (
b110100 $
b110100 &
1#
b110100 %
#105000
b0 !
b0 '
0"
b0 )
b0 (
0#
#106000
b111 !
b111 '
1"
b10 )
b101 (
b110101 $
b110101 &
1#
b110101 %
#107000
b0 !
b0 '
0"
b0 )
b0 (
0#
#108000
b111 !
b111 '
1"
b10 )
b101 (
b110110 $
b110110 &
1#
b110110 %
#109000
b0 !
b0 '
0"
b0 )
b0 (
0#
#110000
b111 !
b111 '
1"
b10 )
b101 (
b110111 $
b110111 &
1#
b110111 %
#111000
b0 !
b0 '
0"
b0 )
b0 (
0#
#112000
b111 !
b111 '
1"
b10 )
b101 (
b111000 $
b111000 &
1#
b111000 %
#113000
b0 !
b0 '
0"
b0 )
b0 (
0#
#114000
b111 !
b111 '
1"
b10 )
b101 (
b111001 $
b111001 &
1#
b111001 %
#115000
b0 !
b0 '
0"
b0 )
b0 (
0#
#116000
b111 !
b111 '
1"
b10 )
b101 (
b111010 $
b111010 &
1#
b111010 %
#117000
b0 !
b0 '
0"
b0 )
b0 (
0#
#118000
b111 !
b111 '
1"
b10 )
b101 (
b111011 $
b111011 &
1#
b111011 %
#119000
b0 !
b0 '
0"
b0 )
b0 (
0#
#120000
b111 !
b111 '
1"
b10 )
b101 (
b111100 $
b111100 &
1#
b111100 %
#121000
b0 !
b0 '
0"
b0 )
b0 (
0#
#122000
b111 !
b111 '
1"
b10 )
b101 (
b111101 $
b111101 &
1#
b111101 %
#123000
b0 !
b0 '
0"
b0 )
b0 (
0#
#124000
b111 !
b111 '
1"
b10 )
b101 (
b111110 $
b111110 &
1#
b111110 %
#125000
b0 !
b0 '
0"
b0 )
b0 (
0#
#126000
b111 !
b111 '
1"
b10 )
b101 (
b111111 $
b111111 &
1#
b111111 %
#127000
b0 !
b0 '
0"
b0 )
b0 (
0#
#128000
b101 !
b101 '
1"
b11 )
b110 (
b1000000 $
b1000000 &
1#
b1000000 %
#129000
b0 !
b0 '
0"
b0 )
b0 (
0#
#130000
b101 !
b101 '
1"
b11 )
b110 (
b1000001 $
b1000001 &
1#
b1000001 %
#131000
b0 !
b0 '
0"
b0 )
b0 (
0#
#132000
b101 !
b101 '
1"
b11 )
b110 (
b1000010 $
b1000010 &
1#
b1000010 %
#133000
b0 !
b0 '
0"
b0 )
b0 (
0#
#134000
b101 !
b101 '
1"
b11 )
b110 (
b1000011 $
b1000011 &
1#
b1000011 %
#135000
b0 !
b0 '
0"
b0 )
b0 (
0#
#136000
b101 !
b101 '
1"
b11 )
b110 (
b1000100 $
b1000100 &
1#
b1000100 %
#137000
b0 !
b0 '
0"
b0 )
b0 (
0#
#138000
b101 !
b101 '
1"
b11 )
b110 (
b1000101 $
b1000101 &
1#
b1000101 %
#139000
b0 !
b0 '
0"
b0 )
b0 (
0#
#140000
b101 !
b101 '
1"
b11 )
b110 (
b1000110 $
b1000110 &
1#
b1000110 %
#141000
b0 !
b0 '
0"
b0 )
b0 (
0#
#142000
b101 !
b101 '
1"
b11 )
b110 (
b1000111 $
b1000111 &
1#
b1000111 %
#143000
b0 !
b0 '
0"
b0 )
b0 (
0#
#144000
b101 !
b101 '
1"
b11 )
b110 (
b1001000 $
b1001000 &
1#
b1001000 %
#145000
b0 !
b0 '
0"
b0 )
b0 (
0#
#146000
b101 !
b101 '
1"
b11 )
b110 (
b1001001 $
b1001001 &
1#
b1001001 %
#147000
b0 !
b0 '
0"
b0 )
b0 (
0#
#148000
b101 !
b101 '
1"
b11 )
b110 (
b1001010 $
b1001010 &
1#
b1001010 %
#149000
b0 !
b0 '
0"
b0 )
b0 (
0#
#150000
b101 !
b101 '
1"
b11 )
b110 (
b1001011 $
b1001011 &
1#
b1001011 %
#151000
b0 !
b0 '
0"
b0 )
b0 (
0#
#152000
b101 !
b101 '
1"
b11 )
b110 (
b1001100 $
b1001100 &
1#
b1001100 %
#153000
b0 !
b0 '
0"
b0 )
b0 (
0#
#154000
b101 !
b101 '
1"
b11 )
b110 (
b1001101 $
b1001101 &
1#
b1001101 %
#155000
b0 !
b0 '
0"
b0 )
b0 (
0#
#156000
b101 !
b101 '
1"
b11 )
b110 (
b1001110 $
b1001110 &
1#
b1001110 %
#157000
b0 !
b0 '
0"
b0 )
b0 (
0#
#158000
b101 !
b101 '
1"
b11 )
b110 (
b1001111 $
b1001111 &
1#
b1001111 %
#159000
b0 !
b0 '
0"
b0 )
b0 (
0#
#160000
b101 !
b101 '
1"
b11 )
b110 (
b1010000 $
b1010000 &
1#
b1010000 %
#161000
b0 !
b0 '
0"
b0 )
b0 (
0#
#162000
b101 !
b101 '
1"
b11 )
b110 (
b1010001 $
b1010001 &
1#
b1010001 %
#163000
b0 !
b0 '
0"
b0 )
b0 (
0#
#164000
b101 !
b101 '
1"
b11 )
b110 (
b1010010 $
b1010010 &
1#
b1010010 %
#165000
b0 !
b0 '
0"
b0 )
b0 (
0#
#166000
b101 !
b101 '
1"
b11 )
b110 (
b1010011 $
b1010011 &
1#
b1010011 %
#167000
b0 !
b0 '
0"
b0 )
b0 (
0#
#168000
b101 !
b101 '
1"
b11 )
b110 (
b1010100 $
b1010100 &
1#
b1010100 %
#169000
b0 !
b0 '
0"
b0 )
b0 (
0#
#170000
b101 !
b101 '
1"
b11 )
b110 (
b1010101 $
b1010101 &
1#
b1010101 %
#171000
b0 !
b0 '
0"
b0 )
b0 (
0#
#172000
b101 !
b101 '
1"
b11 )
b110 (
b1010110 $
b1010110 &
1#
b1010110 %
#173000
b0 !
b0 '
0"
b0 )
b0 (
0#
#174000
b101 !
b101 '
1"
b11 )
b110 (
b1010111 $
b1010111 &
1#
b1010111 %
#175000
b0 !
b0 '
0"
b0 )
b0 (
0#
#176000
b101 !
b101 '
1"
b11 )
b110 (
b1011000 $
b1011000 &
1#
b1011000 %
#177000
b0 !
b0 '
0"
b0 )
b0 (
0#
#178000
b101 !
b101 '
1"
b11 )
b110 (
b1011001 $
b1011001 &
1#
b1011001 %
#179000
b0 !
b0 '
0"
b0 )
b0 (
0#
#180000
b101 !
b101 '
1"
b11 )
b110 (
b1011010 $
b1011010 &
1#
b1011010 %
#181000
b0 !
b0 '
0"
b0 )
b0 (
0#
#182000
b101 !
b101 '
1"
b11 )
b110 (
b1011011 $
b1011011 &
1#
b1011011 %
#183000
b0 !
b0 '
0"
b0 )
b0 (
0#
#184000
b101 !
b101 '
1"
b11 )
b110 (
b1011100 $
b1011100 &
1#
b1011100 %
#185000
b0 !
b0 '
0"
b0 )
b0 (
0#
#186000
b101 !
b101 '
1"
b11 )
b110 (
b1011101 $
b1011101 &
1#
b1011101 %
#187000
b0 !
b0 '
0"
b0 )
b0 (
0#
#188000
b101 !
b101 '
1"
b11 )
b110 (
b1011110 $
b1011110 &
1#
b1011110 %
#189000
b0 !
b0 '
0"
b0 )
b0 (
0#
#190000
b101 !
b101 '
1"
b11 )
b110 (
b1011111 $
b1011111 &
1#
b1011111 %
#191000
b0 !
b0 '
0"
b0 )
b0 (
0#
#192000
b101 !
b101 '
1"
b11 )
b110 (
b1100000 $
b1100000 &
1#
b1100000 %
#193000
b0 !
b0 '
0"
b0 )
b0 (
0#
#194000
b101 !
b101 '
1"
b11 )
b110 (
b1100001 $
b1100001 &
1#
b1100001 %
#195000
b0 !
b0 '
0"
b0 )
b0 (
0#
#196000
b101 !
b101 '
1"
b11 )
b110 (
b1100010 $
b1100010 &
1#
b1100010 %
#197000
b0 !
b0 '
0"
b0 )
b0 (
0#
#198000
b101 !
b101 '
1"
b11 )
b110 (
b1100011 $
b1100011 &
1#
b1100011 %
#199000
b0 !
b0 '
0"
b0 )
b0 (
0#
#200000
b101 !
b101 '
1"
b11 )
b110 (
b1100100 $
b1100100 &
1#
b1100100 %
#201000
b0 !
b0 '
0"
b0 )
b0 (
0#
#202000
b101 !
b101 '
1"
b11 )
b110 (
b1100101 $
b1100101 &
1#
b1100101 %
#203000
b0 !
b0 '
0"
b0 )
b0 (
0#
#204000
b101 !
b101 '
1"
b11 )
b110 (
b1100110 $
b1100110 &
1#
b1100110 %
#205000
b0 !
b0 '
0"
b0 )
b0 (
0#
#206000
b101 !
b101 '
1"
b11 )
b110 (
b1100111 $
b1100111 &
1#
b1100111 %
#207000
b0 !
b0 '
0"
b0 )
b0 (
0#
#208000
b101 !
b101 '
1"
b11 )
b110 (
b1101000 $
b1101000 &
1#
b1101000 %
#209000
b0 !
b0 '
0"
b0 )
b0 (
0#
#210000
b101 !
b101 '
1"
b11 )
b110 (
b1101001 $
b1101001 &
1#
b1101001 %
#211000
b0 !
b0 '
0"
b0 )
b0 (
0#
#212000
b101 !
b101 '
1"
b11 )
b110 (
b1101010 $
b1101010 &
1#
b1101010 %
#213000
b0 !
b0 '
0"
b0 )
b0 (
0#
#214000
b101 !
b101 '
1"
b11 )
b110 (
b1101011 $
b1101011 &
1#
b1101011 %
#215000
b0 !
b0 '
0"
b0 )
b0 (
0#
#216000
b101 !
b101 '
1"
b11 )
b110 (
b1101100 $
b1101100 &
1#
b1101100 %
#217000
b0 !
b0 '
0"
b0 )
b0 (
0#
#218000
b101 !
b101 '
1"
b11 )
b110 (
b1101101 $
b1101101 &
1#
b1101101 %
#219000
b0 !
b0 '
0"
b0 )
b0 (
0#
#220000
b101 !
b101 '
1"
b11 )
b110 (
b1101110 $
b1101110 &
1#
b1101110 %
#221000
b0 !
b0 '
0"
b0 )
b0 (
0#
#222000
b101 !
b101 '
1"
b11 )
b110 (
b1101111 $
b1101111 &
1#
b1101111 %
#223000
b0 !
b0 '
0"
b0 )
b0 (
0#
#224000
b101 !
b101 '
1"
b11 )
b110 (
b1110000 $
b1110000 &
1#
b1110000 %
#225000
b0 !
b0 '
0"
b0 )
b0 (
0#
#226000
b101 !
b101 '
1"
b11 )
b110 (
b1110001 $
b1110001 &
1#
b1110001 %
#227000
b0 !
b0 '
0"
b0 )
b0 (
0#
#228000
b101 !
b101 '
1"
b11 )
b110 (
b1110010 $
b1110010 &
1#
b1110010 %
#229000
b0 !
b0 '
0"
b0 )
b0 (
0#
#230000
b101 !
b101 '
1"
b11 )
b110 (
b1110011 $
b1110011 &
1#
b1110011 %
#231000
b0 !
b0 '
0"
b0 )
b0 (
0#
#232000
b101 !
b101 '
1"
b11 )
b110 (
b1110100 $
b1110100 &
1#
b1110100 %
#233000
b0 !
b0 '
0"
b0 )
b0 (
0#
#234000
b101 !
b101 '
1"
b11 )
b110 (
b1110101 $
b1110101 &
1#
b1110101 %
#235000
b0 !
b0 '
0"
b0 )
b0 (
0#
#236000
b101 !
b101 '
1"
b11 )
b110 (
b1110110 $
b1110110 &
1#
b1110110 %
#237000
b0 !
b0 '
0"
b0 )
b0 (
0#
#238000
b101 !
b101 '
1"
b11 )
b110 (
b1110111 $
b1110111 &
1#
b1110111 %
#239000
b0 !
b0 '
0"
b0 )
b0 (
0#
#240000
b101 !
b101 '
1"
b11 )
b110 (
b1111000 $
b1111000 &
1#
b1111000 %
#241000
b0 !
b0 '
0"
b0 )
b0 (
0#
#242000
b101 !
b101 '
1"
b11 )
b110 (
b1111001 $
b1111001 &
1#
b1111001 %
#243000
b0 !
b0 '
0"
b0 )
b0 (
0#
#244000
b101 !
b101 '
1"
b11 )
b110 (
b1111010 $
b1111010 &
1#
b1111010 %
#245000
b0 !
b0 '
0"
b0 )
b0 (
0#
#246000
b101 !
b101 '
1"
b11 )
b110 (
b1111011 $
b1111011 &
1#
b1111011 %
#247000
b0 !
b0 '
0"
b0 )
b0 (
0#
#248000
b101 !
b101 '
1"
b11 )
b110 (
b1111100 $
b1111100 &
1#
b1111100 %
#249000
b0 !
b0 '
0"
b0 )
b0 (
0#
#250000
b101 !
b101 '
1"
b11 )
b110 (
b1111101 $
b1111101 &
1#
b1111101 %
#251000
b0 !
b0 '
0"
b0 )
b0 (
0#
#252000
b101 !
b101 '
1"
b11 )
b110 (
b1111110 $
b1111110 &
1#
b1111110 %
#253000
b0 !
b0 '
0"
b0 )
b0 (
0#
#254000
b101 !
b101 '
1"
b11 )
b110 (
b1111111 $
b1111111 &
1#
b1111111 %
#255000
b0 !
b0 '
0"
b0 )
b0 (
0#
#256000
b100 !
b100 '
1"
b11 )
b111 (
b10000000 $
b10000000 &
1#
b10000000 %
#257000
b0 !
b0 '
0"
b0 )
b0 (
0#
#258000
b100 !
b100 '
1"
b11 )
b111 (
b10000001 $
b10000001 &
1#
b10000001 %
#259000
b0 !
b0 '
0"
b0 )
b0 (
0#
#260000
b100 !
b100 '
1"
b11 )
b111 (
b10000010 $
b10000010 &
1#
b10000010 %
#261000
b0 !
b0 '
0"
b0 )
b0 (
0#
#262000
b100 !
b100 '
1"
b11 )
b111 (
b10000011 $
b10000011 &
1#
b10000011 %
#263000
b0 !
b0 '
0"
b0 )
b0 (
0#
#264000
b100 !
b100 '
1"
b11 )
b111 (
b10000100 $
b10000100 &
1#
b10000100 %
#265000
b0 !
b0 '
0"
b0 )
b0 (
0#
#266000
b100 !
b100 '
1"
b11 )
b111 (
b10000101 $
b10000101 &
1#
b10000101 %
#267000
b0 !
b0 '
0"
b0 )
b0 (
0#
#268000
b100 !
b100 '
1"
b11 )
b111 (
b10000110 $
b10000110 &
1#
b10000110 %
#269000
b0 !
b0 '
0"
b0 )
b0 (
0#
#270000
b100 !
b100 '
1"
b11 )
b111 (
b10000111 $
b10000111 &
1#
b10000111 %
#271000
b0 !
b0 '
0"
b0 )
b0 (
0#
#272000
b100 !
b100 '
1"
b11 )
b111 (
b10001000 $
b10001000 &
1#
b10001000 %
#273000
b0 !
b0 '
0"
b0 )
b0 (
0#
#274000
b100 !
b100 '
1"
b11 )
b111 (
b10001001 $
b10001001 &
1#
b10001001 %
#275000
b0 !
b0 '
0"
b0 )
b0 (
0#
#276000
b100 !
b100 '
1"
b11 )
b111 (
b10001010 $
b10001010 &
1#
b10001010 %
#277000
b0 !
b0 '
0"
b0 )
b0 (
0#
#278000
b100 !
b100 '
1"
b11 )
b111 (
b10001011 $
b10001011 &
1#
b10001011 %
#279000
b0 !
b0 '
0"
b0 )
b0 (
0#
#280000
b100 !
b100 '
1"
b11 )
b111 (
b10001100 $
b10001100 &
1#
b10001100 %
#281000
b0 !
b0 '
0"
b0 )
b0 (
0#
#282000
b100 !
b100 '
1"
b11 )
b111 (
b10001101 $
b10001101 &
1#
b10001101 %
#283000
b0 !
b0 '
0"
b0 )
b0 (
0#
#284000
b100 !
b100 '
1"
b11 )
b111 (
b10001110 $
b10001110 &
1#
b10001110 %
#285000
b0 !
b0 '
0"
b0 )
b0 (
0#
#286000
b100 !
b100 '
1"
b11 )
b111 (
b10001111 $
b10001111 &
1#
b10001111 %
#287000
b0 !
b0 '
0"
b0 )
b0 (
0#
#288000
b100 !
b100 '
1"
b11 )
b111 (
b10010000 $
b10010000 &
1#
b10010000 %
#289000
b0 !
b0 '
0"
b0 )
b0 (
0#
#290000
b100 !
b100 '
1"
b11 )
b111 (
b10010001 $
b10010001 &
1#
b10010001 %
#291000
b0 !
b0 '
0"
b0 )
b0 (
0#
#292000
b100 !
b100 '
1"
b11 )
b111 (
b10010010 $
b10010010 &
1#
b10010010 %
#293000
b0 !
b0 '
0"
b0 )
b0 (
0#
#294000
b100 !
b100 '
1"
b11 )
b111 (
b10010011 $
b10010011 &
1#
b10010011 %
#295000
b0 !
b0 '
0"
b0 )
b0 (
0#
#296000
b100 !
b100 '
1"
b11 )
b111 (
b10010100 $
b10010100 &
1#
b10010100 %
#297000
b0 !
b0 '
0"
b0 )
b0 (
0#
#298000
b100 !
b100 '
1"
b11 )
b111 (
b10010101 $
b10010101 &
1#
b10010101 %
#299000
b0 !
b0 '
0"
b0 )
b0 (
0#
#300000
b100 !
b100 '
1"
b11 )
b111 (
b10010110 $
b10010110 &
1#
b10010110 %
#301000
b0 !
b0 '
0"
b0 )
b0 (
0#
#302000
b100 !
b100 '
1"
b11 )
b111 (
b10010111 $
b10010111 &
1#
b10010111 %
#303000
b0 !
b0 '
0"
b0 )
b0 (
0#
#304000
b100 !
b100 '
1"
b11 )
b111 (
b10011000 $
b10011000 &
1#
b10011000 %
#305000
b0 !
b0 '
0"
b0 )
b0 (
0#
#306000
b100 !
b100 '
1"
b11 )
b111 (
b10011001 $
b10011001 &
1#
b10011001 %
#307000
b0 !
b0 '
0"
b0 )
b0 (
0#
#308000
b100 !
b100 '
1"
b11 )
b111 (
b10011010 $
b10011010 &
1#
b10011010 %
#309000
b0 !
b0 '
0"
b0 )
b0 (
0#
#310000
b100 !
b100 '
1"
b11 )
b111 (
b10011011 $
b10011011 &
1#
b10011011 %
#311000
b0 !
b0 '
0"
b0 )
b0 (
0#
#312000
b100 !
b100 '
1"
b11 )
b111 (
b10011100 $
b10011100 &
1#
b10011100 %
#313000
b0 !
b0 '
0"
b0 )
b0 (
0#
#314000
b100 !
b100 '
1"
b11 )
b111 (
b10011101 $
b10011101 &
1#
b10011101 %
#315000
b0 !
b0 '
0"
b0 )
b0 (
0#
#316000
b100 !
b100 '
1"
b11 )
b111 (
b10011110 $
b10011110 &
1#
b10011110 %
#317000
b0 !
b0 '
0"
b0 )
b0 (
0#
#318000
b100 !
b100 '
1"
b11 )
b111 (
b10011111 $
b10011111 &
1#
b10011111 %
#319000
b0 !
b0 '
0"
b0 )
b0 (
0#
#320000
b100 !
b100 '
1"
b11 )
b111 (
b10100000 $
b10100000 &
1#
b10100000 %
#321000
b0 !
b0 '
0"
b0 )
b0 (
0#
#322000
b100 !
b100 '
1"
b11 )
b111 (
b10100001 $
b10100001 &
1#
b10100001 %
#323000
b0 !
b0 '
0"
b0 )
b0 (
0#
#324000
b100 !
b100 '
1"
b11 )
b111 (
b10100010 $
b10100010 &
1#
b10100010 %
#325000
b0 !
b0 '
0"
b0 )
b0 (
0#
#326000
b100 !
b100 '
1"
b11 )
b111 (
b10100011 $
b10100011 &
1#
b10100011 %
#327000
b0 !
b0 '
0"
b0 )
b0 (
0#
#328000
b100 !
b100 '
1"
b11 )
b111 (
b10100100 $
b10100100 &
1#
b10100100 %
#329000
b0 !
b0 '
0"
b0 )
b0 (
0#
#330000
b100 !
b100 '
1"
b11 )
b111 (
b10100101 $
b10100101 &
1#
b10100101 %
#331000
b0 !
b0 '
0"
b0 )
b0 (
0#
#332000
b100 !
b100 '
1"
b11 )
b111 (
b10100110 $
b10100110 &
1#
b10100110 %
#333000
b0 !
b0 '
0"
b0 )
b0 (
0#
#334000
b100 !
b100 '
1"
b11 )
b111 (
b10100111 $
b10100111 &
1#
b10100111 %
#335000
b0 !
b0 '
0"
b0 )
b0 (
0#
#336000
b100 !
b100 '
1"
b11 )
b111 (
b10101000 $
b10101000 &
1#
b10101000 %
#337000
b0 !
b0 '
0"
b0 )
b0 (
0#
#338000
b100 !
b100 '
1"
b11 )
b111 (
b10101001 $
b10101001 &
1#
b10101001 %
#339000
b0 !
b0 '
0"
b0 )
b0 (
0#
#340000
b100 !
b100 '
1"
b11 )
b111 (
b10101010 $
b10101010 &
1#
b10101010 %
#341000
b0 !
b0 '
0"
b0 )
b0 (
0#
#342000
b100 !
b100 '
1"
b11 )
b111 (
b10101011 $
b10101011 &
1#
b10101011 %
#343000
b0 !
b0 '
0"
b0 )
b0 (
0#
#344000
b100 !
b100 '
1"
b11 )
b111 (
b10101100 $
b10101100 &
1#
b10101100 %
#345000
b0 !
b0 '
0"
b0 )
b0 (
0#
#346000
b100 !
b100 '
1"
b11 )
b111 (
b10101101 $
b10101101 &
1#
b10101101 %
#347000
b0 !
b0 '
0"
b0 )
b0 (
0#
#348000
b100 !
b100 '
1"
b11 )
b111 (
b10101110 $
b10101110 &
1#
b10101110 %
#349000
b0 !
b0 '
0"
b0 )
b0 (
0#
#350000
b100 !
b100 '
1"
b11 )
b111 (
b10101111 $
b10101111 &
1#
b10101111 %
#351000
b0 !
b0 '
0"
b0 )
b0 (
0#
#352000
b100 !
b100 '
1"
b11 )
b111 (
b10110000 $
b10110000 &
1#
b10110000 %
#353000
b0 !
b0 '
0"
b0 )
b0 (
0#
