assignment4/multiplier/bomu32.v
module bomu32 #(
    parameter n = 16
) (
    input  signed [n-1:0]  q,
    input  signed [n-1:0] m,
    output reg [2*(n+1)-1:0] p
);
integer i;
    reg signed [2*(n+1):0] acc;
    reg [n :0] qb , mb;
    always @(*) begin
        qb = {q[n-1] , q};
        mb = {m[n-1] , m};
        acc = { {(n+1){1'b0}}, qb, 1'b0 };
        for (i = 0; i < n+1; i = i + 1) begin
            case (acc[1:0])
                2'b01: acc[2*(n+1)-:n+1] = acc[2*(n+1)-:n+1] +  mb;
                2'b10: acc[2*(n+1)-:n+1] = acc[2*(n+1)-:n+1] -  mb;
                default: ;
            endcase
            acc = acc>>>1; 
        end
     p = acc[2*(n+1):1];
    end
endmodule

assignment4/multiplier/bomu32tb.v
`timescale 1ns/1ps

module bomu32tb;
    localparam n = 32;  
    reg [n-1:0] a , b;
    wire [2*(n+1)-1:0] m;

    bomu32 #(.n(n)) multiplier( a ,b , m);

    integer i = 0;
    integer j = 0;

    initial begin
        $dumpfile("bomu32v.vcd");
        $dumpvars(0 , bomu32tb);
        a =0;
        b =0;
        
        for (i  =0  ;i <n ; i = i+1 ) begin
                a = 2**i;
            for (j = 0; j<n; j = j+1) begin
                b = 2**j;
                #1;
            end
            #1;
        end
        $finish;
    end
endmodule

assignment4/multiplier/bomu32v.vcd
$date
	Sun Jun 15 17:08:30 2025
$end
$version
	Icarus Verilog
$end
$timescale
	1ps
$end
$scope module bomu32tb $end
$var wire 66 ! m [65:0] $end
$var parameter 32 " n $end
$var reg 32 # a [31:0] $end
$var reg 32 $ b [31:0] $end
$var integer 32 % i [31:0] $end
$var integer 32 & j [31:0] $end
$scope module multiplier $end
$var wire 32 ' m [31:0] $end
$var wire 32 ( q [31:0] $end
$var parameter 32 ) n $end
$var reg 67 * acc [66:0] $end
$var reg 33 + mb [32:0] $end
$var reg 66 , p [65:0] $end
$var reg 33 - qb [32:0] $end
$var integer 32 . i [31:0] $end
$upscope $end
$upscope $end
$enddefinitions $end
$comment Show the parameter values. $end
$dumpall
b100000 )
b100000 "
$end
#0
$dumpvars
b100001 .
b1 -
b1 ,
b1 +
b10 *
b1 (
b1 '
b0 &
b0 %
b1 $
b1 #
b1 !
$end
#1000
b10 !
b10 ,
b100 *
b100001 .
b10 +
b10 $
b10 '
b1 &
#2000
b100 !
b100 ,
b100001 .
b1000 *
b100 +
b100 $
b100 '
b10 &
#3000
b1000 !
b1000 ,
b100001 .
b10000 *
b1000 +
b1000 $
b1000 '
b11 &
#4000
b10000 !
b10000 ,
b100001 .
b100000 *
b10000 +
b10000 $
b10000 '
b100 &
#5000
b100000 !
b100000 ,
b100001 .
b1000000 *
b100000 +
b100000 $
b100000 '
b101 &
#6000
b1000000 !
b1000000 ,
b100001 .
b10000000 *
b1000000 +
b1000000 $
b1000000 '
b110 &
#7000
b10000000 !
b10000000 ,
b100001 .
b100000000 *
b10000000 +
b10000000 $
b10000000 '
b111 &
#8000
b100000000 !
b100000000 ,
b100001 .
b1000000000 *
b100000000 +
b100000000 $
b100000000 '
b1000 &
#9000
b1000000000 !
b1000000000 ,
b100001 .
b10000000000 *
b1000000000 +
b1000000000 $
b1000000000 '
b1001 &
#10000
b10000000000 !
b10000000000 ,
b100001 .
b100000000000 *
b10000000000 +
b10000000000 $
b10000000000 '
b1010 &
#11000
b100000000000 !
b100000000000 ,
b100001 .
b1000000000000 *
b100000000000 +
b100000000000 $
b100000000000 '
b1011 &
#12000
b1000000000000 !
b1000000000000 ,
b100001 .
b10000000000000 *
b1000000000000 +
b1000000000000 $
b1000000000000 '
b1100 &
#13000
b10000000000000 !
b10000000000000 ,
b100001 .
b100000000000000 *
b10000000000000 +
b10000000000000 $
b10000000000000 '
b1101 &
#14000
b100000000000000 !
b100000000000000 ,
b100001 .
b1000000000000000 *
b100000000000000 +
b100000000000000 $
b100000000000000 '
b1110 &
#15000
b1000000000000000 !
b1000000000000000 ,
b100001 .
b10000000000000000 *
b1000000000000000 +
b1000000000000000 $
b1000000000000000 '
b1111 &
#16000
b10000000000000000 !
b10000000000000000 ,
b100001 .
b100000000000000000 *
b10000000000000000 +
b10000000000000000 $
b10000000000000000 '
b10000 &
#17000
b100000000000000000 !
b100000000000000000 ,
b100001 .
b1000000000000000000 *
b100000000000000000 +
b100000000000000000 $
b100000000000000000 '
b10001 &
#18000
b1000000000000000000 !
b1000000000000000000 ,
b100001 .
b10000000000000000000 *
b1000000000000000000 +
b1000000000000000000 $
b1000000000000000000 '
b10010 &
#19000
b10000000000000000000 !
b10000000000000000000 ,
b100001 .
b100000000000000000000 *
b10000000000000000000 +
b10000000000000000000 $
b10000000000000000000 '
b10011 &
#20000
b100000000000000000000 !
b100000000000000000000 ,
b100001 .
b1000000000000000000000 *
b100000000000000000000 +
b100000000000000000000 $
b100000000000000000000 '
b10100 &
#21000
b1000000000000000000000 !
b1000000000000000000000 ,
b100001 .
b10000000000000000000000 *
b1000000000000000000000 +
b1000000000000000000000 $
b1000000000000000000000 '
b10101 &
#22000
b10000000000000000000000 !
b10000000000000000000000 ,
b100001 .
b100000000000000000000000 *
b10000000000000000000000 +
b10000000000000000000000 $
b10000000000000000000000 '
b10110 &
#23000
b100000000000000000000000 !
b100000000000000000000000 ,
b100001 .
b1000000000000000000000000 *
b100000000000000000000000 +
b100000000000000000000000 $
b100000000000000000000000 '
b10111 &
#24000
b1000000000000000000000000 !
b1000000000000000000000000 ,
b100001 .
b10000000000000000000000000 *
b1000000000000000000000000 +
b1000000000000000000000000 $
b1000000000000000000000000 '
b11000 &
#25000
b10000000000000000000000000 !
b10000000000000000000000000 ,
b100001 .
b100000000000000000000000000 *
b10000000000000000000000000 +
b10000000000000000000000000 $
b10000000000000000000000000 '
b11001 &
#26000
b100000000000000000000000000 !
b100000000000000000000000000 ,
b100001 .
b1000000000000000000000000000 *
b100000000000000000000000000 +
b100000000000000000000000000 $
b100000000000000000000000000 '
b11010 &
#27000
b1000000000000000000000000000 !
b1000000000000000000000000000 ,
b100001 .
b10000000000000000000000000000 *
b1000000000000000000000000000 +
b1000000000000000000000000000 $
b1000000000000000000000000000 '
b11011 &
#28000
b10000000000000000000000000000 !
b10000000000000000000000000000 ,
b100001 .
b100000000000000000000000000000 *
b10000000000000000000000000000 +
b10000000000000000000000000000 $
b10000000000000000000000000000 '
b11100 &
#29000
b100000000000000000000000000000 !
b100000000000000000000000000000 ,
b100001 .
b1000000000000000000000000000000 *
b100000000000000000000000000000 +
b100000000000000000000000000000 $
b100000000000000000000000000000 '
b11101 &
#30000
b1000000000000000000000000000000 !
b1000000000000000000000000000000 ,
b100001 .
b10000000000000000000000000000000 *
b1000000000000000000000000000000 +
b1000000000000000000000000000000 $
b1000000000000000000000000000000 '
b11110 &
#31000
b111111111111111111111111111111111110000000000000000000000000000000 !
b111111111111111111111111111111111110000000000000000000000000000000 ,
b100001 .
b1111111111111111111111111111111111100000000000000000000000000000000 *
b110000000000000000000000000000000 +
b10000000000000000000000000000000 $
b10000000000000000000000000000000 '
b11111 &
#32000
b100000 &
#33000
b10 !
b10 ,
b100001 .
b100 *
b1 +
b10 -
b1 $
b1 '
b0 &
b10 #
b10 (
b1 %
#34000
b100 !
b100 ,
b1000 *
b100001 .
b10 +
b10 $
b10 '
b1 &
#35000
b1000 !
b1000 ,
b100001 .
b10000 *
b100 +
b100 $
b100 '
b10 &
#36000
b10000 !
b10000 ,
b100001 .
b100000 *
b1000 +
b1000 $
b1000 '
b11 &
#37000
b100000 !
b100000 ,
b100001 .
b1000000 *
b10000 +
b10000 $
b10000 '
b100 &
#38000
b1000000 !
b1000000 ,
b100001 .
b10000000 *
b100000 +
b100000 $
b100000 '
b101 &
#39000
b10000000 !
b10000000 ,
b100001 .
b100000000 *
b1000000 +
b1000000 $
b1000000 '
b110 &
#40000
b100000000 !
b100000000 ,
b100001 .
b1000000000 *
b10000000 +
b10000000 $
b10000000 '
b111 &
#41000
b1000000000 !
b1000000000 ,
b100001 .
b10000000000 *
b100000000 +
b100000000 $
b100000000 '
b1000 &
#42000
b10000000000 !
b10000000000 ,
b100001 .
b100000000000 *
b1000000000 +
b1000000000 $
b1000000000 '
b1001 &
#43000
b100000000000 !
b100000000000 ,
b100001 .
b1000000000000 *
b10000000000 +
b10000000000 $
b10000000000 '
b1010 &
#44000
b1000000000000 !
b1000000000000 ,
b100001 .
b10000000000000 *
b100000000000 +
b100000000000 $
b100000000000 '
b1011 &
#45000
b10000000000000 !
b10000000000000 ,
b100001 .
b100000000000000 *
b1000000000000 +
b1000000000000 $
b1000000000000 '
b1100 &
#46000
b100000000000000 !
b100000000000000 ,
b100001 .
b1000000000000000 *
b10000000000000 +
b10000000000000 $
b10000000000000 '
b1101 &
#47000
b1000000000000000 !
b1000000000000000 ,
b100001 .
b10000000000000000 *
b100000000000000 +
b100000000000000 $
b100000000000000 '
b1110 &
#48000
b10000000000000000 !
b10000000000000000 ,
b100001 .
b100000000000000000 *
b1000000000000000 +
b1000000000000000 $
b1000000000000000 '
b1111 &
#49000
b100000000000000000 !
b100000000000000000 ,
b100001 .
b1000000000000000000 *
b10000000000000000 +
b10000000000000000 $
b10000000000000000 '
b10000 &
#50000
b1000000000000000000 !
b1000000000000000000 ,
b100001 .
b10000000000000000000 *
b100000000000000000 +
b100000000000000000 $
b100000000000000000 '
b10001 &
#51000
b10000000000000000000 !
b10000000000000000000 ,
b100001 .
b100000000000000000000 *
b1000000000000000000 +
b1000000000000000000 $
b1000000000000000000 '
b10010 &
#52000
b100000000000000000000 !
b100000000000000000000 ,
b100001 .
b1000000000000000000000 *
b10000000000000000000 +
b10000000000000000000 $
b10000000000000000000 '
b10011 &
#53000
b1000000000000000000000 !
b1000000000000000000000 ,
b100001 .
b10000000000000000000000 *
b100000000000000000000 +
b100000000000000000000 $
b100000000000000000000 '
b10100 &
#54000
b10000000000000000000000 !
b10000000000000000000000 ,
b100001 .
b100000000000000000000000 *
b1000000000000000000000 +
b1000000000000000000000 $
b1000000000000000000000 '
b10101 &
#55000
b100000000000000000000000 !
b100000000000000000000000 ,
b100001 .
b1000000000000000000000000 *
b10000000000000000000000 +
b10000000000000000000000 $
b10000000000000000000000 '
b10110 &
#56000
b1000000000000000000000000 !
b1000000000000000000000000 ,
b100001 .
b10000000000000000000000000 *
b100000000000000000000000 +
b100000000000000000000000 $
b100000000000000000000000 '
b10111 &
#57000
b10000000000000000000000000 !
b10000000000000000000000000 ,
b100001 .
b100000000000000000000000000 *
b1000000000000000000000000 +
b1000000000000000000000000 $
b1000000000000000000000000 '
b11000 &
#58000
b100000000000000000000000000 !
b100000000000000000000000000 ,
b100001 .
b1000000000000000000000000000 *
b10000000000000000000000000 +
b10000000000000000000000000 $
b10000000000000000000000000 '
b11001 &
#59000
b1000000000000000000000000000 !
b1000000000000000000000000000 ,
b100001 .
b10000000000000000000000000000 *
b100000000000000000000000000 +
b100000000000000000000000000 $
b100000000000000000000000000 '
b11010 &
#60000
b10000000000000000000000000000 !
b10000000000000000000000000000 ,
b100001 .
b100000000000000000000000000000 *
b1000000000000000000000000000 +
b1000000000000000000000000000 $
b1000000000000000000000000000 '
b11011 &
#61000
b100000000000000000000000000000 !
b100000000000000000000000000000 ,
b100001 .
b1000000000000000000000000000000 *
b10000000000000000000000000000 +
b10000000000000000000000000000 $
b10000000000000000000000000000 '
b11100 &
#62000
b1000000000000000000000000000000 !
b1000000000000000000000000000000 ,
b100001 .
b10000000000000000000000000000000 *
b100000000000000000000000000000 +
b100000000000000000000000000000 $
b100000000000000000000000000000 '
b11101 &
#63000
b10000000000000000000000000000000 !
b10000000000000000000000000000000 ,
b100001 .
b100000000000000000000000000000000 *
b1000000000000000000000000000000 +
b1000000000000000000000000000000 $
b1000000000000000000000000000000 '
b11110 &
#64000
b111111111111111111111111111111111100000000000000000000000000000000 !
b111111111111111111111111111111111100000000000000000000000000000000 ,
b100001 .
b1111111111111111111111111111111111000000000000000000000000000000000 *
b110000000000000000000000000000000 +
b10000000000000000000000000000000 $
b10000000000000000000000000000000 '
b11111 &
#65000
b100000 &
#66000
b100 !
b100 ,
b100001 .
b1000 *
b1 +
b100 -
b1 $
b1 '
b0 &
b100 #
b100 (
b10 %
#67000
b1000 !
b1000 ,
b10000 *
b100001 .
b10 +
b10 $
b10 '
b1 &
#68000
b10000 !
b10000 ,
b100001 .
b100000 *
b100 +
b100 $
b100 '
b10 &
#69000
b100000 !
b100000 ,
b100001 .
b1000000 *
b1000 +
b1000 $
b1000 '
b11 &
#70000
b1000000 !
b1000000 ,
b100001 .
b10000000 *
b10000 +
b10000 $
b10000 '
b100 &
#71000
b10000000 !
b10000000 ,
b100001 .
b100000000 *
b100000 +
b100000 $
b100000 '
b101 &
#72000
b100000000 !
b100000000 ,
b100001 .
b1000000000 *
b1000000 +
b1000000 $
b1000000 '
b110 &
#73000
b1000000000 !
b1000000000 ,
b100001 .
b10000000000 *
b10000000 +
b10000000 $
b10000000 '
b111 &
#74000
b10000000000 !
b10000000000 ,
b100001 .
b100000000000 *
b100000000 +
b100000000 $
b100000000 '
b1000 &
#75000
b100000000000 !
b100000000000 ,
b100001 .
b1000000000000 *
b1000000000 +
b1000000000 $
b1000000000 '
b1001 &
#76000
b1000000000000 !
b1000000000000 ,
b100001 .
b10000000000000 *
b10000000000 +
b10000000000 $
b10000000000 '
b1010 &
#77000
b10000000000000 !
b10000000000000 ,
b100001 .
b100000000000000 *
b100000000000 +
b100000000000 $
b100000000000 '
b1011 &
#78000
b100000000000000 !
b100000000000000 ,
b100001 .
b1000000000000000 *
b1000000000000 +
b1000000000000 $
b1000000000000 '
b1100 &
#79000
b1000000000000000 !
b1000000000000000 ,
b100001 .
b10000000000000000 *
b10000000000000 +
b10000000000000 $
b10000000000000 '
b1101 &
#80000
b10000000000000000 !
b10000000000000000 ,
b100001 .
b100000000000000000 *
b100000000000000 +
b100000000000000 $
b100000000000000 '
b1110 &
#81000
b100000000000000000 !
b100000000000000000 ,
b100001 .
b1000000000000000000 *
b1000000000000000 +
b1000000000000000 $
b1000000000000000 '
b1111 &
#82000
b1000000000000000000 !
b1000000000000000000 ,
b100001 .
b10000000000000000000 *
b10000000000000000 +
b10000000000000000 $
b10000000000000000 '
b10000 &
#83000
b10000000000000000000 !
b10000000000000000000 ,
b100001 .
b100000000000000000000 *
b100000000000000000 +
b100000000000000000 $
b100000000000000000 '
b10001 &
#84000
b100000000000000000000 !
b100000000000000000000 ,
b100001 .
b1000000000000000000000 *
b1000000000000000000 +
b1000000000000000000 $
b1000000000000000000 '
b10010 &
#85000
b1000000000000000000000 !
b1000000000000000000000 ,
b100001 .
b10000000000000000000000 *
b10000000000000000000 +
b10000000000000000000 $
b10000000000000000000 '
b10011 &
#86000
b10000000000000000000000 !
b10000000000000000000000 ,
b100001 .
b100000000000000000000000 *
b100000000000000000000 +
b100000000000000000000 $
b100000000000000000000 '
b10100 &
#87000
b100000000000000000000000 !
b100000000000000000000000 ,
b100001 .
b1000000000000000000000000 *
b1000000000000000000000 +
b1000000000000000000000 $
b1000000000000000000000 '
b10101 &
#88000
b1000000000000000000000000 !
b1000000000000000000000000 ,
b100001 .
b10000000000000000000000000 *
b10000000000000000000000 +
b10000000000000000000000 $
b10000000000000000000000 '
b10110 &
#89000
b10000000000000000000000000 !
b10000000000000000000000000 ,
b100001 .
b100000000000000000000000000 *
b100000000000000000000000 +
b100000000000000000000000 $
b100000000000000000000000 '
b10111 &
#90000
b100000000000000000000000000 !
b100000000000000000000000000 ,
b100001 .
b1000000000000000000000000000 *
b1000000000000000000000000 +
b1000000000000000000000000 $
b1000000000000000000000000 '
b11000 &
#91000
b1000000000000000000000000000 !
b1000000000000000000000000000 ,
b100001 .
b10000000000000000000000000000 *
b10000000000000000000000000 +
b10000000000000000000000000 $
b10000000000000000000000000 '
b11001 &
#92000
b10000000000000000000000000000 !
b10000000000000000000000000000 ,
b100001 .
b100000000000000000000000000000 *
b100000000000000000000000000 +
b100000000000000000000000000 $
b100000000000000000000000000 '
b11010 &
#93000
b100000000000000000000000000000 !
b100000000000000000000000000000 ,
b100001 .
b1000000000000000000000000000000 *
b1000000000000000000000000000 +
b1000000000000000000000000000 $
b1000000000000000000000000000 '
b11011 &
#94000
b1000000000000000000000000000000 !
b1000000000000000000000000000000 ,
b100001 .
b10000000000000000000000000000000 *
b10000000000000000000000000000 +
b10000000000000000000000000000 $
b10000000000000000000000000000 '
b11100 &
#95000
b10000000000000000000000000000000 !
b10000000000000000000000000000000 ,
b100001 .
b100000000000000000000000000000000 *
b100000000000000000000000000000 +
b100000000000000000000000000000 $
b100000000000000000000000000000 '
b11101 &
#96000
b100000000000000000000000000000000 !
b100000000000000000000000000000000 ,
b100001 .
b1000000000000000000000000000000000 *
b1000000000000000000000000000000 +
b1000000000000000000000000000000 $
b1000000000000000000000000000000 '
b11110 &
#97000
b111111111111111111111111111111111000000000000000000000000000000000 !
b111111111111111111111111111111111000000000000000000000000000000000 ,
b100001 .
b1111111111111111111111111111111110000000000000000000000000000000000 *
b110000000000000000000000000000000 +
b10000000000000000000000000000000 $
b10000000000000000000000000000000 '
b11111 &
#98000
b100000 &
#99000
b1000 !
b1000 ,
b100001 .
b10000 *
b1 +
b1000 -
b1 $
b1 '
b0 &
b1000 #
b1000 (
b11 %
#100000
b10000 !
b10000 ,
b100000 *
b100001 .
b10 +
b10 $
b10 '
b1 &
#101000
b100000 !
b100000 ,
b100001 .
b1000000 *
b100 +
b100 $
b100 '
b10 &
#102000
b1000000 !
b1000000 ,
b100001 .
b10000000 *
b1000 +
b1000 $
b1000 '
b11 &
#103000
b10000000 !
b10000000 ,
b100001 .
b100000000 *
b10000 +
b10000 $
b10000 '
b100 &
#104000
b100000000 !
b100000000 ,
b100001 .
b1000000000 *
b100000 +
b100000 $
b100000 '
b101 &
#105000
b1000000000 !
b1000000000 ,
b100001 .
b10000000000 *
b1000000 +
b1000000 $
b1000000 '
b110 &
#106000
b10000000000 !
b10000000000 ,
b100001 .
b100000000000 *
b10000000 +
b10000000 $
b10000000 '
b111 &
#107000
b100000000000 !
b100000000000 ,
b100001 .
b1000000000000 *
b100000000 +
b100000000 $
b100000000 '
b1000 &
#108000
b1000000000000 !
b1000000000000 ,
b100001 .
b10000000000000 *
b1000000000 +
b1000000000 $
b1000000000 '
b1001 &
#109000
b10000000000000 !
b10000000000000 ,
b100001 .
b100000000000000 *
b10000000000 +
b10000000000 $
b10000000000 '
b1010 &
#110000
b100000000000000 !
b100000000000000 ,
b100001 .
b1000000000000000 *
b100000000000 +
b100000000000 $
b100000000000 '
b1011 &
#111000
b1000000000000000 !
b1000000000000000 ,
b100001 .
b10000000000000000 *
b1000000000000 +
b1000000000000 $
b1000000000000 '
b1100 &
#112000
b10000000000000000 !
b10000000000000000 ,
b100001 .
b100000000000000000 *
b10000000000000 +
b10000000000000 $
b10000000000000 '
b1101 &
#113000
b100000000000000000 !
b100000000000000000 ,
b100001 .
b1000000000000000000 *
b100000000000000 +
b100000000000000 $
b100000000000000 '
b1110 &
#114000
b1000000000000000000 !
b1000000000000000000 ,
b100001 .
b10000000000000000000 *
b1000000000000000 +
b1000000000000000 $
b1000000000000000 '
b1111 &
#115000
b10000000000000000000 !
b10000000000000000000 ,
b100001 .
b100000000000000000000 *
b10000000000000000 +
b10000000000000000 $
b10000000000000000 '
b10000 &
#116000
b100000000000000000000 !
b100000000000000000000 ,
b100001 .
b1000000000000000000000 *
b100000000000000000 +
b100000000000000000 $
b100000000000000000 '
b10001 &
#117000
b1000000000000000000000 !
b1000000000000000000000 ,
b100001 .
b10000000000000000000000 *
b1000000000000000000 +
b1000000000000000000 $
b1000000000000000000 '
b10010 &
#118000
b10000000000000000000000 !
b10000000000000000000000 ,
b100001 .
b100000000000000000000000 *
b10000000000000000000 +
b10000000000000000000 $
b10000000000000000000 '
b10011 &
#119000
b100000000000000000000000 !
b100000000000000000000000 ,
b100001 .
b1000000000000000000000000 *
b100000000000000000000 +
b100000000000000000000 $
b100000000000000000000 '
b10100 &
#120000
b1000000000000000000000000 !
b1000000000000000000000000 ,
b100001 .
b10000000000000000000000000 *
b1000000000000000000000 +
b1000000000000000000000 $
b1000000000000000000000 '
b10101 &
#121000
b10000000000000000000000000 !
b10000000000000000000000000 ,
b100001 .
b100000000000000000000000000 *
b10000000000000000000000 +
b10000000000000000000000 $
b10000000000000000000000 '
b10110 &
#122000
b100000000000000000000000000 !
b100000000000000000000000000 ,
b100001 .
b1000000000000000000000000000 *
b100000000000000000000000 +
b100000000000000000000000 $
b100000000000000000000000 '
b10111 &
#123000
b1000000000000000000000000000 !
b1000000000000000000000000000 ,
b100001 .
b10000000000000000000000000000 *
b1000000000000000000000000 +
b1000000000000000000000000 $
b1000000000000000000000000 '
b11000 &
#124000
b10000000000000000000000000000 !
b10000000000000000000000000000 ,
b100001 .
b100000000000000000000000000000 *
b10000000000000000000000000 +
b10000000000000000000000000 $
b10000000000000000000000000 '
b11001 &
#125000
b100000000000000000000000000000 !
b100000000000000000000000000000 ,
b100001 .
b1000000000000000000000000000000 *
b100000000000000000000000000 +
b100000000000000000000000000 $
b100000000000000000000000000 '
b11010 &
#126000
b1000000000000000000000000000000 !
b1000000000000000000000000000000 ,
b100001 .
b10000000000000000000000000000000 *
b1000000000000000000000000000 +
b1000000000000000000000000000 $
b1000000000000000000000000000 '
b11011 &
#127000
b10000000000000000000000000000000 !
b10000000000000000000000000000000 ,
b100001 .
b100000000000000000000000000000000 *
b10000000000000000000000000000 +
b10000000000000000000000000000 $
b10000000000000000000000000000 '
b11100 &
#128000
b100000000000000000000000000000000 !
b100000000000000000000000000000000 ,
b100001 .
b1000000000000000000000000000000000 *
b100000000000000000000000000000 +
b100000000000000000000000000000 $
b100000000000000000000000000000 '
b11101 &
#129000
b1000000000000000000000000000000000 !
b1000000000000000000000000000000000 ,
b100001 .
b10000000000000000000000000000000000 *
b1000000000000000000000000000000 +
b1000000000000000000000000000000 $
b1000000000000000000000000000000 '
b11110 &
#130000
b111111111111111111111111111111110000000000000000000000000000000000 !
b111111111111111111111111111111110000000000000000000000000000000000 ,
b100001 .
b1111111111111111111111111111111100000000000000000000000000000000000 *
b110000000000000000000000000000000 +
b10000000000000000000000000000000 $
b10000000000000000000000000000000 '
b11111 &
#131000
b100000 &
#132000
b10000 !
b10000 ,
b100001 .
b100000 *
b1 +
b10000 -
b1 $
b1 '
b0 &
b10000 #
b10000 (
b100 %
#133000
b100000 !
b100000 ,
b1000000 *
b100001 .
b10 +
b10 $
b10 '
b1 &
#134000
b1000000 !
b1000000 ,
b100001 .
b10000000 *
b100 +
b100 $
b100 '
b10 &
#135000
b10000000 !
b10000000 ,
b100001 .
b100000000 *
b1000 +
b1000 $
b1000 '
b11 &
#136000
b100000000 !
b100000000 ,
b100001 .
b1000000000 *
b10000 +
b10000 $
b10000 '
b100 &
#137000
b1000000000 !
b1000000000 ,
b100001 .
b10000000000 *
b100000 +
b100000 $
b100000 '
b101 &
#138000
b10000000000 !
b10000000000 ,
b100001 .
b100000000000 *
b1000000 +
b1000000 $
b1000000 '
b110 &
#139000
b100000000000 !
b100000000000 ,
b100001 .
b1000000000000 *
b10000000 +
b10000000 $
b10000000 '
b111 &
#140000
b1000000000000 !
b1000000000000 ,
b100001 .
b10000000000000 *
b100000000 +
b100000000 $
b100000000 '
b1000 &
#141000
b10000000000000 !
b10000000000000 ,
b100001 .
b100000000000000 *
b1000000000 +
b1000000000 $
b1000000000 '
b1001 &
#142000
b100000000000000 !
b100000000000000 ,
b100001 .
b1000000000000000 *
b10000000000 +
b10000000000 $
b10000000000 '
b1010 &
#143000
b1000000000000000 !
b1000000000000000 ,
b100001 .
b10000000000000000 *
b100000000000 +
b100000000000 $
b100000000000 '
b1011 &
#144000
b10000000000000000 !
b10000000000000000 ,
b100001 .
b100000000000000000 *
b1000000000000 +
b1000000000000 $
b1000000000000 '
b1100 &
#145000
b100000000000000000 !
b100000000000000000 ,
b100001 .
b1000000000000000000 *
b10000000000000 +
b10000000000000 $
b10000000000000 '
b1101 &
#146000
b1000000000000000000 !
b1000000000000000000 ,
b100001 .
b10000000000000000000 *
b100000000000000 +
b100000000000000 $
b100000000000000 '
b1110 &
#147000
b10000000000000000000 !
b10000000000000000000 ,
b100001 .
b100000000000000000000 *
b1000000000000000 +
b1000000000000000 $
b1000000000000000 '
b1111 &
#148000
b100000000000000000000 !
b100000000000000000000 ,
b100001 .
b1000000000000000000000 *
b10000000000000000 +
b10000000000000000 $
b10000000000000000 '
b10000 &
#149000
b1000000000000000000000 !
b1000000000000000000000 ,
b100001 .
b10000000000000000000000 *
b100000000000000000 +
b100000000000000000 $
b100000000000000000 '
b10001 &
#150000
b10000000000000000000000 !
b10000000000000000000000 ,
b100001 .
b100000000000000000000000 *
b1000000000000000000 +
b1000000000000000000 $
b1000000000000000000 '
b10010 &
#151000
b100000000000000000000000 !
b100000000000000000000000 ,
b100001 .
b1000000000000000000000000 *
b10000000000000000000 +
b10000000000000000000 $
b10000000000000000000 '
b10011 &
#152000
b1000000000000000000000000 !
b1000000000000000000000000 ,
b100001 .
b10000000000000000000000000 *
b100000000000000000000 +
b100000000000000000000 $
b100000000000000000000 '
b10100 &
#153000
b10000000000000000000000000 !
b10000000000000000000000000 ,
b100001 .
b100000000000000000000000000 *
b1000000000000000000000 +
b1000000000000000000000 $
b1000000000000000000000 '
b10101 &
#154000
b100000000000000000000000000 !
b100000000000000000000000000 ,
b100001 .
b1000000000000000000000000000 *
b10000000000000000000000 +
b10000000000000000000000 $
b10000000000000000000000 '
b10110 &
#155000
b1000000000000000000000000000 !
b1000000000000000000000000000 ,
b100001 .
b10000000000000000000000000000 *
b100000000000000000000000 +
b100000000000000000000000 $
b100000000000000000000000 '
b10111 &
#156000
b10000000000000000000000000000 !
b10000000000000000000000000000 ,
b100001 .
b100000000000000000000000000000 *
b1000000000000000000000000 +
b1000000000000000000000000 $
b1000000000000000000000000 '
b11000 &
#157000
b100000000000000000000000000000 !
b100000000000000000000000000000 ,
b100001 .
b1000000000000000000000000000000 *
b10000000000000000000000000 +
b10000000000000000000000000 $
b10000000000000000000000000 '
b11001 &
#158000
b1000000000000000000000000000000 !
b1000000000000000000000000000000 ,
b100001 .
b10000000000000000000000000000000 *
b100000000000000000000000000 +
b100000000000000000000000000 $
b100000000000000000000000000 '
b11010 &
#159000
b10000000000000000000000000000000 !
b10000000000000000000000000000000 ,
b100001 .
b100000000000000000000000000000000 *
b1000000000000000000000000000 +
b1000000000000000000000000000 $
b1000000000000000000000000000 '
b11011 &
#160000
b100000000000000000000000000000000 !
b100000000000000000000000000000000 ,
b100001 .
b1000000000000000000000000000000000 *
b10000000000000000000000000000 +
b10000000000000000000000000000 $
b10000000000000000000000000000 '
b11100 &
#161000
b1000000000000000000000000000000000 !
b1000000000000000000000000000000000 ,
b100001 .
b10000000000000000000000000000000000 *
b100000000000000000000000000000 +
b100000000000000000000000000000 $
b100000000000000000000000000000 '
b11101 &
#162000
b10000000000000000000000000000000000 !
b10000000000000000000000000000000000 ,
b100001 .
b100000000000000000000000000000000000 *
b1000000000000000000000000000000 +
b1000000000000000000000000000000 $
b1000000000000000000000000000000 '
b11110 &
#163000
b111111111111111111111111111111100000000000000000000000000000000000 !
b111111111111111111111111111111100000000000000000000000000000000000 ,
b100001 .
b1111111111111111111111111111111000000000000000000000000000000000000 *
b110000000000000000000000000000000 +
b10000000000000000000000000000000 $
b10000000000000000000000000000000 '
b11111 &
#164000
b100000 &
#165000
b100000 !
b100000 ,
b100001 .
b1000000 *
b1 +
b100000 -
b1 $
b1 '
b0 &
b100000 #
b100000 (
b101 %
#166000
b1000000 !
b1000000 ,
b10000000 *
b100001 .
b10 +
b10 $
b10 '
b1 &
#167000
b10000000 !
b10000000 ,
b100001 .
b100000000 *
b100 +
b100 $
b100 '
b10 &
#168000
b100000000 !
b100000000 ,
b100001 .
b1000000000 *
b1000 +
b1000 $
b1000 '
b11 &
#169000
b1000000000 !
b1000000000 ,
b100001 .
b10000000000 *
b10000 +
b10000 $
b10000 '
b100 &
#170000
b10000000000 !
b10000000000 ,
b100001 .
b100000000000 *
b100000 +
b100000 $
b100000 '
b101 &
#171000
b100000000000 !
b100000000000 ,
b100001 .
b1000000000000 *
b1000000 +
b1000000 $
b1000000 '
b110 &
#172000
b1000000000000 !
b1000000000000 ,
b100001 .
b10000000000000 *
b10000000 +
b10000000 $
b10000000 '
b111 &
#173000
b10000000000000 !
b10000000000000 ,
b100001 .
b100000000000000 *
b100000000 +
b100000000 $
b100000000 '
b1000 &
#174000
b100000000000000 !
b100000000000000 ,
b100001 .
b1000000000000000 *
b1000000000 +
b1000000000 $
b1000000000 '
b1001 &
#175000
b1000000000000000 !
b1000000000000000 ,
b100001 .
b10000000000000000 *
b10000000000 +
b10000000000 $
b10000000000 '
b1010 &
#176000
b10000000000000000 !
b10000000000000000 ,
b100001 .
b100000000000000000 *
b100000000000 +
b100000000000 $
b100000000000 '
b1011 &
#177000
b100000000000000000 !
b100000000000000000 ,
b100001 .
b1000000000000000000 *
b1000000000000 +
b1000000000000 $
b1000000000000 '
b1100 &
#178000
b1000000000000000000 !
b1000000000000000000 ,
b100001 .
b10000000000000000000 *
b10000000000000 +
b10000000000000 $
b10000000000000 '
b1101 &
#179000
b10000000000000000000 !
b10000000000000000000 ,
b100001 .
b100000000000000000000 *
b100000000000000 +
b100000000000000 $
b100000000000000 '
b1110 &
#180000
b100000000000000000000 !
b100000000000000000000 ,
b100001 .
b1000000000000000000000 *
b1000000000000000 +
b1000000000000000 $
b1000000000000000 '
b1111 &
