assignment4/multiplier/bomu8.v
module bomu8 #(
    parameter n = 16
) (
    input  signed [n-1:0]  q,
    input  signed [n-1:0] m,
    output reg [2*(n+1)-1:0] p
);
integer i;
    reg signed [2*(n+1):0] acc;
    reg [n :0] qb , mb;
    always @(*) begin
        qb = {q[n-1] , q};
        mb = {m[n-1] , m};
        acc = { {(n+1){1'b0}}, qb, 1'b0 };
        for (i = 0; i < n+1; i = i + 1) begin
            case (acc[1:0])
                2'b01: acc[2*(n+1)-:n+1] = acc[2*(n+1)-:n+1] +  mb;
                2'b10: acc[2*(n+1)-:n+1] = acc[2*(n+1)-:n+1] -  mb;
                default: ;
            endcase
            acc = acc>>>1; 
        end
     p = acc[2*(n+1):1];
    end
endmodule

assignment4/multiplier/bomu8tb.v
`timescale 1ns/1ps

module bomu8tb;
    localparam n = 16;  
    reg [n-1:0] a , b;
    wire [2*(n+1)-1:0] m;

    bomu8 #(.n(n)) multiplier( a ,b , m);

    integer i = 0;
    integer j = 0;

    initial begin
        $dumpfile("bomu8v.vcd");
        $dumpvars(0 , bomu8tb);
        a =0;
        b =0;
        
        for (i  =0  ;i <n ; i = i+1 ) begin
                a = 2**i;
            for (j = 0; j<n; j = j+1) begin
                b = 2**j;
                #1;
            end
            #1;
        end
        $finish;
    end
endmodule

assignment4/multiplier/bomu8v.vcd
$date
	Sun Jun 15 17:07:01 2025
$end
$version
	Icarus Verilog
$end
$timescale
	1ps
$end
$scope module bomu8tb $end
$var wire 34 ! m [33:0] $end
$var parameter 32 " n $end
$var reg 16 # a [15:0] $end
$var reg 16 $ b [15:0] $end
$var integer 32 % i [31:0] $end
$var integer 32 & j [31:0] $end
$scope module multiplier $end
$var wire 16 ' m [15:0] $end
$var wire 16 ( q [15:0] $end
$var parameter 32 ) n $end
$var reg 35 * acc [34:0] $end
$var reg 17 + mb [16:0] $end
$var reg 34 , p [33:0] $end
$var reg 17 - qb [16:0] $end
$var integer 32 . i [31:0] $end
$upscope $end
$upscope $end
$enddefinitions $end
$comment Show the parameter values. $end
$dumpall
b10000 )
b10000 "
$end
#0
$dumpvars
b10001 .
b1 -
b1 ,
b1 +
b10 *
b1 (
b1 '
b0 &
b0 %
b1 $
b1 #
b1 !
$end
#1000
b10 !
b10 ,
b100 *
b10001 .
b10 +
b10 $
b10 '
b1 &
#2000
b100 !
b100 ,
b10001 .
b1000 *
b100 +
b100 $
b100 '
b10 &
#3000
b1000 !
b1000 ,
b10001 .
b10000 *
b1000 +
b1000 $
b1000 '
b11 &
#4000
b10000 !
b10000 ,
b10001 .
b100000 *
b10000 +
b10000 $
b10000 '
b100 &
#5000
b100000 !
b100000 ,
b10001 .
b1000000 *
b100000 +
b100000 $
b100000 '
b101 &
#6000
b1000000 !
b1000000 ,
b10001 .
b10000000 *
b1000000 +
b1000000 $
b1000000 '
b110 &
#7000
b10000000 !
b10000000 ,
b10001 .
b100000000 *
b10000000 +
b10000000 $
b10000000 '
b111 &
#8000
b100000000 !
b100000000 ,
b10001 .
b1000000000 *
b100000000 +
b100000000 $
b100000000 '
b1000 &
#9000
b1000000000 !
b1000000000 ,
b10001 .
b10000000000 *
b1000000000 +
b1000000000 $
b1000000000 '
b1001 &
#10000
b10000000000 !
b10000000000 ,
b10001 .
b100000000000 *
b10000000000 +
b10000000000 $
b10000000000 '
b1010 &
#11000
b100000000000 !
b100000000000 ,
b10001 .
b1000000000000 *
b100000000000 +
b100000000000 $
b100000000000 '
b1011 &
#12000
b1000000000000 !
b1000000000000 ,
b10001 .
b10000000000000 *
b1000000000000 +
b1000000000000 $
b1000000000000 '
b1100 &
#13000
b10000000000000 !
b10000000000000 ,
b10001 .
b100000000000000 *
b10000000000000 +
b10000000000000 $
b10000000000000 '
b1101 &
#14000
b100000000000000 !
b100000000000000 ,
b10001 .
b1000000000000000 *
b100000000000000 +
b100000000000000 $
b100000000000000 '
b1110 &
#15000
b1111111111111111111000000000000000 !
b1111111111111111111000000000000000 ,
b10001 .
b11111111111111111110000000000000000 *
b11000000000000000 +
b1000000000000000 $
b1000000000000000 '
b1111 &
#16000
b10000 &
#17000
b10 !
b10 ,
b10001 .
b100 *
b1 +
b10 -
b1 $
b1 '
b0 &
b10 #
b10 (
b1 %
#18000
b100 !
b100 ,
b1000 *
b10001 .
b10 +
b10 $
b10 '
b1 &
#19000
b1000 !
b1000 ,
b10001 .
b10000 *
b100 +
b100 $
b100 '
b10 &
#20000
b10000 !
b10000 ,
b10001 .
b100000 *
b1000 +
b1000 $
b1000 '
b11 &
#21000
b100000 !
b100000 ,
b10001 .
b1000000 *
b10000 +
b10000 $
b10000 '
b100 &
#22000
b1000000 !
b1000000 ,
b10001 .
b10000000 *
b100000 +
b100000 $
b100000 '
b101 &
#23000
b10000000 !
b10000000 ,
b10001 .
b100000000 *
b1000000 +
b1000000 $
b1000000 '
b110 &
#24000
b100000000 !
b100000000 ,
b10001 .
b1000000000 *
b10000000 +
b10000000 $
b10000000 '
b111 &
#25000
b1000000000 !
b1000000000 ,
b10001 .
b10000000000 *
b100000000 +
b100000000 $
b100000000 '
b1000 &
#26000
b10000000000 !
b10000000000 ,
b10001 .
b100000000000 *
b1000000000 +
b1000000000 $
b1000000000 '
b1001 &
#27000
b100000000000 !
b100000000000 ,
b10001 .
b1000000000000 *
b10000000000 +
b10000000000 $
b10000000000 '
b1010 &
#28000
b1000000000000 !
b1000000000000 ,
b10001 .
b10000000000000 *
b100000000000 +
b100000000000 $
b100000000000 '
b1011 &
#29000
b10000000000000 !
b10000000000000 ,
b10001 .
b100000000000000 *
b1000000000000 +
b1000000000000 $
b1000000000000 '
b1100 &
#30000
b100000000000000 !
b100000000000000 ,
b10001 .
b1000000000000000 *
b10000000000000 +
b10000000000000 $
b10000000000000 '
b1101 &
#31000
b1000000000000000 !
b1000000000000000 ,
b10001 .
b10000000000000000 *
b100000000000000 +
b100000000000000 $
b100000000000000 '
b1110 &
#32000
b1111111111111111110000000000000000 !
b1111111111111111110000000000000000 ,
b10001 .
b11111111111111111100000000000000000 *
b11000000000000000 +
b1000000000000000 $
b1000000000000000 '
b1111 &
#33000
b10000 &
#34000
b100 !
b100 ,
b10001 .
b1000 *
b1 +
b100 -
b1 $
b1 '
b0 &
b100 #
b100 (
b10 %
#35000
b1000 !
b1000 ,
b10000 *
b10001 .
b10 +
b10 $
b10 '
b1 &
#36000
b10000 !
b10000 ,
b10001 .
b100000 *
b100 +
b100 $
b100 '
b10 &
#37000
b100000 !
b100000 ,
b10001 .
b1000000 *
b1000 +
b1000 $
b1000 '
b11 &
#38000
b1000000 !
b1000000 ,
b10001 .
b10000000 *
b10000 +
b10000 $
b10000 '
b100 &
#39000
b10000000 !
b10000000 ,
b10001 .
b100000000 *
b100000 +
b100000 $
b100000 '
b101 &
#40000
b100000000 !
b100000000 ,
b10001 .
b1000000000 *
b1000000 +
b1000000 $
b1000000 '
b110 &
#41000
b1000000000 !
b1000000000 ,
b10001 .
b10000000000 *
b10000000 +
b10000000 $
b10000000 '
b111 &
#42000
b10000000000 !
b10000000000 ,
b10001 .
b100000000000 *
b100000000 +
b100000000 $
b100000000 '
b1000 &
#43000
b100000000000 !
b100000000000 ,
b10001 .
b1000000000000 *
b1000000000 +
b1000000000 $
b1000000000 '
b1001 &
#44000
b1000000000000 !
b1000000000000 ,
b10001 .
b10000000000000 *
b10000000000 +
b10000000000 $
b10000000000 '
b1010 &
#45000
b10000000000000 !
b10000000000000 ,
b10001 .
b100000000000000 *
b100000000000 +
b100000000000 $
b100000000000 '
b1011 &
#46000
b100000000000000 !
b100000000000000 ,
b10001 .
b1000000000000000 *
b1000000000000 +
b1000000000000 $
b1000000000000 '
b1100 &
#47000
b1000000000000000 !
b1000000000000000 ,
b10001 .
b10000000000000000 *
b10000000000000 +
b10000000000000 $
b10000000000000 '
b1101 &
#48000
b10000000000000000 !
b10000000000000000 ,
b10001 .
b100000000000000000 *
b100000000000000 +
b100000000000000 $
b100000000000000 '
b1110 &
#49000
b1111111111111111100000000000000000 !
b1111111111111111100000000000000000 ,
b10001 .
b11111111111111111000000000000000000 *
b11000000000000000 +
b1000000000000000 $
b1000000000000000 '
b1111 &
#50000
b10000 &
#51000
b1000 !
b1000 ,
b10001 .
b10000 *
b1 +
b1000 -
b1 $
b1 '
b0 &
b1000 #
b1000 (
b11 %
#52000
b10000 !
b10000 ,
b100000 *
b10001 .
b10 +
b10 $
b10 '
b1 &
#53000
b100000 !
b100000 ,
b10001 .
b1000000 *
b100 +
b100 $
b100 '
b10 &
#54000
b1000000 !
b1000000 ,
b10001 .
b10000000 *
b1000 +
b1000 $
b1000 '
b11 &
#55000
b10000000 !
b10000000 ,
b10001 .
b100000000 *
b10000 +
b10000 $
b10000 '
b100 &
#56000
b100000000 !
b100000000 ,
b10001 .
b1000000000 *
b100000 +
b100000 $
b100000 '
b101 &
#57000
b1000000000 !
b1000000000 ,
b10001 .
b10000000000 *
b1000000 +
b1000000 $
b1000000 '
b110 &
#58000
b10000000000 !
b10000000000 ,
b10001 .
b100000000000 *
b10000000 +
b10000000 $
b10000000 '
b111 &
#59000
b100000000000 !
b100000000000 ,
b10001 .
b1000000000000 *
b100000000 +
b100000000 $
b100000000 '
b1000 &
#60000
b1000000000000 !
b1000000000000 ,
b10001 .
b10000000000000 *
b1000000000 +
b1000000000 $
b1000000000 '
b1001 &
#61000
b10000000000000 !
b10000000000000 ,
b10001 .
b100000000000000 *
b10000000000 +
b10000000000 $
b10000000000 '
b1010 &
#62000
b100000000000000 !
b100000000000000 ,
b10001 .
b1000000000000000 *
b100000000000 +
b100000000000 $
b100000000000 '
b1011 &
#63000
b1000000000000000 !
b1000000000000000 ,
b10001 .
b10000000000000000 *
b1000000000000 +
b1000000000000 $
b1000000000000 '
b1100 &
#64000
b10000000000000000 !
b10000000000000000 ,
b10001 .
b100000000000000000 *
b10000000000000 +
b10000000000000 $
b10000000000000 '
b1101 &
#65000
b100000000000000000 !
b100000000000000000 ,
b10001 .
b1000000000000000000 *
b100000000000000 +
b100000000000000 $
b100000000000000 '
b1110 &
#66000
b1111111111111111000000000000000000 !
b1111111111111111000000000000000000 ,
b10001 .
b11111111111111110000000000000000000 *
b11000000000000000 +
b1000000000000000 $
b1000000000000000 '
b1111 &
#67000
b10000 &
#68000
b10000 !
b10000 ,
b10001 .
b100000 *
b1 +
b10000 -
b1 $
b1 '
b0 &
b10000 #
b10000 (
b100 %
#69000
b100000 !
b100000 ,
b1000000 *
b10001 .
b10 +
b10 $
b10 '
b1 &
#70000
b1000000 !
b1000000 ,
b10001 .
b10000000 *
b100 +
b100 $
b100 '
b10 &
#71000
b10000000 !
b10000000 ,
b10001 .
b100000000 *
b1000 +
b1000 $
b1000 '
b11 &
#72000
b100000000 !
b100000000 ,
b10001 .
b1000000000 *
b10000 +
b10000 $
b10000 '
b100 &
#73000
b1000000000 !
b1000000000 ,
b10001 .
b10000000000 *
b100000 +
b100000 $
b100000 '
b101 &
#74000
b10000000000 !
b10000000000 ,
b10001 .
b100000000000 *
b1000000 +
b1000000 $
b1000000 '
b110 &
#75000
b100000000000 !
b100000000000 ,
b10001 .
b1000000000000 *
b10000000 +
b10000000 $
b10000000 '
b111 &
#76000
b1000000000000 !
b1000000000000 ,
b10001 .
b10000000000000 *
b100000000 +
b100000000 $
b100000000 '
b1000 &
#77000
b10000000000000 !
b10000000000000 ,
b10001 .
b100000000000000 *
b1000000000 +
b1000000000 $
b1000000000 '
b1001 &
#78000
b100000000000000 !
b100000000000000 ,
b10001 .
b1000000000000000 *
b10000000000 +
b10000000000 $
b10000000000 '
b1010 &
#79000
b1000000000000000 !
b1000000000000000 ,
b10001 .
b10000000000000000 *
b100000000000 +
b100000000000 $
b100000000000 '
b1011 &
#80000
b10000000000000000 !
b10000000000000000 ,
b10001 .
b100000000000000000 *
b1000000000000 +
b1000000000000 $
b1000000000000 '
b1100 &
#81000
b100000000000000000 !
b100000000000000000 ,
b10001 .
b1000000000000000000 *
b10000000000000 +
b10000000000000 $
b10000000000000 '
b1101 &
#82000
b1000000000000000000 !
b1000000000000000000 ,
b10001 .
b10000000000000000000 *
b100000000000000 +
b100000000000000 $
b100000000000000 '
b1110 &
#83000
b1111111111111110000000000000000000 !
b1111111111111110000000000000000000 ,
b10001 .
b11111111111111100000000000000000000 *
b11000000000000000 +
b1000000000000000 $
b1000000000000000 '
b1111 &
#84000
b10000 &
#85000
b100000 !
b100000 ,
b10001 .
b1000000 *
b1 +
b100000 -
b1 $
b1 '
b0 &
b100000 #
b100000 (
b101 %
#86000
b1000000 !
b1000000 ,
b10000000 *
b10001 .
b10 +
b10 $
b10 '
b1 &
#87000
b10000000 !
b10000000 ,
b10001 .
b100000000 *
b100 +
b100 $
b100 '
b10 &
#88000
b100000000 !
b100000000 ,
b10001 .
b1000000000 *
b1000 +
b1000 $
b1000 '
b11 &
#89000
b1000000000 !
b1000000000 ,
b10001 .
b10000000000 *
b10000 +
b10000 $
b10000 '
b100 &
#90000
b10000000000 !
b10000000000 ,
b10001 .
b100000000000 *
b100000 +
b100000 $
b100000 '
b101 &
#91000
b100000000000 !
b100000000000 ,
b10001 .
b1000000000000 *
b1000000 +
b1000000 $
b1000000 '
b110 &
#92000
b1000000000000 !
b1000000000000 ,
b10001 .
b10000000000000 *
b10000000 +
b10000000 $
b10000000 '
b111 &
#93000
b10000000000000 !
b10000000000000 ,
b10001 .
b100000000000000 *
b100000000 +
b100000000 $
b100000000 '
b1000 &
#94000
b100000000000000 !
b100000000000000 ,
b10001 .
b1000000000000000 *
b1000000000 +
b1000000000 $
b1000000000 '
b1001 &
#95000
b1000000000000000 !
b1000000000000000 ,
b10001 .
b10000000000000000 *
b10000000000 +
b10000000000 $
b10000000000 '
b1010 &
#96000
b10000000000000000 !
b10000000000000000 ,
b10001 .
b100000000000000000 *
b100000000000 +
b100000000000 $
b100000000000 '
b1011 &
#97000
b100000000000000000 !
b100000000000000000 ,
b10001 .
b1000000000000000000 *
b1000000000000 +
b1000000000000 $
b1000000000000 '
b1100 &
#98000
b1000000000000000000 !
b1000000000000000000 ,
b10001 .
b10000000000000000000 *
b10000000000000 +
b10000000000000 $
b10000000000000 '
b1101 &
#99000
b10000000000000000000 !
b10000000000000000000 ,
b10001 .
b100000000000000000000 *
b100000000000000 +
b100000000000000 $
b100000000000000 '
b1110 &
#100000
b1111111111111100000000000000000000 !
b1111111111111100000000000000000000 ,
b10001 .
b11111111111111000000000000000000000 *
b11000000000000000 +
b1000000000000000 $
b1000000000000000 '
b1111 &
#101000
b10000 &
#102000
b1000000 !
b1000000 ,
b10001 .
b10000000 *
b1 +
b1000000 -
b1 $
b1 '
b0 &
b1000000 #
b1000000 (
b110 %
#103000
b10000000 !
b10000000 ,
b100000000 *
b10001 .
b10 +
b10 $
b10 '
b1 &
#104000
b100000000 !
b100000000 ,
b10001 .
b1000000000 *
b100 +
b100 $
b100 '
b10 &
#105000
b1000000000 !
b1000000000 ,
b10001 .
b10000000000 *
b1000 +
b1000 $
b1000 '
b11 &
#106000
b10000000000 !
b10000000000 ,
b10001 .
b100000000000 *
b10000 +
b10000 $
b10000 '
b100 &
#107000
b100000000000 !
b100000000000 ,
b10001 .
b1000000000000 *
b100000 +
b100000 $
b100000 '
b101 &
#108000
b1000000000000 !
b1000000000000 ,
b10001 .
b10000000000000 *
b1000000 +
b1000000 $
b1000000 '
b110 &
#109000
b10000000000000 !
b10000000000000 ,
b10001 .
b100000000000000 *
b10000000 +
b10000000 $
b10000000 '
b111 &
#110000
b100000000000000 !
b100000000000000 ,
b10001 .
b1000000000000000 *
b100000000 +
b100000000 $
b100000000 '
b1000 &
#111000
b1000000000000000 !
b1000000000000000 ,
b10001 .
b10000000000000000 *
b1000000000 +
b1000000000 $
b1000000000 '
b1001 &
#112000
b10000000000000000 !
b10000000000000000 ,
b10001 .
b100000000000000000 *
b10000000000 +
b10000000000 $
b10000000000 '
b1010 &
#113000
b100000000000000000 !
b100000000000000000 ,
b10001 .
b1000000000000000000 *
b100000000000 +
b100000000000 $
b100000000000 '
b1011 &
#114000
b1000000000000000000 !
b1000000000000000000 ,
b10001 .
b10000000000000000000 *
b1000000000000 +
b1000000000000 $
b1000000000000 '
b1100 &
#115000
b10000000000000000000 !
b10000000000000000000 ,
b10001 .
b100000000000000000000 *
b10000000000000 +
b10000000000000 $
b10000000000000 '
b1101 &
#116000
b100000000000000000000 !
b100000000000000000000 ,
b10001 .
b1000000000000000000000 *
b100000000000000 +
b100000000000000 $
b100000000000000 '
b1110 &
#117000
b1111111111111000000000000000000000 !
b1111111111111000000000000000000000 ,
b10001 .
b11111111111110000000000000000000000 *
b11000000000000000 +
b1000000000000000 $
b1000000000000000 '
b1111 &
#118000
b10000 &
#119000
b10000000 !
b10000000 ,
b10001 .
b100000000 *
b1 +
b10000000 -
b1 $
b1 '
b0 &
b10000000 #
b10000000 (
b111 %
#120000
b100000000 !
b100000000 ,
b1000000000 *
b10001 .
b10 +
b10 $
b10 '
b1 &
#121000
b1000000000 !
b1000000000 ,
b10001 .
b10000000000 *
b100 +
b100 $
b100 '
b10 &
#122000
b10000000000 !
b10000000000 ,
b10001 .
b100000000000 *
b1000 +
b1000 $
b1000 '
b11 &
#123000
b100000000000 !
b100000000000 ,
b10001 .
b1000000000000 *
b10000 +
b10000 $
b10000 '
b100 &
#124000
b1000000000000 !
b1000000000000 ,
b10001 .
b10000000000000 *
b100000 +
b100000 $
b100000 '
b101 &
#125000
b10000000000000 !
b10000000000000 ,
b10001 .
b100000000000000 *
b1000000 +
b1000000 $
b1000000 '
b110 &
#126000
b100000000000000 !
b100000000000000 ,
b10001 .
b1000000000000000 *
b10000000 +
b10000000 $
b10000000 '
b111 &
#127000
b1000000000000000 !
b1000000000000000 ,
b10001 .
b10000000000000000 *
b100000000 +
b100000000 $
b100000000 '
b1000 &
#128000
b10000000000000000 !
b10000000000000000 ,
b10001 .
b100000000000000000 *
b1000000000 +
b1000000000 $
b1000000000 '
b1001 &
#129000
b100000000000000000 !
b100000000000000000 ,
b10001 .
b1000000000000000000 *
b10000000000 +
b10000000000 $
b10000000000 '
b1010 &
#130000
b1000000000000000000 !
b1000000000000000000 ,
b10001 .
b10000000000000000000 *
b100000000000 +
b100000000000 $
b100000000000 '
b1011 &
#131000
b10000000000000000000 !
b10000000000000000000 ,
b10001 .
b100000000000000000000 *
b1000000000000 +
b1000000000000 $
b1000000000000 '
b1100 &
#132000
b100000000000000000000 !
b100000000000000000000 ,
b10001 .
b1000000000000000000000 *
b10000000000000 +
b10000000000000 $
b10000000000000 '
b1101 &
#133000
b1000000000000000000000 !
b1000000000000000000000 ,
b10001 .
b10000000000000000000000 *
b100000000000000 +
b100000000000000 $
b100000000000000 '
b1110 &
#134000
b1111111111110000000000000000000000 !
b1111111111110000000000000000000000 ,
b10001 .
b11111111111100000000000000000000000 *
b11000000000000000 +
b1000000000000000 $
b1000000000000000 '
b1111 &
#135000
b10000 &
#136000
b100000000 !
b100000000 ,
b10001 .
b1000000000 *
b1 +
b100000000 -
b1 $
b1 '
b0 &
b100000000 #
b100000000 (
b1000 %
#137000
b1000000000 !
b1000000000 ,
b10000000000 *
b10001 .
b10 +
b10 $
b10 '
b1 &
#138000
b10000000000 !
b10000000000 ,
b10001 .
b100000000000 *
b100 +
b100 $
b100 '
b10 &
#139000
b100000000000 !
b100000000000 ,
b10001 .
b1000000000000 *
b1000 +
b1000 $
b1000 '
b11 &
#140000
b1000000000000 !
b1000000000000 ,
b10001 .
b10000000000000 *
b10000 +
b10000 $
b10000 '
b100 &
#141000
b10000000000000 !
b10000000000000 ,
b10001 .
b100000000000000 *
b100000 +
b100000 $
b100000 '
b101 &
#142000
b100000000000000 !
b100000000000000 ,
b10001 .
b1000000000000000 *
b1000000 +
b1000000 $
b1000000 '
b110 &
#143000
b1000000000000000 !
b1000000000000000 ,
b10001 .
b10000000000000000 *
b10000000 +
b10000000 $
b10000000 '
b111 &
#144000
b10000000000000000 !
b10000000000000000 ,
b10001 .
b100000000000000000 *
b100000000 +
b100000000 $
b100000000 '
b1000 &
#145000
b100000000000000000 !
b100000000000000000 ,
b10001 .
b1000000000000000000 *
b1000000000 +
b1000000000 $
b1000000000 '
b1001 &
#146000
b1000000000000000000 !
b1000000000000000000 ,
b10001 .
b10000000000000000000 *
b10000000000 +
b10000000000 $
b10000000000 '
b1010 &
#147000
b10000000000000000000 !
b10000000000000000000 ,
b10001 .
b100000000000000000000 *
b100000000000 +
b100000000000 $
b100000000000 '
b1011 &
#148000
b100000000000000000000 !
b100000000000000000000 ,
b10001 .
b1000000000000000000000 *
b1000000000000 +
b1000000000000 $
b1000000000000 '
b1100 &
#149000
b1000000000000000000000 !
b1000000000000000000000 ,
b10001 .
b10000000000000000000000 *
b10000000000000 +
b10000000000000 $
b10000000000000 '
b1101 &
#150000
b10000000000000000000000 !
b10000000000000000000000 ,
b10001 .
b100000000000000000000000 *
b100000000000000 +
b100000000000000 $
b100000000000000 '
b1110 &
#151000
b1111111111100000000000000000000000 !
b1111111111100000000000000000000000 ,
b10001 .
b11111111111000000000000000000000000 *
b11000000000000000 +
b1000000000000000 $
b1000000000000000 '
b1111 &
#152000
b10000 &
#153000
b1000000000 !
b1000000000 ,
b10001 .
b10000000000 *
b1 +
b1000000000 -
b1 $
b1 '
b0 &
b1000000000 #
b1000000000 (
b1001 %
#154000
b10000000000 !
b10000000000 ,
b100000000000 *
b10001 .
b10 +
b10 $
b10 '
b1 &
#155000
b100000000000 !
b100000000000 ,
b10001 .
b1000000000000 *
b100 +
b100 $
b100 '
b10 &
#156000
b1000000000000 !
b1000000000000 ,
b10001 .
b10000000000000 *
b1000 +
b1000 $
b1000 '
b11 &
#157000
b10000000000000 !
b10000000000000 ,
b10001 .
b100000000000000 *
b10000 +
b10000 $
b10000 '
b100 &
#158000
b100000000000000 !
b100000000000000 ,
b10001 .
b1000000000000000 *
b100000 +
b100000 $
b100000 '
b101 &
#159000
b1000000000000000 !
b1000000000000000 ,
b10001 .
b10000000000000000 *
b1000000 +
b1000000 $
b1000000 '
b110 &
#160000
b10000000000000000 !
b10000000000000000 ,
b10001 .
b100000000000000000 *
b10000000 +
b10000000 $
b10000000 '
b111 &
#161000
b100000000000000000 !
b100000000000000000 ,
b10001 .
b1000000000000000000 *
b100000000 +
b100000000 $
b100000000 '
b1000 &
#162000
b1000000000000000000 !
b1000000000000000000 ,
b10001 .
b10000000000000000000 *
b1000000000 +
b1000000000 $
b1000000000 '
b1001 &
#163000
b10000000000000000000 !
b10000000000000000000 ,
b10001 .
b100000000000000000000 *
b10000000000 +
b10000000000 $
b10000000000 '
b1010 &
#164000
b100000000000000000000 !
b100000000000000000000 ,
b10001 .
b1000000000000000000000 *
b100000000000 +
b100000000000 $
b100000000000 '
b1011 &
#165000
b1000000000000000000000 !
b1000000000000000000000 ,
b10001 .
b10000000000000000000000 *
b1000000000000 +
b1000000000000 $
b1000000000000 '
b1100 &
#166000
b10000000000000000000000 !
b10000000000000000000000 ,
b10001 .
b100000000000000000000000 *
b10000000000000 +
b10000000000000 $
b10000000000000 '
b1101 &
#167000
b100000000000000000000000 !
b100000000000000000000000 ,
b10001 .
b1000000000000000000000000 *
b100000000000000 +
b100000000000000 $
b100000000000000 '
b1110 &
#168000
b1111111111000000000000000000000000 !
b1111111111000000000000000000000000 ,
b10001 .
b11111111110000000000000000000000000 *
b11000000000000000 +
b1000000000000000 $
b1000000000000000 '
b1111 &
#169000
b10000 &
#170000
b10000000000 !
b10000000000 ,
b10001 .
b100000000000 *
b1 +
b10000000000 -
b1 $
b1 '
b0 &
b10000000000 #
b10000000000 (
b1010 %
#171000
b100000000000 !
b100000000000 ,
b1000000000000 *
b10001 .
b10 +
b10 $
b10 '
b1 &
#172000
b1000000000000 !
b1000000000000 ,
b10001 .
b10000000000000 *
b100 +
b100 $
b100 '
b10 &
#173000
b10000000000000 !
b10000000000000 ,
b10001 .
b100000000000000 *
b1000 +
b1000 $
b1000 '
b11 &
#174000
b100000000000000 !
b100000000000000 ,
b10001 .
b1000000000000000 *
b10000 +
b10000 $
b10000 '
b100 &
#175000
b1000000000000000 !
b1000000000000000 ,
b10001 .
b10000000000000000 *
b100000 +
b100000 $
b100000 '
b101 &
#176000
b10000000000000000 !
b10000000000000000 ,
b10001 .
b100000000000000000 *
b1000000 +
b1000000 $
b1000000 '
b110 &
#177000
b100000000000000000 !
b100000000000000000 ,
b10001 .
b1000000000000000000 *
b10000000 +
b10000000 $
b10000000 '
b111 &
#178000
b1000000000000000000 !
b1000000000000000000 ,
b10001 .
b10000000000000000000 *
b100000000 +
b100000000 $
b100000000 '
b1000 &
#179000
b10000000000000000000 !
b10000000000000000000 ,
b10001 .
b100000000000000000000 *
b1000000000 +
b1000000000 $
b1000000000 '
b1001 &
#180000
b100000000000000000000 !
b100000000000000000000 ,
b10001 .
b1000000000000000000000 *
b10000000000 +
b10000000000 $
b10000000000 '
b1010 &
#181000
b1000000000000000000000 !
b1000000000000000000000 ,
b10001 .
b10000000000000000000000 *
b100000000000 +
b100000000000 $
b100000000000 '
b1011 &
#182000
b10000000000000000000000 !
b10000000000000000000000 ,
b10001 .
b100000000000000000000000 *
b1000000000000 +
b1000000000000 $
b1000000000000 '
b1100 &
#183000
b100000000000000000000000 !
b100000000000000000000000 ,
b10001 .
b1000000000000000000000000 *
b10000000000000 +
b10000000000000 $
b10000000000000 '
b1101 &
#184000
b1000000000000000000000000 !
b1000000000000000000000000 ,
b10001 .
b10000000000000000000000000 *
b100000000000000 +
b100000000000000 $
b100000000000000 '
b1110 &
#185000
b1111111110000000000000000000000000 !
b1111111110000000000000000000000000 ,
b10001 .
b11111111100000000000000000000000000 *
b11000000000000000 +
b1000000000000000 $
b1000000000000000 '
b1111 &
#186000
b10000 &
#187000
b100000000000 !
b100000000000 ,
b10001 .
b1000000000000 *
b1 +
b100000000000 -
b1 $
b1 '
b0 &
b100000000000 #
b100000000000 (
b1011 %
#188000
b1000000000000 !
b1000000000000 ,
b10000000000000 *
b10001 .
b10 +
b10 $
b10 '
b1 &
#189000
b10000000000000 !
b10000000000000 ,
b10001 .
b100000000000000 *
b100 +
b100 $
b100 '
b10 &
#190000
b100000000000000 !
b100000000000000 ,
b10001 .
b1000000000000000 *
b1000 +
b1000 $
b1000 '
b11 &
#191000
b1000000000000000 !
b1000000000000000 ,
b10001 .
b10000000000000000 *
b10000 +
b10000 $
b10000 '
b100 &
#192000
b10000000000000000 !
b10000000000000000 ,
b10001 .
b100000000000000000 *
b100000 +
b100000 $
b100000 '
b101 &
#193000
b100000000000000000 !
b100000000000000000 ,
b10001 .
b1000000000000000000 *
b1000000 +
b1000000 $
b1000000 '
b110 &
#194000
b1000000000000000000 !
b1000000000000000000 ,
b10001 .
b10000000000000000000 *
b10000000 +
b10000000 $
b10000000 '
b111 &
#195000
b10000000000000000000 !
b10000000000000000000 ,
b10001 .
b100000000000000000000 *
b100000000 +
b100000000 $
b100000000 '
b1000 &
#196000
b100000000000000000000 !
b100000000000000000000 ,
b10001 .
b1000000000000000000000 *
b1000000000 +
b1000000000 $
b1000000000 '
b1001 &
#197000
b1000000000000000000000 !
b1000000000000000000000 ,
b10001 .
b10000000000000000000000 *
b10000000000 +
b10000000000 $
b10000000000 '
b1010 &
#198000
b10000000000000000000000 !
b10000000000000000000000 ,
b10001 .
b100000000000000000000000 *
b100000000000 +
b100000000000 $
b100000000000 '
b1011 &
#199000
b100000000000000000000000 !
b100000000000000000000000 ,
b10001 .
b1000000000000000000000000 *
b1000000000000 +
b1000000000000 $
b1000000000000 '
b1100 &
#200000
b1000000000000000000000000 !
b1000000000000000000000000 ,
b10001 .
b10000000000000000000000000 *
b10000000000000 +
b10000000000000 $
b10000000000000 '
b1101 &
#201000
b10000000000000000000000000 !
b10000000000000000000000000 ,
b10001 .
b100000000000000000000000000 *
b100000000000000 +
b100000000000000 $
b100000000000000 '
b1110 &
#202000
b1111111100000000000000000000000000 !
b1111111100000000000000000000000000 ,
b10001 .
b11111111000000000000000000000000000 *
b11000000000000000 +
b1000000000000000 $
b1000000000000000 '
b1111 &
#203000
b10000 &
#204000
b1000000000000 !
b1000000000000 ,
b10001 .
b10000000000000 *
b1 +
b1000000000000 -
b1 $
b1 '
b0 &
b1000000000000 #
b1000000000000 (
b1100 %
#205000
b10000000000000 !
b10000000000000 ,
b100000000000000 *
b10001 .
b10 +
b10 $
b10 '
b1 &
#206000
b100000000000000 !
b100000000000000 ,
b10001 .
b1000000000000000 *
b100 +
b100 $
b100 '
b10 &
#207000
b1000000000000000 !
b1000000000000000 ,
b10001 .
b10000000000000000 *
b1000 +
b1000 $
b1000 '
b11 &
#208000
b10000000000000000 !
b10000000000000000 ,
b10001 .
b100000000000000000 *
b10000 +
b10000 $
b10000 '
b100 &
#209000
b100000000000000000 !
b100000000000000000 ,
b10001 .
b1000000000000000000 *
b100000 +
b100000 $
b100000 '
b101 &
#210000
b1000000000000000000 !
b1000000000000000000 ,
b10001 .
b10000000000000000000 *
b1000000 +
b1000000 $
b1000000 '
b110 &
#211000
b10000000000000000000 !
b10000000000000000000 ,
b10001 .
b100000000000000000000 *
b10000000 +
b10000000 $
b10000000 '
b111 &
#212000
b100000000000000000000 !
b100000000000000000000 ,
b10001 .
b1000000000000000000000 *
b100000000 +
b100000000 $
b100000000 '
b1000 &
#213000
b1000000000000000000000 !
b1000000000000000000000 ,
b10001 .
b10000000000000000000000 *
b1000000000 +
b1000000000 $
b1000000000 '
b1001 &
#214000
b10000000000000000000000 !
b10000000000000000000000 ,
b10001 .
b100000000000000000000000 *
b10000000000 +
b10000000000 $
b10000000000 '
b1010 &
