assignment4/funcamdtask/dec.v
module dec(
    input e,
    input [2:0] i,
    output reg [7:0] s
);
    task decoder;
    input [3:0] in;
    output [7:0] z;
    begin
        case(in)
            4'd0 : z = 8'b00000001;
            4'd1 : z = 8'b00000010;
            4'd2 : z = 8'b00000100;
            4'd3 : z = 8'b00001000;
            4'd4 : z = 8'b00010000;
            4'd5 : z = 8'b00100000;
            4'd6 : z = 8'b01000000;
            4'd7 : z = 8'b10000000;
            default : z = 8'b00000000;
        endcase
    end
    endtask

    always @(*) begin
        if(e)
            decoder(i, s);
        else
            s = 8'b00000000; // Default output when e is low
    end
endmodule

assignment4/funcamdtask/dectb.v
`timescale 1ns/1ps
module dectb;
    reg e;
    reg [2:0] s;
    wire [7:0] o;

    dec decoder ( e , s , o );
    integer j;
    initial begin
        $dumpfile("decv.vcd");
        $dumpvars(0, dectb);
        
        e = 1;
        for (j = 0; j < 8; j = j + 1) begin
            s = j[2:0];
            #1; 
        end
        
        
        e = 0;
        s = 3'b101; 
        #1;
        
        
        $finish;
    end
    endmodule

assignment4/funcamdtask/decv.vcd
$date
	Wed Jun 11 18:46:07 2025
$end
$version
	Icarus Verilog
$end
$timescale
	1ps
$end
$scope module dectb $end
$var wire 8 ! o [7:0] $end
$var reg 1 " e $end
$var reg 3 # s [2:0] $end
$var integer 32 $ j [31:0] $end
$scope module decoder $end
$var wire 1 " e $end
$var wire 3 % i [2:0] $end
$var reg 8 & s [7:0] $end
$scope task decoder $end
$var reg 4 ' in [3:0] $end
$var reg 8 ( z [7:0] $end
$upscope $end
$upscope $end
$upscope $end
$enddefinitions $end
$comment Show the parameter values. $end
$dumpall
$end
#0
$dumpvars
b1 (
b0 '
b1 &
b0 %
b0 $
b0 #
1"
b1 !
$end
#1000
b10 !
b10 &
b10 (
b1 '
b1 #
b1 %
b1 $
#2000
b100 !
b100 &
b100 (
b10 '
b10 #
b10 %
b10 $
#3000
b1000 !
b1000 &
b1000 (
b11 '
b11 #
b11 %
b11 $
#4000
b10000 !
b10000 &
b10000 (
b100 '
b100 #
b100 %
b100 $
#5000
b100000 !
b100000 &
b100000 (
b101 '
b101 #
b101 %
b101 $
#6000
b1000000 !
b1000000 &
b1000000 (
b110 '
b110 #
b110 %
b110 $
#7000
b10000000 !
b10000000 &
b10000000 (
b111 '
b111 #
b111 %
b111 $
#8000
b0 !
b0 &
b101 #
b101 %
0"
b1000 $
