assignment4/funcamdtask/dem.v
module dem(
    input e,
    input  i,
    input [3:0] s,
    output  reg [15:0] o
);
    function [15:0] demux;
        input i;
        input [3:0] s;
        begin
            demux = 16'b0;
            demux[s] = i;
        end
    endfunction

    always @(*) begin
        if (e)
            o = demux(i, s);
        else
            o = 16'b0;
    end
endmodule

assignment4/funcamdtask/demtb.v
`timescale 1ns/1ps  

module demtb;

    reg e;
    reg  i;
    reg [3:0] s;
    wire [15:0] o;

    dem demux( e ,i ,s ,o);
    integer j;
    initial begin
        $dumpfile("demv.vcd");
        $dumpvars(0, demtb);
        
        e = 1;
        for (j = 0; j < 16; j = j + 1) begin
            i = 1;
            s = j;
            #1; 
        end
        
        e = 0;
        i = 8'hff; 
        s = 3'b001;
        #1;
        
        $finish;
    end
endmodule

assignment4/funcamdtask/demv.vcd
$date
	Wed Jun 11 19:23:18 2025
$end
$version
	Icarus Verilog
$end
$timescale
	1ps
$end
$scope module demtb $end
$var wire 16 ! o [15:0] $end
$var reg 1 " e $end
$var reg 1 # i $end
$var reg 4 $ s [3:0] $end
$var integer 32 % j [31:0] $end
$scope module demux $end
$var wire 1 " e $end
$var wire 1 # i $end
$var wire 4 & s [3:0] $end
$var reg 16 ' o [15:0] $end
$scope function demux $end
$var reg 1 ( i $end
$var reg 4 ) s [3:0] $end
$upscope $end
$upscope $end
$upscope $end
$enddefinitions $end
$comment Show the parameter values. $end
$dumpall
$end
#0
$dumpvars
b0 )
1(
b1 '
b0 &
b0 %
b0 $
1#
1"
b1 !
$end
#1000
b10 !
b10 '
b1 )
b1 $
b1 &
b1 %
#2000
b100 !
b100 '
b10 )
b10 $
b10 &
b10 %
#3000
b1000 !
b1000 '
b11 )
b11 $
b11 &
b11 %
#4000
b10000 !
b10000 '
b100 )
b100 $
b100 &
b100 %
#5000
b100000 !
b100000 '
b101 )
b101 $
b101 &
b101 %
#6000
b1000000 !
b1000000 '
b110 )
b110 $
b110 &
b110 %
#7000
b10000000 !
b10000000 '
b111 )
b111 $
b111 &
b111 %
#8000
b100000000 !
b100000000 '
b1000 )
b1000 $
b1000 &
b1000 %
#9000
b1000000000 !
b1000000000 '
b1001 )
b1001 $
b1001 &
b1001 %
#10000
b10000000000 !
b10000000000 '
b1010 )
b1010 $
b1010 &
b1010 %
#11000
b100000000000 !
b100000000000 '
b1011 )
b1011 $
b1011 &
b1011 %
#12000
b1000000000000 !
b1000000000000 '
b1100 )
b1100 $
b1100 &
b1100 %
#13000
b10000000000000 !
b10000000000000 '
b1101 )
b1101 $
b1101 &
b1101 %
#14000
b100000000000000 !
b100000000000000 '
b1110 )
b1110 $
b1110 &
b1110 %
#15000
b1000000000000000 !
b1000000000000000 '
b1111 )
b1111 $
b1111 &
b1111 %
#16000
b0 !
b0 '
b1 $
b1 &
0"
b10000 %
