assignment4/funcamdtask/enc.v
module enc(
    input e,
    input [7:0] i,
    output reg [2:0] s
    );
    task encoder;
    input [7:0] in;
    output [3:0] z;
    begin
    
        casex(in)
        8'b1xxxxxxx : z = 3'd7;
        8'b01xxxxxx : z = 3'd6;
        8'b001xxxxx : z = 3'd5;
        8'b0001xxxx : z = 3'd4;
        8'b00001xxx : z = 3'd3;
        8'b000001xx : z = 3'd2;
        8'b0000001x : z = 3'd1;
        8'b00000001 : z = 3'd0;
        default :     z = 3'd0;
        endcase
        end
        endtask
        
        always @(*) begin
            if(e)
                encoder(i ,s);
            else
                s = 3'd0;
        end
endmodule

assignment4/funcamdtask/enctb.v
`timescale 1ns/1ps

module enctb;
    reg e;
    reg [7:0] i;
    wire [2:0] s;

    enc encoder ( e , i , s );
    integer j;
    initial begin
        $dumpfile("encv.vcd");
        $dumpvars(0, enctb);
        
        e = 1;
        for (j = 0; j < 256; j = j + 1) begin
            i = j[7:0];
            #1; 
        end
        
        
        e = 0;
        i = 8'b10101010; 
        #1;
        
        
        $finish;
    end
endmodule

assignment4/funcamdtask/encv.vcd
$date
	Wed Jun 11 18:11:31 2025
$end
$version
	Icarus Verilog
$end
$timescale
	1ps
$end
$scope module enctb $end
$var wire 3 ! s [2:0] $end
$var reg 1 " e $end
$var reg 8 # i [7:0] $end
$var integer 32 $ j [31:0] $end
$scope module encoder $end
$var wire 1 " e $end
$var wire 8 % i [7:0] $end
$var reg 3 & s [2:0] $end
$scope task encoder $end
$var reg 8 ' in [7:0] $end
$var reg 4 ( z [3:0] $end
$upscope $end
$upscope $end
$upscope $end
$enddefinitions $end
$comment Show the parameter values. $end
$dumpall
$end
#0
$dumpvars
b0 (
b0 '
b0 &
b0 %
b0 $
b0 #
1"
b0 !
$end
#1000
b1 '
b1 #
b1 %
b1 $
#2000
b1 !
b1 &
b1 (
b10 '
b10 #
b10 %
b10 $
#3000
b11 '
b11 #
b11 %
b11 $
#4000
b10 !
b10 &
b10 (
b100 '
b100 #
b100 %
b100 $
#5000
b101 '
b101 #
b101 %
b101 $
#6000
b110 '
b110 #
b110 %
b110 $
#7000
b111 '
b111 #
b111 %
b111 $
#8000
b11 !
b11 &
b11 (
b1000 '
b1000 #
b1000 %
b1000 $
#9000
b1001 '
b1001 #
b1001 %
b1001 $
#10000
b1010 '
b1010 #
b1010 %
b1010 $
#11000
b1011 '
b1011 #
b1011 %
b1011 $
#12000
b1100 '
b1100 #
b1100 %
b1100 $
#13000
b1101 '
b1101 #
b1101 %
b1101 $
#14000
b1110 '
b1110 #
b1110 %
b1110 $
#15000
b1111 '
b1111 #
b1111 %
b1111 $
#16000
b100 !
b100 &
b100 (
b10000 '
b10000 #
b10000 %
b10000 $
#17000
b10001 '
b10001 #
b10001 %
b10001 $
#18000
b10010 '
b10010 #
b10010 %
b10010 $
#19000
b10011 '
b10011 #
b10011 %
b10011 $
#20000
b10100 '
b10100 #
b10100 %
b10100 $
#21000
b10101 '
b10101 #
b10101 %
b10101 $
#22000
b10110 '
b10110 #
b10110 %
b10110 $
#23000
b10111 '
b10111 #
b10111 %
b10111 $
#24000
b11000 '
b11000 #
b11000 %
b11000 $
#25000
b11001 '
b11001 #
b11001 %
b11001 $
#26000
b11010 '
b11010 #
b11010 %
b11010 $
#27000
b11011 '
b11011 #
b11011 %
b11011 $
#28000
b11100 '
b11100 #
b11100 %
b11100 $
#29000
b11101 '
b11101 #
b11101 %
b11101 $
#30000
b11110 '
b11110 #
b11110 %
b11110 $
#31000
b11111 '
b11111 #
b11111 %
b11111 $
#32000
b101 !
b101 &
b101 (
b100000 '
b100000 #
b100000 %
b100000 $
#33000
b100001 '
b100001 #
b100001 %
b100001 $
#34000
b100010 '
b100010 #
b100010 %
b100010 $
#35000
b100011 '
b100011 #
b100011 %
b100011 $
#36000
b100100 '
b100100 #
b100100 %
b100100 $
#37000
b100101 '
b100101 #
b100101 %
b100101 $
#38000
b100110 '
b100110 #
b100110 %
b100110 $
#39000
b100111 '
b100111 #
b100111 %
b100111 $
#40000
b101000 '
b101000 #
b101000 %
b101000 $
#41000
b101001 '
b101001 #
b101001 %
b101001 $
#42000
b101010 '
b101010 #
b101010 %
b101010 $
#43000
b101011 '
b101011 #
b101011 %
b101011 $
#44000
b101100 '
b101100 #
b101100 %
b101100 $
#45000
b101101 '
b101101 #
b101101 %
b101101 $
#46000
b101110 '
b101110 #
b101110 %
b101110 $
#47000
b101111 '
b101111 #
b101111 %
b101111 $
#48000
b110000 '
b110000 #
b110000 %
b110000 $
#49000
b110001 '
b110001 #
b110001 %
b110001 $
#50000
b110010 '
b110010 #
b110010 %
b110010 $
#51000
b110011 '
b110011 #
b110011 %
b110011 $
#52000
b110100 '
b110100 #
b110100 %
b110100 $
#53000
b110101 '
b110101 #
b110101 %
b110101 $
#54000
b110110 '
b110110 #
b110110 %
b110110 $
#55000
b110111 '
b110111 #
b110111 %
b110111 $
#56000
b111000 '
b111000 #
b111000 %
b111000 $
#57000
b111001 '
b111001 #
b111001 %
b111001 $
#58000
b111010 '
b111010 #
b111010 %
b111010 $
#59000
b111011 '
b111011 #
b111011 %
b111011 $
#60000
b111100 '
b111100 #
b111100 %
b111100 $
#61000
b111101 '
b111101 #
b111101 %
b111101 $
#62000
b111110 '
b111110 #
b111110 %
b111110 $
#63000
b111111 '
b111111 #
b111111 %
b111111 $
#64000
b110 !
b110 &
b110 (
b1000000 '
b1000000 #
b1000000 %
b1000000 $
#65000
b1000001 '
b1000001 #
b1000001 %
b1000001 $
#66000
b1000010 '
b1000010 #
b1000010 %
b1000010 $
#67000
b1000011 '
b1000011 #
b1000011 %
b1000011 $
#68000
b1000100 '
b1000100 #
b1000100 %
b1000100 $
#69000
b1000101 '
b1000101 #
b1000101 %
b1000101 $
#70000
b1000110 '
b1000110 #
b1000110 %
b1000110 $
#71000
b1000111 '
b1000111 #
b1000111 %
b1000111 $
#72000
b1001000 '
b1001000 #
b1001000 %
b1001000 $
#73000
b1001001 '
b1001001 #
b1001001 %
b1001001 $
#74000
b1001010 '
b1001010 #
b1001010 %
b1001010 $
#75000
b1001011 '
b1001011 #
b1001011 %
b1001011 $
#76000
b1001100 '
b1001100 #
b1001100 %
b1001100 $
#77000
b1001101 '
b1001101 #
b1001101 %
b1001101 $
#78000
b1001110 '
b1001110 #
b1001110 %
b1001110 $
#79000
b1001111 '
b1001111 #
b1001111 %
b1001111 $
#80000
b1010000 '
b1010000 #
b1010000 %
b1010000 $
#81000
b1010001 '
b1010001 #
b1010001 %
b1010001 $
#82000
b1010010 '
b1010010 #
b1010010 %
b1010010 $
#83000
b1010011 '
b1010011 #
b1010011 %
b1010011 $
#84000
b1010100 '
b1010100 #
b1010100 %
b1010100 $
#85000
b1010101 '
b1010101 #
b1010101 %
b1010101 $
#86000
b1010110 '
b1010110 #
b1010110 %
b1010110 $
#87000
b1010111 '
b1010111 #
b1010111 %
b1010111 $
#88000
b1011000 '
b1011000 #
b1011000 %
b1011000 $
#89000
b1011001 '
b1011001 #
b1011001 %
b1011001 $
#90000
b1011010 '
b1011010 #
b1011010 %
b1011010 $
#91000
b1011011 '
b1011011 #
b1011011 %
b1011011 $
#92000
b1011100 '
b1011100 #
b1011100 %
b1011100 $
#93000
b1011101 '
b1011101 #
b1011101 %
b1011101 $
#94000
b1011110 '
b1011110 #
b1011110 %
b1011110 $
#95000
b1011111 '
b1011111 #
b1011111 %
b1011111 $
#96000
b1100000 '
b1100000 #
b1100000 %
b1100000 $
#97000
b1100001 '
b1100001 #
b1100001 %
b1100001 $
#98000
b1100010 '
b1100010 #
b1100010 %
b1100010 $
#99000
b1100011 '
b1100011 #
b1100011 %
b1100011 $
#100000
b1100100 '
b1100100 #
b1100100 %
b1100100 $
#101000
b1100101 '
b1100101 #
b1100101 %
b1100101 $
#102000
b1100110 '
b1100110 #
b1100110 %
b1100110 $
#103000
b1100111 '
b1100111 #
b1100111 %
b1100111 $
#104000
b1101000 '
b1101000 #
b1101000 %
b1101000 $
#105000
b1101001 '
b1101001 #
b1101001 %
b1101001 $
#106000
b1101010 '
b1101010 #
b1101010 %
b1101010 $
#107000
b1101011 '
b1101011 #
b1101011 %
b1101011 $
#108000
b1101100 '
b1101100 #
b1101100 %
b1101100 $
#109000
b1101101 '
b1101101 #
b1101101 %
b1101101 $
#110000
b1101110 '
b1101110 #
b1101110 %
b1101110 $
#111000
b1101111 '
b1101111 #
b1101111 %
b1101111 $
#112000
b1110000 '
b1110000 #
b1110000 %
b1110000 $
#113000
b1110001 '
b1110001 #
b1110001 %
b1110001 $
#114000
b1110010 '
b1110010 #
b1110010 %
b1110010 $
#115000
b1110011 '
b1110011 #
b1110011 %
b1110011 $
#116000
b1110100 '
b1110100 #
b1110100 %
b1110100 $
#117000
b1110101 '
b1110101 #
b1110101 %
b1110101 $
#118000
b1110110 '
b1110110 #
b1110110 %
b1110110 $
#119000
b1110111 '
b1110111 #
b1110111 %
b1110111 $
#120000
b1111000 '
b1111000 #
b1111000 %
b1111000 $
#121000
b1111001 '
b1111001 #
b1111001 %
b1111001 $
#122000
b1111010 '
b1111010 #
b1111010 %
b1111010 $
#123000
b1111011 '
b1111011 #
b1111011 %
b1111011 $
#124000
b1111100 '
b1111100 #
b1111100 %
b1111100 $
#125000
b1111101 '
b1111101 #
b1111101 %
b1111101 $
#126000
b1111110 '
b1111110 #
b1111110 %
b1111110 $
#127000
b1111111 '
b1111111 #
b1111111 %
b1111111 $
#128000
b111 !
b111 &
b111 (
b10000000 '
b10000000 #
b10000000 %
b10000000 $
#129000
b10000001 '
b10000001 #
b10000001 %
b10000001 $
#130000
b10000010 '
b10000010 #
b10000010 %
b10000010 $
#131000
b10000011 '
b10000011 #
b10000011 %
b10000011 $
#132000
b10000100 '
b10000100 #
b10000100 %
b10000100 $
#133000
b10000101 '
b10000101 #
b10000101 %
b10000101 $
#134000
b10000110 '
b10000110 #
b10000110 %
b10000110 $
#135000
b10000111 '
b10000111 #
b10000111 %
b10000111 $
#136000
b10001000 '
b10001000 #
b10001000 %
b10001000 $
#137000
b10001001 '
b10001001 #
b10001001 %
b10001001 $
#138000
b10001010 '
b10001010 #
b10001010 %
b10001010 $
#139000
b10001011 '
b10001011 #
b10001011 %
b10001011 $
#140000
b10001100 '
b10001100 #
b10001100 %
b10001100 $
#141000
b10001101 '
b10001101 #
b10001101 %
b10001101 $
#142000
b10001110 '
b10001110 #
b10001110 %
b10001110 $
#143000
b10001111 '
b10001111 #
b10001111 %
b10001111 $
#144000
b10010000 '
b10010000 #
b10010000 %
b10010000 $
#145000
b10010001 '
b10010001 #
b10010001 %
b10010001 $
#146000
b10010010 '
b10010010 #
b10010010 %
b10010010 $
#147000
b10010011 '
b10010011 #
b10010011 %
b10010011 $
#148000
b10010100 '
b10010100 #
b10010100 %
b10010100 $
#149000
b10010101 '
b10010101 #
b10010101 %
b10010101 $
#150000
b10010110 '
b10010110 #
b10010110 %
b10010110 $
#151000
b10010111 '
b10010111 #
b10010111 %
b10010111 $
#152000
b10011000 '
b10011000 #
b10011000 %
b10011000 $
#153000
b10011001 '
b10011001 #
b10011001 %
b10011001 $
#154000
b10011010 '
b10011010 #
b10011010 %
b10011010 $
#155000
b10011011 '
b10011011 #
b10011011 %
b10011011 $
#156000
b10011100 '
b10011100 #
b10011100 %
b10011100 $
#157000
b10011101 '
b10011101 #
b10011101 %
b10011101 $
#158000
b10011110 '
b10011110 #
b10011110 %
b10011110 $
#159000
b10011111 '
b10011111 #
b10011111 %
b10011111 $
#160000
b10100000 '
b10100000 #
b10100000 %
b10100000 $
#161000
b10100001 '
b10100001 #
b10100001 %
b10100001 $
#162000
b10100010 '
b10100010 #
b10100010 %
b10100010 $
#163000
b10100011 '
b10100011 #
b10100011 %
b10100011 $
#164000
b10100100 '
b10100100 #
b10100100 %
b10100100 $
#165000
b10100101 '
b10100101 #
b10100101 %
b10100101 $
#166000
b10100110 '
b10100110 #
b10100110 %
b10100110 $
#167000
b10100111 '
b10100111 #
b10100111 %
b10100111 $
#168000
b10101000 '
b10101000 #
b10101000 %
b10101000 $
#169000
b10101001 '
b10101001 #
b10101001 %
b10101001 $
#170000
b10101010 '
b10101010 #
b10101010 %
b10101010 $
#171000
b10101011 '
b10101011 #
b10101011 %
b10101011 $
#172000
b10101100 '
b10101100 #
b10101100 %
b10101100 $
#173000
b10101101 '
b10101101 #
b10101101 %
b10101101 $
#174000
b10101110 '
b10101110 #
b10101110 %
b10101110 $
#175000
b10101111 '
b10101111 #
b10101111 %
b10101111 $
#176000
b10110000 '
b10110000 #
b10110000 %
b10110000 $
#177000
b10110001 '
b10110001 #
b10110001 %
b10110001 $
#178000
b10110010 '
b10110010 #
b10110010 %
b10110010 $
#179000
b10110011 '
b10110011 #
b10110011 %
b10110011 $
#180000
b10110100 '
b10110100 #
b10110100 %
b10110100 $
#181000
b10110101 '
b10110101 #
b10110101 %
b10110101 $
#182000
b10110110 '
b10110110 #
b10110110 %
b10110110 $
#183000
b10110111 '
b10110111 #
b10110111 %
b10110111 $
#184000
b10111000 '
b10111000 #
b10111000 %
b10111000 $
#185000
b10111001 '
b10111001 #
b10111001 %
b10111001 $
#186000
b10111010 '
b10111010 #
b10111010 %
b10111010 $
#187000
b10111011 '
b10111011 #
b10111011 %
b10111011 $
#188000
b10111100 '
b10111100 #
b10111100 %
b10111100 $
#189000
b10111101 '
b10111101 #
b10111101 %
b10111101 $
#190000
b10111110 '
b10111110 #
b10111110 %
b10111110 $
#191000
b10111111 '
b10111111 #
b10111111 %
b10111111 $
#192000
b11000000 '
b11000000 #
b11000000 %
b11000000 $
#193000
b11000001 '
b11000001 #
b11000001 %
b11000001 $
#194000
b11000010 '
b11000010 #
b11000010 %
b11000010 $
#195000
b11000011 '
b11000011 #
b11000011 %
b11000011 $
#196000
b11000100 '
b11000100 #
b11000100 %
b11000100 $
#197000
b11000101 '
b11000101 #
b11000101 %
b11000101 $
#198000
b11000110 '
b11000110 #
b11000110 %
b11000110 $
#199000
b11000111 '
b11000111 #
b11000111 %
b11000111 $
#200000
b11001000 '
b11001000 #
b11001000 %
b11001000 $
#201000
b11001001 '
b11001001 #
b11001001 %
b11001001 $
#202000
b11001010 '
b11001010 #
b11001010 %
b11001010 $
#203000
b11001011 '
b11001011 #
b11001011 %
b11001011 $
#204000
b11001100 '
b11001100 #
b11001100 %
b11001100 $
#205000
b11001101 '
b11001101 #
b11001101 %
b11001101 $
#206000
b11001110 '
b11001110 #
b11001110 %
b11001110 $
#207000
b11001111 '
b11001111 #
b11001111 %
b11001111 $
#208000
b11010000 '
b11010000 #
b11010000 %
b11010000 $
#209000
b11010001 '
b11010001 #
b11010001 %
b11010001 $
#210000
b11010010 '
b11010010 #
b11010010 %
b11010010 $
#211000
b11010011 '
b11010011 #
b11010011 %
b11010011 $
#212000
b11010100 '
b11010100 #
b11010100 %
b11010100 $
#213000
b11010101 '
b11010101 #
b11010101 %
b11010101 $
#214000
b11010110 '
b11010110 #
b11010110 %
b11010110 $
#215000
b11010111 '
b11010111 #
b11010111 %
b11010111 $
#216000
b11011000 '
b11011000 #
b11011000 %
b11011000 $
#217000
b11011001 '
b11011001 #
b11011001 %
b11011001 $
#218000
b11011010 '
b11011010 #
b11011010 %
b11011010 $
#219000
b11011011 '
b11011011 #
b11011011 %
b11011011 $
#220000
b11011100 '
b11011100 #
b11011100 %
b11011100 $
#221000
b11011101 '
b11011101 #
b11011101 %
b11011101 $
#222000
b11011110 '
b11011110 #
b11011110 %
b11011110 $
#223000
b11011111 '
b11011111 #
b11011111 %
b11011111 $
#224000
b11100000 '
b11100000 #
b11100000 %
b11100000 $
#225000
b11100001 '
b11100001 #
b11100001 %
b11100001 $
#226000
b11100010 '
b11100010 #
b11100010 %
b11100010 $
#227000
b11100011 '
b11100011 #
b11100011 %
b11100011 $
#228000
b11100100 '
b11100100 #
b11100100 %
b11100100 $
#229000
b11100101 '
b11100101 #
b11100101 %
b11100101 $
#230000
b11100110 '
b11100110 #
b11100110 %
b11100110 $
#231000
b11100111 '
b11100111 #
b11100111 %
b11100111 $
#232000
b11101000 '
b11101000 #
b11101000 %
b11101000 $
#233000
b11101001 '
b11101001 #
b11101001 %
b11101001 $
#234000
b11101010 '
b11101010 #
b11101010 %
b11101010 $
#235000
b11101011 '
b11101011 #
b11101011 %
b11101011 $
#236000
b11101100 '
b11101100 #
b11101100 %
b11101100 $
#237000
b11101101 '
b11101101 #
b11101101 %
b11101101 $
#238000
b11101110 '
b11101110 #
b11101110 %
b11101110 $
#239000
b11101111 '
b11101111 #
b11101111 %
b11101111 $
#240000
b11110000 '
b11110000 #
b11110000 %
b11110000 $
#241000
b11110001 '
b11110001 #
b11110001 %
b11110001 $
#242000
b11110010 '
b11110010 #
b11110010 %
b11110010 $
#243000
b11110011 '
b11110011 #
b11110011 %
b11110011 $
#244000
b11110100 '
b11110100 #
b11110100 %
b11110100 $
#245000
b11110101 '
b11110101 #
b11110101 %
b11110101 $
#246000
b11110110 '
b11110110 #
b11110110 %
b11110110 $
#247000
b11110111 '
b11110111 #
b11110111 %
b11110111 $
#248000
b11111000 '
b11111000 #
b11111000 %
b11111000 $
#249000
b11111001 '
b11111001 #
b11111001 %
b11111001 $
#250000
b11111010 '
b11111010 #
b11111010 %
b11111010 $
#251000
b11111011 '
b11111011 #
b11111011 %
b11111011 $
#252000
b11111100 '
b11111100 #
b11111100 %
b11111100 $
#253000
b11111101 '
b11111101 #
b11111101 %
b11111101 $
#254000
b11111110 '
b11111110 #
b11111110 %
b11111110 $
#255000
b11111111 '
b11111111 #
b11111111 %
b11111111 $
#256000
b0 !
b0 &
b10101010 #
b10101010 %
0"
b100000000 $
