assignment4/funcamdtask/mux.v
module mux (
    input e,
    input [15:0] i,
    input [3:0] s,
    output reg  o
);
    function [0:0] mux;
        input [15:0] i;
        input [3:0] s;
        begin
            mux = i[s];
        end
    endfunction
    always @(*) begin
        if (e)
            o =  mux(i, s);
        else
            o = 1'b0;
    end
endmodule

assignment4/funcamdtask/muxtb.v
`timescale 1ns/1ps

module muxtb;

    reg e;
    reg [15:0] i;
    reg [3:0] s;
    wire o;

    mux mux( e ,i ,s ,o);
    integer z;
    initial begin
        $dumpfile("muxv.vcd");
        $dumpvars(0, muxtb);
        
        e = 1;
        for (z = 0; z < 16; z = z + 1) begin
            i = 1<<z;
            s = z;
            #1; 
        end
        
        e = 0;
        i = 16'hffff; 
        s = 4'b0001;
        #1;
        
        $finish;
    end
endmodule

assignment4/funcamdtask/muxv.vcd
$date
	Wed Jun 11 19:20:42 2025
$end
$version
	Icarus Verilog
$end
$timescale
	1ps
$end
$scope module muxtb $end
$var wire 1 ! o $end
$var reg 1 " e $end
$var reg 16 # i [15:0] $end
$var reg 4 $ s [3:0] $end
$var integer 32 % z [31:0] $end
$scope module mux $end
$var wire 1 " e $end
$var wire 16 & i [15:0] $end
$var wire 4 ' s [3:0] $end
$var reg 1 ! o $end
$scope function mux $end
$var reg 16 ( i [15:0] $end
$var reg 4 ) s [3:0] $end
$upscope $end
$upscope $end
$upscope $end
$enddefinitions $end
$comment Show the parameter values. $end
$dumpall
$end
#0
$dumpvars
b0 )
b1 (
b0 '
b1 &
b0 %
b0 $
b1 #
1"
1!
$end
#1000
b10 (
b1 )
b1 $
b1 '
b10 #
b10 &
b1 %
#2000
b100 (
b10 )
b10 $
b10 '
b100 #
b100 &
b10 %
#3000
b1000 (
b11 )
b11 $
b11 '
b1000 #
b1000 &
b11 %
#4000
b10000 (
b100 )
b100 $
b100 '
b10000 #
b10000 &
b100 %
#5000
b100000 (
b101 )
b101 $
b101 '
b100000 #
b100000 &
b101 %
#6000
b1000000 (
b110 )
b110 $
b110 '
b1000000 #
b1000000 &
b110 %
#7000
b10000000 (
b111 )
b111 $
b111 '
b10000000 #
b10000000 &
b111 %
#8000
b100000000 (
b1000 )
b1000 $
b1000 '
b100000000 #
b100000000 &
b1000 %
#9000
b1000000000 (
b1001 )
b1001 $
b1001 '
b1000000000 #
b1000000000 &
b1001 %
#10000
b10000000000 (
b1010 )
b1010 $
b1010 '
b10000000000 #
b10000000000 &
b1010 %
#11000
b100000000000 (
b1011 )
b1011 $
b1011 '
b100000000000 #
b100000000000 &
b1011 %
#12000
b1000000000000 (
b1100 )
b1100 $
b1100 '
b1000000000000 #
b1000000000000 &
b1100 %
#13000
b10000000000000 (
b1101 )
b1101 $
b1101 '
b10000000000000 #
b10000000000000 &
b1101 %
#14000
b100000000000000 (
b1110 )
b1110 $
b1110 '
b100000000000000 #
b100000000000000 &
b1110 %
#15000
b1000000000000000 (
b1111 )
b1111 $
b1111 '
b1000000000000000 #
b1000000000000000 &
b1111 %
#16000
0!
b1 $
b1 '
b1111111111111111 #
b1111111111111111 &
0"
b10000 %
