assignment3/demux/dem1xn.v
module dem1xn #(parameter N = 4) (
    input en,
    input i,
    input [$clog2(N)-1:0] s,
    output [N-1:0] y
);
    reg [N-1:0] x;
    always @(*)  begin
        x=0;
        if (en==1) begin
            x[s] = i;
        end else begin
            x[s] = 0;
        end
    end
    assign y =x;

endmodule

assignment3/demux/dem1xntb.v
`timescale 1ns/1ps
module dem1xntb;
    localparam N  = 16;
    reg en;
    reg i;
    reg [$clog2(N)-1:0] s ;
    wire [N-1:0] y;

    dem1xn #(.N(N)) demux(
        .en(en) , .i(i) , .s(s) , .y(y)
    );
    integer z;
    initial begin
        $dumpfile("dem1xnv.vcd");
        $dumpvars(0 , dem1xntb);
        for (z = 0; z<N ; z =z+1) begin
            en =1;
            s = z;
            i =1;
            #1;
            i =0;
            #1;
            en = 0;
            s =z;
            i =1;
            #1;
            i =0;
            #1;
        end
        $finish;
    end
endmodule

assignment3/demux/dem1xnv.vcd
$date
	Fri Jun 06 11:45:13 2025
$end
$version
	Icarus Verilog
$end
$timescale
	1ps
$end
$scope module dem1xntb $end
$var wire 16 ! y [15:0] $end
$var parameter 32 " N $end
$var reg 1 # en $end
$var reg 1 $ i $end
$var reg 4 % s [3:0] $end
$var integer 32 & z [31:0] $end
$scope module demux $end
$var wire 1 # en $end
$var wire 1 $ i $end
$var wire 4 ' s [3:0] $end
$var wire 16 ( y [15:0] $end
$var parameter 32 ) N $end
$var reg 16 * x [15:0] $end
$upscope $end
$upscope $end
$enddefinitions $end
$comment Show the parameter values. $end
$dumpall
b10000 )
b10000 "
$end
#0
$dumpvars
b1 *
b1 (
b0 '
b0 &
b0 %
1$
1#
b1 !
$end
#1000
b0 !
b0 (
b0 *
0$
#2000
1$
0#
#3000
0$
#4000
b10 !
b10 (
b10 *
1$
b1 %
b1 '
1#
b1 &
#5000
b0 !
b0 (
b0 *
0$
#6000
1$
0#
#7000
0$
#8000
b100 !
b100 (
b100 *
1$
b10 %
b10 '
1#
b10 &
#9000
b0 !
b0 (
b0 *
0$
#10000
1$
0#
#11000
0$
#12000
b1000 !
b1000 (
b1000 *
1$
b11 %
b11 '
1#
b11 &
#13000
b0 !
b0 (
b0 *
0$
#14000
1$
0#
#15000
0$
#16000
b10000 !
b10000 (
b10000 *
1$
b100 %
b100 '
1#
b100 &
#17000
b0 !
b0 (
b0 *
0$
#18000
1$
0#
#19000
0$
#20000
b100000 !
b100000 (
b100000 *
1$
b101 %
b101 '
1#
b101 &
#21000
b0 !
b0 (
b0 *
0$
#22000
1$
0#
#23000
0$
#24000
b1000000 !
b1000000 (
b1000000 *
1$
b110 %
b110 '
1#
b110 &
#25000
b0 !
b0 (
b0 *
0$
#26000
1$
0#
#27000
0$
#28000
b10000000 !
b10000000 (
b10000000 *
1$
b111 %
b111 '
1#
b111 &
#29000
b0 !
b0 (
b0 *
0$
#30000
1$
0#
#31000
0$
#32000
b100000000 !
b100000000 (
b100000000 *
1$
b1000 %
b1000 '
1#
b1000 &
#33000
b0 !
b0 (
b0 *
0$
#34000
1$
0#
#35000
0$
#36000
b1000000000 !
b1000000000 (
b1000000000 *
1$
b1001 %
b1001 '
1#
b1001 &
#37000
b0 !
b0 (
b0 *
0$
#38000
1$
0#
#39000
0$
#40000
b10000000000 !
b10000000000 (
b10000000000 *
1$
b1010 %
b1010 '
1#
b1010 &
#41000
b0 !
b0 (
b0 *
0$
#42000
1$
0#
#43000
0$
#44000
b100000000000 !
b100000000000 (
b100000000000 *
1$
b1011 %
b1011 '
1#
b1011 &
#45000
b0 !
b0 (
b0 *
0$
#46000
1$
0#
#47000
0$
#48000
b1000000000000 !
b1000000000000 (
b1000000000000 *
1$
b1100 %
b1100 '
1#
b1100 &
#49000
b0 !
b0 (
b0 *
0$
#50000
1$
0#
#51000
0$
#52000
b10000000000000 !
b10000000000000 (
b10000000000000 *
1$
b1101 %
b1101 '
1#
b1101 &
#53000
b0 !
b0 (
b0 *
0$
#54000
1$
0#
#55000
0$
#56000
b100000000000000 !
b100000000000000 (
b100000000000000 *
1$
b1110 %
b1110 '
1#
b1110 &
#57000
b0 !
b0 (
b0 *
0$
#58000
1$
0#
#59000
0$
#60000
b1000000000000000 !
b1000000000000000 (
b1000000000000000 *
1$
b1111 %
b1111 '
1#
b1111 &
#61000
b0 !
b0 (
b0 *
0$
#62000
1$
0#
#63000
0$
#64000
b10000 &
