assignment3/demux/dem1x4.v
module dem1x4(
    input en,
    input i,
    input [1:0] s,
    output [3:0] y
);

    reg [3:0] x;
    always @(*) begin
        x = 0;
        if (en == 1) begin
            x[s] = i;
        end else begin
            x[s] = 0;
        end
    end
    assign y =x;

endmodule

assignment3/demux/dem1x4tb.v
`timescale 1ns/1ps
module dem1x4tb;
    reg en;
    reg i;
    reg [1:0] s;
    wire [3:0] y;

    dem1x4 demux(
      .en(en) , .i(i) , .s(s) , .y(y)
    );
    integer z;

    initial begin
        $dumpfile("dem1x4v.vcd");
        $dumpvars(0 , dem1x4tb);
        for (z = 0; z<4; z = z+1) begin
            en = 1;
            s = z;
            i = 1;
            #1;
            en = 0;
            s = z;
            i = 1;
            #1;
        end
    $finish;
    end
endmodule

assignment3/demux/dem1x4v.vcd
$date
	Fri Jun 06 11:27:05 2025
$end
$version
	Icarus Verilog
$end
$timescale
	1ps
$end
$scope module dem1x4tb $end
$var wire 4 ! y [3:0] $end
$var reg 1 " en $end
$var reg 1 # i $end
$var reg 2 $ s [1:0] $end
$var integer 32 % z [31:0] $end
$scope module demux $end
$var wire 1 " en $end
$var wire 1 # i $end
$var wire 2 & s [1:0] $end
$var wire 4 ' y [3:0] $end
$var reg 4 ( x [3:0] $end
$upscope $end
$upscope $end
$enddefinitions $end
$comment Show the parameter values. $end
$dumpall
$end
#0
$dumpvars
b1 (
b1 '
b0 &
b0 %
b0 $
1#
1"
b1 !
$end
#1000
b0 !
b0 '
b0 (
0"
#2000
b10 !
b10 '
b10 (
b1 $
b1 &
1"
b1 %
#3000
b0 !
b0 '
b0 (
0"
#4000
b100 !
b100 '
b100 (
b10 $
b10 &
1"
b10 %
#5000
b0 !
b0 '
b0 (
0"
#6000
b1000 !
b1000 '
b1000 (
b11 $
b11 &
1"
b11 %
#7000
b0 !
b0 '
b0 (
0"
#8000
b100 %
